Workbook

Sheet Sheet1
A1: رقم السجل التجاري | B1: رقم العقد | C1: العميل | D1: Name of factories | E1: المدينة | F1: Mobile | G1: Phone | H1: Email | I1: Fax | J1: حالة العميل | K1: نوع الأرض | L1: حالة الإنشائية | M1: تاريخ البدء | N1: تاريخ الإنتهاء | O1: Area | P1: تاريخ إصدار السجل التجاري | Q1: الأنشطة الصناعية
A2: 1010239390 | B2: 801190 | C2: مصنع أسامة عبدالعزيز الدهيشي لهياكل السيارات | D2: Osama Abdul Aziz Al-Dahishi Factory for Car Bodies | E2: الخرج | F2: 0505450758 | G2: 0112416652 | H2: info@aldheeshi.com | I2: 0112440368 | J2: مفتوح | K2: صناعي | L2: منتج | M2: 2010-06-29 | N2: 2029-11-22 | O2: 10500 | P2: 2 | Q2: =VLOOKUP(B2,[1]Sheet1!$A$1:$F$6212,6,0) -> #N/A
A3: 1011000322 | B3: 805402 | C3: مصنع الجعيثن للصناعات الحديدية | D3: Al-Jeathen Factory for Steel Industries | E3: الخرج | F3: 0504270970 | G3: 0115500000 | H3: mubarak@aljeathen.com | I3: 0115510000 | J3: مفتوح | K3: صناعي | L3: لم يبدأ في التنفيذ | M3: 2014-11-16 | N3: 2034-04-12 | O3: 65818 | P3: 28546 | Q3: =VLOOKUP(B3,[1]Sheet1!$A$1:$F$6212,6,0) -> #N/A
A4: 1010402346 | B4: 805352 | C4: مصنع شركة الاتحاد الدوليه للصناعات المعدنية | D4: Al-Etihad International Co. Factory for Metal Industries | E4: الخرج | F4: 0594111120 | G4: 0114459027 | H4: vip_z55z@hotmail.com | I4: 0114459027 | J4: مفتوح | K4: صناعي | L4: متوقف عن الإنشاء | M4: 2014-11-03 | N4: 2034-03-30 | O4: 10484 | P4: 41662 | Q4: =VLOOKUP(B4,[1]Sheet1!$A$1:$F$6212,6,0) -> #N/A
A5: 1011022145 | B5: 805898 | C5: مصنع عبدالرحمن محمد الرويشد للمنتجات المعدنيه | D5: Abdel Rahman Mohamed Al-Ruwaished Factory for Metal Products | E5: الخرج | F5: 0553075709 | G5: 0115448339 | H5: rowish_acv@hotmail.com | I5: 0115453121 | J5: مفتوح | K5: صناعي | L5: متوقف عن الإنشاء | M5: 2015-02-24 | N5: 2034-07-21 | O5: 9322 | P5: 41837 | Q5: =VLOOKUP(B5,[1]Sheet1!$A$1:$F$6212,6,0) -> #N/A
A6: 1010225012 | B6: 804986 | C6: مصنع السعودية للأتوبيسات | D6: Saudi Bus Factory | E6: الرياض الأولى | F6: 0504488444 | G6: 0114484477 | H6: industry@owaidah.com.sa | I6: 0114469761 | J6: مفتوح | K6: صناعي | L6: منتج | M6: 2014-04-22 | N6: 2029-10-29 | O6: 8420 | P6: 39040 | Q6: =VLOOKUP(B6,[1]Sheet1!$A$1:$F$6212,6,0) -> #N/A
A7: 1010427174 | B7: 805522 | C7: هايل تريلور العربية السعودية المحدودة | D7: Saudi Arabia Hale Tralor Company Limited | E7: الرياض الثالثة | F7: 0535259069 | G7: 0535259069 | H7: smohammed@heiltrailer.com | I7: 0112187801 | J7: مفتوح | K7: مصنع جاهز | L7: منتج | M7: 2014-12-15 | N7: 2019-10-22 | O7: 2936 | P7: 41940 | Q7: =VLOOKUP(B7,[1]Sheet1!$A$1:$F$6212,6,0) -> #N/A
A8: 1010005675 | B8: 800357 | C8: مصنع المطرودي لهياكل السيارات | D8: Al-Matroudi Car Bodies Factory | E8: الرياض الثانية | F8: 0553222284 | G8: 0114981592 | H8: fahadsalah24@hotmail.com | I8: 0114980723 | J8: مفتوح | K8: صناعي | L8: منتج | M8: 2009-06-12 | N8: 2019-02-23 | O8: 16000 | P8: 2 | Q8: =VLOOKUP(B8,[1]Sheet1!$A$1:$F$6212,6,0) -> #N/A
A9: 4030086643 | B9: 30658 | C9: شركة الشمراني (مصنع مقطورات السحب والجر) | D9: Al-Shamrani company (Push-Pull Tractors Factory) | E9: جدة الأولى | F9: 0500006597 | G9: 0126378612 | H9: shamrany_jed@hotmail.com | I9: 0126080797 | J9: مفتوح | K9: صناعي | L9: منتج | M9: 2010-03-01 | N9: 2029-07-26 | O9: 11740 | P9: 33721 | Q9: =VLOOKUP(B9,[1]Sheet1!$A$1:$F$6212,6,0) -> #N/A
A10: 4030266121 | B10: 805014 | C10: مصنع إيثار لمعدات الإطفاء والسلامه | D10: Eysar Factory for Fire Extinguishing and Safety Equipment | E10: جدة الأولى | F10: 0582999999 | G10: 0126141667 | H10: faisal13456@gmail.com | I10: 0126141669 | J10: مفتوح | K10: صناعي | L10: منتج | M10: 2014-05-28 | N10: 2034-10-12 | O10: 7080 | P10: 41696 | Q10: =VLOOKUP(B10,[1]Sheet1!$A$1:$F$6212,6,0) -> #N/A
A11: 4030267606 | B11: 805102 | C11: مصتع مقطورات النامى | D11: Al-Namy Trailers Factory | E11: جدة الثالثة | F11: 0553444748 | G11: 0114713573 | H11: alnmi_99@hotmail.com | I11: 0114713573 | J11: مفتوح | K11: صناعي | L11: منتج | M11: 2014-07-09 | N11: 2033-12-04 | O11: 9000 | P11: 41718 | Q11: =VLOOKUP(B11,[1]Sheet1!$A$1:$F$6212,6,0) -> #N/A
A12: 4030154013 | B12: 803302 | C12: مصنع عبدالله محمد السعدي لانتاج هياكل المقطورات | D12: Abdullah Mohamed Al-Saadi Factory for Metal Industries | E12: جدة الثالثة | F12: 0555548989 | G12: 0126205050 | H12: f.m.aloufi@hotmail.com | I12: 026201059 | J12: مفتوح | K12: صناعي | L12: منتج | M12: 2012-10-13 | N12: 2032-03-09 | O12: 16890 | P12: 38413 | Q12: =VLOOKUP(B12,[1]Sheet1!$A$1:$F$6212,6,0) -> #N/A
A13: 4030137859 | B13: 803659 | C13: مصنع عبده زايد علي الشميري للصناعات المعدنية | D13: Abdo Zayed Ali Al-Shemeri Factory for Metal Industries | E13: جدة الثالثة | F13: 0505697584 | G13: 0126204915 | H13: alriyadh_consultant@yahoo.com | I13: 026204915 | J13: مفتوح | K13: صناعي | L13: مكتمل إنشائياً | M13: 2013-01-26 | N13: 2032-06-22 | O13: 9000 | P13: 37349 | Q13: =VLOOKUP(B13,[1]Sheet1!$A$1:$F$6212,6,0) -> #N/A
... A16: 1010111255 | B16: 801623 | C16: شركة المصنع السعودي لصناعات الصوف الصخري | D16: Saudi Rock Wool Factory | E16: الخرج | F16: 0509994555 | G16: 0112650034 | H16: eidi_sulaiman@sudirockwool.com | I16: 0112650089 | J16: مفتوح | K16: صناعي | L16: منتج | M16: 2011-01-19 | N16: 2030-06-15 | O16: 80455 | P16: 2 | Q16: =VLOOKUP(B16,[1]Sheet1!$A$1:$F$6212,6,0) -> #N/A
A17: 1010178847 | B17: 802891 | C17: مصنع أسلم أنصار أنصاري لانتاج اللحف والمخدات | D17: #N/A | E17: الخرج | F17: 0505491660 | G17: 0112985828 | H17: aansari5026@hotmail.com | I17: 0112985813 | J17: مفتوح | K17: صناعي | L17: متوقف عن الإنشاء | M17: 2012-04-12 | N17: 2030-11-08 | O17: 24115 | P17: 37451 | Q17: =VLOOKUP(B17,[1]Sheet1!$A$1:$F$6212,6,0) -> #N/A
A18: 1010301144 | B18: 802043 | C18: مصنع النسيج الإدريسي | D18: El-Idrissi Textile Co. | E18: الخرج | F18: 0552288390 | G18: 0114456608 | H18: im2006@yahoo.cpm | I18: 0114456608 | J18: مفتوح | K18: صناعي | L18: تجهيز خطوط الانتاج | M18: 2011-06-11 | N18: 2030-11-04 | O18: 5067 | P18: 2 | Q18: =VLOOKUP(B18,[1]Sheet1!$A$1:$F$6212,6,0) -> #N/A
A19: 1010280745 | B19: 801492 | C19: الشركة العربية لصناعة الأغطية والوسائد | D19: Arabian Company for Comforters and Pillows (ACCP) | E19: الرياض الثانية | F19: 0505405516 | G19: 0114982226 | H19: accp@satex.com.sa | I19: 0112411553 | J19: مفتوح | K19: صناعي | L19: منتج | M19: 2010-03-17 | N19: 2030-03-08 | O19: 7500 | P19: 2 | Q19: =VLOOKUP(B19,[1]Sheet1!$A$1:$F$6212,6,0) -> #N/A
A20: 1010083670 | B20: 20673 | C20: المصنع السعودي للشماغ | D20: Saudi Shemagh Factory | E20: الرياض الثانية | F20: 0509996786 | G20: 0114980558 | H20: alajlan2000@hotmail.com | I20: 0114980570 | J20: مفتوح | K20: صناعي | L20: منتج | M20: 1998-03-22 | N20: 2022-06-22 | O20: 22000 | P20: 2 | Q20: =VLOOKUP(B20,[1]Sheet1!$A$1:$F$6212,6,0) -> #N/A
A21: 1010142008 | B21: 20571 | C21: المصنع الوطني لخيوط البوليستر | D21: National Polyester Fiber Factory | E21: الرياض الثانية | F21: 0505559335 | G21: 0114982250 | H21: info@ayed-sa.com | I21: 0114982246 | J21: مفتوح | K21: صناعي | L21: منتج | M21: 1997-01-26 | N21: 2021-04-28 | O21: 2500 | P21: 2 | Q21: =VLOOKUP(B21,[1]Sheet1!$A$1:$F$6212,6,0) -> #N/A
A22: 1010073685 | B22: 800788 | C22: شركة العبداللطيف للاستثمار الصناعي | D22: Al-Abdullatif Industrial Investment Company | E22: الرياض الثانية | F22: 0505757403 | G22: 0112658888 | H22: jaber@carpets.com | I22: 0112659999 | J22: مفتوح | K22: صناعي | L22: منتج | M22: 2009-09-30 | N22: 2029-02-23 | O22: 90586 | P22: 32777 | Q22: =VLOOKUP(B22,[1]Sheet1!$A$1:$F$6212,6,0) -> #N/A
A23: 1010167895 | B23: 20561 | C23: شركة العبيكان للمنسوجات التقنية | D23: Obeikan Technical Fabrics Co. (OTF) | E23: الرياض الثانية | F23: 0541244376 | G23: 0112653533 | H23: zayed@obeikan.com.sa | I23: 0112653438 | J23: مفتوح | K23: صناعي | L23: منتج | M23: 1999-07-14 | N23: 2023-10-15 | O23: 16800 | P23: 36546 | Q23: =VLOOKUP(B23,[1]Sheet1!$A$1:$F$6212,6,0) -> #N/A
A24: 1010056407 | B24: 20437 | C24: شركة بادية للغزل والنسيج | D24: Badia Spinning & Weaving Co. | E24: الرياض الثانية | F24: 0509997013 | G24: 0112652156 | H24: info@badia.com.sa | I24: 0112652157 | J24: مفتوح | K24: صناعي | L24: منتج | M24: 2010-09-27 | N24: 2030-02-20 | O24: 11685 | P24: 31032 | Q24: =VLOOKUP(B24,[1]Sheet1!$A$1:$F$6212,6,0) -> #N/A
A25: 1010127521 | B25: 20733 | C25: شركة خلدون الصناعية (مصنع النسيج والتطريز) | D25: Khaldoun Industrial Co. (Weaving & embroidery Factory) | E25: الرياض الثانية | F25: 0505479526 | G25: 0114981410 | H25: khaldoon_factory@yahoo.com | I25: 0114981304 | J25: مفتوح | K25: صناعي | L25: منتج | M25: 1995-01-28 | N25: 2019-05-01 | O25: 3100 | P25: 34562 | Q25: =VLOOKUP(B25,[1]Sheet1!$A$1:$F$6212,6,0) -> #N/A
A26: 1010068363 | B26: 805460 | C26: شركة سافي الدولية المحدودة | D26: Safi Leather Factory | E26: الرياض الثانية | F26: 0504675308 | G26: 0112651591 | H26: safyleather@hotmail.com | I26: 0112651590 | J26: مفتوح | K26: صناعي | L26: منتج | M26: 2014-11-03 | N26: 2016-11-03 | O26: 10186 | P26: 2 | Q26: =VLOOKUP(B26,[1]Sheet1!$A$1:$F$6212,6,0) -> #N/A
A27: 1010163897 | B27: 290085 | C27: شركة مصنع أحمد محمد بخاري وشريكه للوسائد والشراشف | D27: Ahmed Mohammed Bukari & Partner Factory Company for Pillows and Bedspreads | E27: الرياض الثانية | F27: 0504494875 | G27: 0112653633 | H27: ama_bukhari@yahoo.com | I27: 0112653635 | J27: مفتوح | K27: صناعي | L27: منتج | M27: 2008-02-04 | N27: 2030-05-27 | O27: 4224 | P27: 2 | Q27: =VLOOKUP(B27,[1]Sheet1!$A$1:$F$6212,6,0) -> #N/A
A28: 1010046659 | B28: 20392 | C28: مصنع أديم للازياء الموحدة | D28: Adeem Uniforms Company | E28: الرياض الثانية | F28: 0504161615 | G28: 0114771803 | H28: adeemadeem@hotmail.com | I28: 0114767896 | J28: مفتوح | K28: صناعي | L28: منتج | M28: 2004-01-18 | N28: 2028-04-20 | O28: 6120 | P28: 30272 | Q28: =VLOOKUP(B28,[1]Sheet1!$A$1:$F$6212,6,0) -> #N/A
A29: 1010143752 | B29: 20707 | C29: مصنع الياف لأنتاج الملابس الجاهزة والعباءات | D29: Alyaf Readymade Garments and Gowns Manufacturing Factory | E29: الرياض الثانية | F29: 0505206475 | G29: 0114982962 | H29: alyafgorp@yahoo.com | I29: 0114986482 | J29: مفتوح | K29: صناعي | L29: منتج | M29: 2006-06-28 | N29: 2030-09-29 | O29: 1716 | P29: 2 | Q29: =VLOOKUP(B29,[1]Sheet1!$A$1:$F$6212,6,0) -> #N/A
... A39: 4650039414 | B39: 802588 | C39: مصنع طيبة للسجاد | D39: Tiba Carpet Factory | E39: المدينة المنورة | F39: 0507999111 | G39: 0148415321 | H39: teiba-carpet@hotmail.com | I39: 048415321 | J39: مفتوح | K39: صناعي | L39: تحت الإنشاء | M39: 2012-01-14 | N39: 2031-06-09 | O39: 9226 | P39: 39291 | Q39: =VLOOKUP(B39,[1]Sheet1!$A$1:$F$6212,6,0) -> #N/A
A40: 4650082887 | B40: 805212 | C40: مصنع عبدالعزيز عبدالرحمن العياف للمشالح والفراء | D40: #N/A | E40: المدينة المنورة | F40: 0555708449 | G40: 0127325591 | H40: ayyaf2014@hotmail.com | I40: 0127325294 | J40: مفتوح | K40: صناعي | L40: منتج | M40: 2014-08-26 | N40: 2034-01-20 | O40: 4637 | P40: 42970 | Q40: =VLOOKUP(B40,[1]Sheet1!$A$1:$F$6212,6,0) -> #N/A
A41: 4650042009 | B41: 801690 | C41: مصنع مشالح البدر | D41: Mashaleh Elbadr Factory | E41: المدينة المنورة | F41: 0555322001 | G41: 0148253089 | H41: info@m-albader.com | I41: 048253089 | J41: مفتوح | K41: صناعي | L41: منتج | M41: 2010-12-10 | N41: 2028-05-27 | O41: 4320 | P41: 2 | Q41: =VLOOKUP(B41,[1]Sheet1!$A$1:$F$6212,6,0) -> #N/A
A42: 4650038090 | B42: 801092 | C42: مصنع نور طيبة للأحذية | D42: Noor Tiba Shoes Factory | E42: المدينة المنورة | F42: 0503335822 | G42: 0148488260 | H42: basem822@windowslive.com | I42: 048488260 | J42: مفتوح | K42: صناعي | L42: تحت الإنشاء | M42: 2009-03-19 | N42: 2028-08-12 | O42: 4608 | P42: 39060 | Q42: =VLOOKUP(B42,[1]Sheet1!$A$1:$F$6212,6,0) -> #N/A
A43: 4650047267 | B43: 801266 | C43: مصنع يوسف على المغذوي لمنتجات البوليستارين | D43: Yusuf Ali Al-Maghzaoui Factory for Polystyrene Products | E43: المدينة المنورة | F43: 0505314894 | G43: 0148408070 | H43: yosf-fac@hotmail.com | I43: 048408070 | J43: مفتوح | K43: صناعي | L43: منتج | M43: 2010-07-18 | N43: 2029-12-11 | O43: 6912 | P43: 2 | Q43: =VLOOKUP(B43,[1]Sheet1!$A$1:$F$6212,6,0) -> #N/A
A44: 5855032186 | B44: 805238 | C44: مصنع تركيه علي ال فايع للملابس الجاهزه | D44: Turkieh Ali Al Faye Factory for Garments | E44: جازان | F44: 0554513131 | G44: 0172353309 | H44: h.saif.5@hotmail.com | I44: 0172354037 | J44: مفتوح | K44: صناعي | L44: لم يبدأ في التنفيذ | M44: 2014-09-17 | N44: 2034-02-11 | O44: 5477 | P44: 39924 | Q44: =VLOOKUP(B44,[1]Sheet1!$A$1:$F$6212,6,0) -> #N/A
A45: 4030095441 | B45: 30502 | C45: المصنع السعودي لتقنية الخيوط والنسيج | D45: Saudi Yarn and Knitting Technology Factory | E45: جدة الأولى | F45: 0557603734 | G45: 0126351731 | H45: syntech@nafa.net | I45: 0126380866 | J45: مفتوح | K45: صناعي | L45: منتج | M45: 1994-07-25 | N45: 2018-10-25 | O45: 50050 | P45: 34098 | Q45: =VLOOKUP(B45,[1]Sheet1!$A$1:$F$6212,6,0) -> #N/A
A46: 4030012551 | B46: 30605 | C46: شركة المصنع الوطني لعبوات البوليستايرين (ستايرينباك) | D46: National Factory for Polystyrene Packs Co. Ltd (StyrenPack) | E46: جدة الأولى | F46: 0505627479 | G46: 0126360517 | H46: styrene@styrenpack.com | I46: 0126378964 | J46: مفتوح | K46: صناعي | L46: منتج | M46: 2009-12-31 | N46: 2029-05-26 | O46: 8000 | P46: 28296 | Q46: =VLOOKUP(B46,[1]Sheet1!$A$1:$F$6212,6,0) -> #N/A
A47: 4030013068 | B47: 800523 | C47: شركة مصانع مفروشات ابو السعود | D47: Abul Saud Furniture Factories Co. | E47: جدة الأولى | F47: 0505608806 | G47: 0126373075 | H47: sales@abouseoud.com | I47: 026354451 | J47: مفتوح | K47: صناعي | L47: منتج | M47: 2009-05-13 | N47: 2019-01-23 | O47: 10000 | P47: 2 | Q47: =VLOOKUP(B47,[1]Sheet1!$A$1:$F$6212,6,0) -> #N/A
A48: 4030143934 | B48: 30976 | C48: شركة مصنع المستلزمات الحديثة للنسيج | D48: Modern Textile Supplies Factory Company | E48: جدة الأولى | F48: 0564061001 | G48: 0126365252 | H48: hadeel@asiig.com | I48: 0126367771 | J48: مفتوح | K48: صناعي | L48: منتج | M48: 2013-12-17 | N48: 2023-08-29 | O48: 8250 | P48: 1/1/53 0:00 | Q48: =VLOOKUP(B48,[1]Sheet1!$A$1:$F$6212,6,0) -> #N/A
A49: 4030115974 | B49: 30800 | C49: شركة مصنع جدة للخيوط الصناعية | D49: Jeddah Industrial Yarn Factory Co. | E49: جدة الأولى | F49: 0552121242 | G49: 0126370888 | H49: ali.katheri@al-sorayai.com | I49: 0126380813 | J49: مفتوح | K49: صناعي | L49: منتج | M49: 1997-03-02 | N49: 2020-06-14 | O49: 16875 | P49: 35028 | Q49: =VLOOKUP(B49,[1]Sheet1!$A$1:$F$6212,6,0) -> #N/A
A50: 4030115974 | B50: 30885 | C50: شركة مصنع جدة للخيوط الصناعية | D50: Jeddah Industrial Yarn Factory Co. | E50: جدة الأولى | F50: 0552121242 | G50: 0126370888 | H50: ali.katheri@al-sorayai.com | I50: 0126380813 | J50: مفتوح | K50: صناعي | L50: منتج | M50: 2006-07-03 | N50: 2030-10-04 | O50: 1125 | P50: 35028 | Q50: =VLOOKUP(B50,[1]Sheet1!$A$1:$F$6212,6,0) -> #N/A
A51: 4030115974 | B51: 30994 | C51: شركة مصنع جدة للخيوط الصناعية | D51: Jeddah Industrial Yarn Factory Co. | E51: جدة الأولى | F51: 0552121242 | G51: 0126370888 | H51: ali.katheri@al-sorayai.com | I51: 0126380813 | J51: مفتوح | K51: صناعي | L51: منتج | M51: 2006-08-20 | N51: 2030-11-21 | O51: 3720 | P51: 35028 | Q51: =VLOOKUP(B51,[1]Sheet1!$A$1:$F$6212,6,0) -> #N/A
A52: 4030115974 | B52: 804944 | C52: شركة مصنع جدة للخيوط الصناعية | D52: Jeddah Industrial Yarn Factory Co. | E52: جدة الأولى | F52: 0552121242 | G52: 0126370888 | H52: ali.katheri@al-sorayai.com | I52: 0126380813 | J52: مفتوح | K52: صناعي | L52: منتج | M52: 2014-04-10 | N52: 2029-10-17 | O52: 38422 | P52: 35028 | Q52: =VLOOKUP(B52,[1]Sheet1!$A$1:$F$6212,6,0) -> #N/A
A53: 4030055196 | B53: 30738 | C53: شركة مصنع جدة للنسيج البلاستيكي | D53: NULL | E53: جدة الأولى | F53: 0505693344 | G53: 0126379944 | H53: makool@moussallati.com | I53: 0126379944 | J53: مفتوح | K53: صناعي | L53: منتج | M53: 1998-01-12 | N53: 2022-04-14 | O53: 3750 | P53: 31731 | Q53: =VLOOKUP(B53,[1]Sheet1!$A$1:$F$6212,6,0) -> #N/A
A54: 0 | B54: 30574 | C54: مصنع الجزيرة للغزل والموكيت | D54: Al-Dawaa Medical Services Co. Ltd. | E54: جدة الأولى | F54: 0552121242 | G54: 0126081251 | H54: carpet2@al-sorayai.com | I54: 026081251 | J54: مفتوح | K54: صناعي | L54: منتج | M54: 2001-02-27 | N54: 2025-05-30 | O54: 18514 | P54: 1/1/53 0:00 | Q54: =VLOOKUP(B54,[1]Sheet1!$A$1:$F$6212,6,0) -> #N/A
A55: 4030133919 | B55: 30554 | C55: مصنع السريع للسجاد المحدودة | D55: Fast Carpet Ltd. Factory | E55: جدة الأولى | F55: 0552121242 | G55: 0126918222 | H55: ali.katheri@al-sorayai.com | I55: 0126974771 | J55: مفتوح | K55: صناعي | L55: منتج | M55: 1997-06-01 | N55: 2021-09-02 | O55: 5625 | P55: 37039 | Q55: =VLOOKUP(B55,[1]Sheet1!$A$1:$F$6212,6,0) -> #N/A
A56: 4030133919 | B56: 30680 | C56: مصنع السريع للسجاد المحدودة | D56: Fast Carpet Ltd. Factory | E56: جدة الأولى | F56: 0552121242 | G56: 0126918222 | H56: ali.katheri@al-sorayai.com | I56: 0126974771 | J56: مفتوح | K56: صناعي | L56: منتج | M56: 2010-01-22 | N56: 2029-06-18 | O56: 20196 | P56: 37039 | Q56: =VLOOKUP(B56,[1]Sheet1!$A$1:$F$6212,6,0) -> #N/A
A57: 4030133919 | B57: 30955 | C57: مصنع السريع للسجاد المحدودة | D57: Fast Carpet Ltd. Factory | E57: جدة الأولى | F57: 0552121242 | G57: 0126918222 | H57: ali.katheri@al-sorayai.com | I57: 0126974771 | J57: مفتوح | K57: صناعي | L57: منتج | M57: 2010-01-22 | N57: 2029-06-18 | O57: 15000 | P57: 37039 | Q57: =VLOOKUP(B57,[1]Sheet1!$A$1:$F$6212,6,0) -> #N/A
A58: 4030133919 | B58: 31111 | C58: مصنع السريع للسجاد المحدودة | D58: Fast Carpet Ltd. Factory | E58: جدة الأولى | F58: 0552121242 | G58: 0126918222 | H58: ali.katheri@al-sorayai.com | I58: 0126974771 | J58: مفتوح | K58: صناعي | L58: منتج | M58: 1994-01-25 | N58: 2018-04-29 | O58: 500 | P58: 37039 | Q58: =VLOOKUP(B58,[1]Sheet1!$A$1:$F$6212,6,0) -> #N/A
A59: 4030133919 | B59: 31216 | C59: مصنع السريع للسجاد المحدودة | D59: Fast Carpet Ltd. Factory | E59: جدة الأولى | F59: 0552121242 | G59: 0126918222 | H59: ali.katheri@al-sorayai.com | I59: 0126974771 | J59: مفتوح | K59: صناعي | L59: منتج | M59: 2006-03-06 | N59: 2030-06-06 | O59: 3357 | P59: 37039 | Q59: =VLOOKUP(B59,[1]Sheet1!$A$1:$F$6212,6,0) -> #N/A
A60: 4030133919 | B60: 280081 | C60: مصنع السريع للسجاد المحدودة | D60: Fast Carpet Ltd. Factory | E60: جدة الأولى | F60: 0552121242 | G60: 0126918222 | H60: ali.katheri@al-sorayai.com | I60: 0126974771 | J60: مفتوح | K60: صناعي | L60: منتج | M60: 2009-04-21 | N60: 2018-12-31 | O60: 5039 | P60: 37039 | Q60: =VLOOKUP(B60,[1]Sheet1!$A$1:$F$6212,6,0) -> #N/A
A61: 4030133919 | B61: 30387 | C61: مصنع السريع للنسيـج | D61: Fast Carpet Ltd. Factory | E61: جدة الأولى | F61: 0552121242 | G61: 0126913959 | H61: ali.katheri@al-sorayai.com | I61: 026913959 | J61: مفتوح | K61: صناعي | L61: منتج | M61: 1998-06-07 | N61: 2022-09-08 | O61: 11250 | P61: 37039 | Q61: =VLOOKUP(B61,[1]Sheet1!$A$1:$F$6212,6,0) -> #N/A
A62: 4030121778 | B62: 30010 | C62: مصنع المراتب والسرر الحديثة | D62: NULL | E62: جدة الأولى | F62: 0555642469 | G62: 0126356177 | H62: info@sleebhigh.com | I62: 0126356177 | J62: مفتوح | K62: صناعي | L62: منتج | M62: 2006-04-04 | N62: 2024-09-08 | O62: 7200 | P62: 1/1/53 0:00 | Q62: =VLOOKUP(B62,[1]Sheet1!$A$1:$F$6212,6,0) -> #N/A
A63: 4030121778 | B63: 31184 | C63: مصنع المراتب والسرر الحديثة | D63: NULL | E63: جدة الأولى | F63: 0555642469 | G63: 0126356177 | H63: info@sleebhigh.com | I63: 0126356177 | J63: مفتوح | K63: صناعي | L63: منتج | M63: 1999-11-14 | N63: 2024-02-15 | O63: 11578 | P63: 1/1/53 0:00 | Q63: =VLOOKUP(B63,[1]Sheet1!$A$1:$F$6212,6,0) -> #N/A
A64: 4030133566 | B64: 30288 | C64: مصنع تترا للسجاد واقمشة المفروشات | D64: Tetra Factory for Carpet And Furniture Fabrics | E64: جدة الأولى | F64: 0505450911 | G64: 0126080818 | H64: tatrarug@saudionline.com.sa | I64: 026080818 | J64: مفتوح | K64: صناعي | L64: منتج | M64: 2001-05-13 | N64: 2025-08-12 | O64: 5845 | P64: 2 | Q64: =VLOOKUP(B64,[1]Sheet1!$A$1:$F$6212,6,0) -> #N/A
A65: 4030133566 | B65: 30877 | C65: مصنع تترا للسجاد واقمشة المفروشات | D65: Tetra Factory for Carpet And Furniture Fabrics | E65: جدة الأولى | F65: 0505450911 | G65: 0126080818 | H65: tatrarug@saudionline.com.sa | I65: 026080818 | J65: مفتوح | K65: صناعي | L65: منتج | M65: 2006-08-08 | N65: 2030-11-09 | O65: 2375 | P65: 2 | Q65: =VLOOKUP(B65,[1]Sheet1!$A$1:$F$6212,6,0) -> #N/A
A66: 4030089309 | B66: 30462 | C66: مصنع دسار لصناعة النسيج | D66: Dessar Factory for Textile Industry | E66: جدة الأولى | F66: 0505611255 | G66: 0126380850 | H66: w.tayaran@desargroup.com | I66: 0126380815 | J66: مفتوح | K66: صناعي | L66: منتج | M66: 1995-02-20 | N66: 2019-05-25 | O66: 8477 | P66: 34030 | Q66: =VLOOKUP(B66,[1]Sheet1!$A$1:$F$6212,6,0) -> #N/A
A67: 4030195673 | B67: 805808 | C67: مصنع لبسي موضة للملابس الجاهزة | D67: Lebsy Moda Factory for Ready-made Garments | E67: جدة الأولى | F67: 0554656663 | G67: 0126080899 | H67: fnoonalmoda@gmail.com | I67: 026081005 | J67: مفتوح | K67: صناعي | L67: منتج | M67: 2015-01-27 | N67: 2034-06-23 | O67: 4275 | P67: 40174 | Q67: =VLOOKUP(B67,[1]Sheet1!$A$1:$F$6212,6,0) -> #N/A
A68: 4030121778 | B68: 30212 | C68: مصنع منتجات القطن والالياف الحديثة | D68: NULL | E68: جدة الأولى | F68: 0555591944 | G68: 0126380591 | H68: Info@sleephigh.com | I68: 026380591 | J68: مفتوح | K68: صناعي | L68: منتج | M68: 1998-06-30 | N68: 2022-10-01 | O68: 11250 | P68: 1/1/53 0:00 | Q68: =VLOOKUP(B68,[1]Sheet1!$A$1:$F$6212,6,0) -> #N/A
A69: 4030120764 | B69: 804447 | C69: مصنع جمال حسين حبتور للملابس | D69: Jamal Hussein Habtoor Garments Factory | E69: جدة الثالثة | F69: 0500005438 | G69: 0126481108 | H69: habtoor.est@hotmail.com | I69: 026481108 | J69: مفتوح | K69: صناعي | L69: متوقف عن الإنشاء | M69: 2013-11-07 | N69: 2033-04-04 | O69: 5016 | P69: 35441 | Q69: =VLOOKUP(B69,[1]Sheet1!$A$1:$F$6212,6,0) -> #N/A
A70: 4030204575 | B70: 804798 | C70: مصنع الفيحاء الحديث للجوارب | D70: Al-Fayhaa Modern Factory for Socks | E70: جدة الثالثة | F70: 0509837966 | G70: 0126510205 | H70: mazen.82@hotmail.com | I70: 0126573698 | J70: مفتوح | K70: صناعي | L70: متوقف عن الإنشاء | M70: 2014-02-27 | N70: 2033-07-24 | O70: 3600 | P70: 40449 | Q70: =VLOOKUP(B70,[1]Sheet1!$A$1:$F$6212,6,0) -> #N/A
A71: 4031066202 | B71: 805037 | C71: مصنع عطيه بتاع البشري للملابس الجاهزة | D71: Attia Betaa Al-Boshra Factory for Ready-made Garments | E71: جدة الثالثة | F71: 0544151516 | G71: 0125944299 | H71: aljeel01@gmail.com | I71: 0125944299 | J71: مفتوح | K71: صناعي | L71: متوقف عن الإنشاء | M71: 2014-06-08 | N71: 2033-11-02 | O71: 6000 | P71: 40909 | Q71: =VLOOKUP(B71,[1]Sheet1!$A$1:$F$6212,6,0) -> #N/A
A72: 4030278793 | B72: 805826 | C72: مصنع محمد سعيد كعكي للبوليستر والبياضات | D72: Mohamed Saeed Kaaki Factory for Polyester and Linens | E72: جدة الثالثة | F72: 0505646800 | G72: 0126082062 | H72: msskaki.polyester@gmail.com | I72: 0126082064 | J72: مفتوح | K72: صناعي | L72: متوقف عن الإنشاء | M72: 2015-01-28 | N72: 2034-06-24 | O72: 15071 | P72: 41960 | Q72: =VLOOKUP(B72,[1]Sheet1!$A$1:$F$6212,6,0) -> #N/A
A73: 4030137129 | B73: 805074 | C73: مصنع مروان محمود سعدون للزي الموحد | D73: Marwan Mahmoud Saadoun Factory for Uniforms | E73: جدة الثالثة | F73: 0504599103 | G73: 0126334979 | H73: magst100@hotmail.com | I73: 0126334984 | J73: مفتوح | K73: صناعي | L73: متوقف عن الإنشاء | M73: 2014-06-24 | N73: 2033-11-18 | O73: 4592 | P73: 37293 | Q73: =VLOOKUP(B73,[1]Sheet1!$A$1:$F$6212,6,0) -> #N/A
A74: 4030170606 | B74: 803833 | C74: شركة مصنع النسيج العربي | D74: Al-Kafela Factory for Manufacturing Media Advertising Panels | E74: جدة الثانية | F74: 0505646186 | G74: 0126926415 | H74: fahad@alnasseej.com | I74: 0126282692 | J74: مفتوح | K74: صناعي | L74: منتج | M74: 2013-03-19 | N74: 2032-08-14 | O74: 10028 | P74: 39260 | Q74: =VLOOKUP(B74,[1]Sheet1!$A$1:$F$6212,6,0) -> #N/A
A75: 4030135958 | B75: 801139 | C75: فرع شركة مصنع احمد محمد بخاري وشركاه للوسائد والشراشف | D75: Branch of Ahmed Mohamed Bukhari & Partners Co. Factory for Pillows and Bedspreads | E75: جدة الثانية | F75: 0504690815 | G75: 0126336692 | H75: alhuda_jed@yahoo.com | I75: 026336692 | J75: مفتوح | K75: صناعي | L75: منتج | M75: 2010-06-19 | N75: 2029-11-12 | O75: 14760 | P75: 2 | Q75: =VLOOKUP(B75,[1]Sheet1!$A$1:$F$6212,6,0) -> #N/A
A76: 4030137699 | B76: 801327 | C76: مصنع البركة لإنتاج اللحف والمخدات | D76: #N/A | E76: جدة الثانية | F76: 0505678648 | G76: 0126085052 | H76: albarakah111@hotmail.com | I76: 026085052 | J76: مفتوح | K76: صناعي | L76: منتج | M76: 2010-08-17 | N76: 2030-01-10 | O76: 14753 | P76: 37341 | Q76: =VLOOKUP(B76,[1]Sheet1!$A$1:$F$6212,6,0) -> #N/A
A77: 4030142072 | B77: 802177 | C77: مصنع محمد مناف عبد الستار ابراهيم للبوليستر واللحف والمخدات | D77: NULL | E77: جدة الثانية | F77: 0504325712 | G77: 0126379965 | H77: saadmunaf7@hotmail.com | I77: 026379965 | J77: مفتوح | K77: صناعي | L77: منتج | M77: 2011-07-11 | N77: 2030-11-08 | O77: 6744 | P77: 37698 | Q77: =VLOOKUP(B77,[1]Sheet1!$A$1:$F$6212,6,0) -> #N/A
A78: 5855031903 | B78: 802317 | C78: مصنع قداح علي الشبلي للملابس الجاهزة | D78: Qaddah Ali Al-Shibli Factory for Ready-made Garments | E78: عسيـــر | F78: 0500855455 | G78: 0172505050 | H78: alshebli100@hotmail.com | I78: 0172500000 | J78: مفتوح | K78: صناعي | L78: متوقف عن الإنتاج | M78: 2011-09-18 | N78: 2031-02-11 | O78: 5076 | P78: 39883 | Q78: =VLOOKUP(B78,[1]Sheet1!$A$1:$F$6212,6,0) -> #N/A
A79: 4031008300 | B79: 60011 | C79: مصنع شركة النسيج والملابس الجاهزة | D79: Textile & Readymade Garments Co. Factory | E79: مكة المكرمة | F79: 0505523744 | G79: 0125204553 | H79: info@saudithobe.com | I79: 025204553 | J79: مفتوح | K79: صناعي | L79: منتج | M79: 2003-06-21 | N79: 2027-09-21 | O79: 10368 | P79: 1/1/53 0:00 | Q79: =VLOOKUP(B79,[1]Sheet1!$A$1:$F$6212,6,0) -> #N/A
A80: 1010245946 | B80: 804804 | C80: مصنع شركة تقنية الطرق للأسفلت المحسن | D80: Road Technology co. factory for Enhanced Asphalt | E80: الباحة | F80: 0533002844 | G80: 0114980888 | H80: yousef.alrashid@redanational.com | I80: 0114980619 | J80: مفتوح | K80: صناعي | L80: اعتماد المخططات | M80: 2014-03-03 | N80: 2033-07-29 | O80: 10428 | P80: 39517 | Q80: =VLOOKUP(B80,[1]Sheet1!$A$1:$F$6212,6,0) -> #N/A
A81: 1010347159 | B81: 804782 | C81: المصنع السعودي لإنتاج زيوت المحركات المعاد تكريرها | D81: Saudi Factory for the Production of Re-Refined Motor Oils | E81: الخرج | F81: 0505440509 | G81: 0112445016 | H81: saud_sa99@hotmail.com | I81: 0112445016 | J81: مفتوح | K81: صناعي | L81: متوقف عن الإنتاج | M81: 2014-02-23 | N81: 2033-07-19 | O81: 5331 | P81: 2 | Q81: =VLOOKUP(B81,[1]Sheet1!$A$1:$F$6212,6,0) -> #N/A
A82: 1010298424 | B82: 805354 | C82: شركة مصنع بترول ناس لانتاج واعادة تكرير الزيوت | D82: Petrol Nas Factory co. for producing and re-refining oil | E82: الخرج | F82: 0504447760 | G82: 0114998888 | H82: abdu03466@gmail.com | I82: 014998888 | J82: مفتوح | K82: صناعي | L82: متوقف عن الإنشاء | M82: 2014-11-03 | N82: 2034-03-30 | O82: 8731 | P82: 40523 | Q82: =VLOOKUP(B82,[1]Sheet1!$A$1:$F$6212,6,0) -> #N/A
A83: 1010341150 | B83: 803135 | C83: مصنع احمد علي الغامدي لزيوت المحركات | D83: Ahmed Ali Al-Ghamdi Factory for Engine Oils | E83: الخرج | F83: 0554124744 | G83: 0114776025 | H83: ads_22sd@hotmail.com | I83: 0114776025 | J83: مفتوح | K83: صناعي | L83: منتج | M83: 2012-07-31 | N83: 2030-11-08 | O83: 4496 | P83: 41065 | Q83: =VLOOKUP(B83,[1]Sheet1!$A$1:$F$6212,6,0) -> #N/A
A84: 1011020927 | B84: 804913 | C84: مصنع الزيوت ومواد التشحيم الموثوقة للكيماويات | D84: Reliable Oils and Lubricants Factory for Chemicals | E84: الخرج | F84: 0505297776 | G84: 0114191741 | H84: upc@upcmails.com | I84: 0114191747 | J84: مفتوح | K84: صناعي | L84: تجهيز خطوط الانتاج | M84: 2014-04-06 | N84: 2028-10-23 | O84: 19981 | P84: 41631 | Q84: =VLOOKUP(B84,[1]Sheet1!$A$1:$F$6212,6,0) -> #N/A
A85: 1011014701 | B85: 802728 | C85: مصنع الشركة السعودية للزيوت | D85: Saudi Oils Company Factory | E85: الخرج | F85: 0504242448 | G85: 0112444424 | H85: hkiic1261@hotmail.com | I85: 0112382593 | J85: مفتوح | K85: صناعي | L85: منتج | M85: 2012-02-25 | N85: 2030-11-08 | O85: 9004 | P85: 40601 | Q85: =VLOOKUP(B85,[1]Sheet1!$A$1:$F$6212,6,0) -> #N/A
A86: 1010289361 | B86: 803662 | C86: مصنع خالد عبدالعزيز الزير لإعادة تكرير الزيوت المستعملة | D86: Khaled Abdulaziz Al-Zir Factory for Re-refining Used Oils | E86: الخرج | F86: 0500040576 | G86: 0114647686 | H86: egabcenter@gmail.com | I86: 0114629181 | J86: مفتوح | K86: صناعي | L86: تحت الإنشاء | M86: 2013-01-28 | N86: 2032-06-23 | O86: 6744 | P86: 40334 | Q86: =VLOOKUP(B86,[1]Sheet1!$A$1:$F$6212,6,0) -> #N/A
A87: 1011016373 | B87: 802988 | C87: مصنع رواسي العاصمة لزيوت التشحيم والمنتجات الاسفلتية | D87: Rawasi Al-Assema Factory for Lubricants and Asphalt Products | E87: الخرج | F87: 0550070407 | G87: 0112428865 | H87: X.tarat.x@hotmail.com | I87: 0112428899 | J87: مفتوح | K87: صناعي | L87: تحت الإنشاء | M87: 2012-05-26 | N87: 2030-11-08 | O87: 8992 | P87: 40924 | Q87: =VLOOKUP(B87,[1]Sheet1!$A$1:$F$6212,6,0) -> #N/A
A88: 1011015512 | B88: 802563 | C88: مصنع زيوت الرياض | D88: Riyadh Oils Factory | E88: الخرج | F88: 0505474668 | G88: 0112070215 | H88: roextco@hotmail.com | I88: 0112071019 | J88: مفتوح | K88: صناعي | L88: منتج | M88: 2012-01-04 | N88: 2031-05-30 | O88: 5334 | P88: 40804 | Q88: =VLOOKUP(B88,[1]Sheet1!$A$1:$F$6212,6,0) -> #N/A
A89: 1011015512 | B89: 800867 | C89: مصنع زيوت الرياض | D89: Riyadh Oils Factory | E89: الخرج | F89: 0505474668 | G89: 0112075324 | H89: roextco@hotmail.com | I89: 0112071019 | J89: مفتوح | K89: صناعي | L89: منتج | M89: 2010-02-08 | N89: 2029-07-05 | O89: 5331 | P89: 2 | Q89: =VLOOKUP(B89,[1]Sheet1!$A$1:$F$6212,6,0) -> #N/A
A90: 1010421621 | B90: 805499 | C90: مصنع سما الحرية لخلط وتعبئة الزيوت والشحوم | D90: Sama Al-Horia Factory for Mixing and Packing Oils & Greases | E90: الخرج | F90: 0559610400 | G90: 0112570815 | H90: hamadafiras@yahoo.com | I90: 0112572882 | J90: مفتوح | K90: صناعي | L90: تجهيز خطوط الانتاج | M90: 2014-12-09 | N90: 2034-05-06 | O90: 8999 | P90: 41865 | Q90: =VLOOKUP(B90,[1]Sheet1!$A$1:$F$6212,6,0) -> #N/A
A91: 1011016629 | B91: 802964 | C91: مصنع سيف عايد المطرفي للمشتقات البترولية | D91: Saif Ayed Al-Mautrofi Factory for Petroleum Derivatives | E91: الخرج | F91: 0542288188 | G91: 0115455861 | H91: saif_1411@hotmail.com | I91: 0115457445 | J91: مفتوح | K91: صناعي | L91: منتج | M91: 2012-05-14 | N91: 2031-10-09 | O91: 10725 | P91: 40951 | Q91: =VLOOKUP(B91,[1]Sheet1!$A$1:$F$6212,6,0) -> #N/A
... A94: 1010227924 | B94: 801834 | C94: مصنع قاعدة التقنية لتدوير للزيوت | D94: Qaidat Al-Teknia Factory for Oils Recycling | E94: الخرج | F94: 0555421066 | G94: 0114732927 | H94: ys.stlop@gmail.com | I94: 0114733837 | J94: مفتوح | K94: صناعي | L94: تحت الإنشاء | M94: 2011-03-20 | N94: 2030-08-14 | O94: 17651 | P94: 2 | Q94: =VLOOKUP(B94,[1]Sheet1!$A$1:$F$6212,6,0) -> #N/A
A95: 1010221607 | B95: 801391 | C95: مصنع ليالي الصحراء للزيوت والشحوم والبيتومين | D95: Laialy Al-Sahara Factory for Oils, Grease and Bitumen | E95: الخرج | F95: 0500044439 | G95: 0114710128 | H95: ehabmara86@gmail.com | I95: 0112708114 | J95: مفتوح | K95: صناعي | L95: منتج | M95: 2011-04-26 | N95: 2030-09-19 | O95: 6750 | P95: 1/1/53 0:00 | Q95: =VLOOKUP(B95,[1]Sheet1!$A$1:$F$6212,6,0) -> #N/A
A96: 1011014731 | B96: 802966 | C96: مصنع ماجد اليمني لتعبئة الزيوت | D96: Majed Al-Yemani Oils Packing Factory | E96: الخرج | F96: 0555483275 | G96: 0114520237 | H96: majed_cis@hotmail.com | I96: 0114619935 | J96: مفتوح | K96: صناعي | L96: تحت الإنشاء | M96: 2012-05-14 | N96: 2031-10-09 | O96: 6687 | P96: 40611 | Q96: =VLOOKUP(B96,[1]Sheet1!$A$1:$F$6212,6,0) -> #N/A
A97: 101240963 | B97: 801721 | C97: مصنع محمد عبد العزيز محمد المهيلب لاعادة تكرير الزيوت | D97: Mohamed Abdulaziz Mohamed Almeheleb for Re-refining Oil | E97: الخرج | F97: 0506666637 | G97: 0144822574 | H97: qv37@hotmail.com | I97: 044822574 | J97: مفتوح | K97: صناعي | L97: متوقف عن الإنشاء | M97: 2011-02-27 | N97: 2030-07-25 | O97: 6753 | P97: 39417 | Q97: =VLOOKUP(B97,[1]Sheet1!$A$1:$F$6212,6,0) -> #N/A
A98: 1011015781 | B98: 802801 | C98: مصنع نجد للكيماويات والزيوت | D98: Najd Factory for Chemicals & Oils | E98: الخرج | F98: 0555464254 | G98: 0114385209 | H98: kin.g.007@hotmail.com | I98: 0114385209 | J98: مفتوح | K98: صناعي | L98: منتج | M98: 2012-03-14 | N98: 2031-08-09 | O98: 9002 | P98: 40831 | Q98: =VLOOKUP(B98,[1]Sheet1!$A$1:$F$6212,6,0) -> #N/A
A99: 1010049588 | B99: 800463 | C99: شركة الجميح وشل لزيوت التشحيم | D99: Aljomaih and Shell Lubricating Oil Company | E99: الرياض الثانية | F99: 0553678512 | G99: 0112650888 | H99: admin@aljomaihshell.com | I99: 0112650949 | J99: مفتوح | K99: صناعي | L99: منتج | M99: 2009-04-18 | N99: 2018-12-28 | O99: 60000 | P99: 30440 | Q99: =VLOOKUP(B99,[1]Sheet1!$A$1:$F$6212,6,0) -> #N/A
A100: 1010211279 | B100: 20191 | C100: مصنع تدوير الزيوت التلقائي | D100: Automatic Oil Recycling Factory | E100: الرياض الثانية | F100: 0505106654 | G100: 0112654987 | H100: entajana@hotmail.com | I100: 0112655429 | J100: مفتوح | K100: صناعي | L100: منتج | M100: 2006-10-30 | N100: 2031-01-30 | O100: 4970 | P100: 2 | Q100: =VLOOKUP(B100,[1]Sheet1!$A$1:$F$6212,6,0) -> #N/A
A101: 1123404170 | B101: 805464 | C101: مصنع الشركة العالمية لزيوت التشحيم | D101: Global Lubricating Oil Company Factory | E101: الزلفي | F101: 0509900033 | G101: 0114628089 | H101: tamimi19709@hotmail.com | I101: 01144625955 | J101: مفتوح | K101: صناعي | L101: متوقف عن الإنشاء | M101: 2014-12-02 | N101: 2034-04-29 | O101: 15898 | P101: 41759 | Q101: =VLOOKUP(B101,[1]Sheet1!$A$1:$F$6212,6,0) -> #N/A
A102: 1126001755 | B102: 805225 | C102: مصنع فنون الزيت للصناعة | D102: Fonoun Oil Factory for Industry | E102: الزلفي | F102: 0550660009 | G102: 0112989995 | H102: khazzan2000@hotmail.com | I102: 0112989995 | J102: مفتوح | K102: صناعي | L102: تجهيز خطوط الانتاج | M102: 2014-09-02 | N102: 2035-01-17 | O102: 7594 | P102: 41443 | Q102: =VLOOKUP(B102,[1]Sheet1!$A$1:$F$6212,6,0) -> #N/A
A103: 4650038964 | B103: 800343 | C103: مصنع الحرمين لاعادة تكرير الزيوت المستعمله | D103: Al-Haramain Factory for Re-refining Used Oil | E103: المدينة المنورة | F103: 0541103444 | G103: 0126225880 | H103: Sindi_r@hotmail.com | I103: 026225880 | J103: مفتوح | K103: صناعي | L103: منتج | M103: 2009-07-15 | N103: 2019-03-28 | O103: 6912 | P103: 39222 | Q103: =VLOOKUP(B103,[1]Sheet1!$A$1:$F$6212,6,0) -> #N/A
A104: 4650057009 | B104: 803437 | C104: مصنع ريتاج الزيوت للمشتقات البتروليه | D104: Retage Oils Factory for Petroleum Derivatives | E104: المدينة المنورة | F104: 0557981234 | G104: 0138114401 | H104: samri2003@hotmail.com | I104: 038114401 | J104: مفتوح | K104: صناعي | L104: تحت الإنشاء | M104: 2012-11-26 | N104: 2032-04-22 | O104: 8601 | P104: 41071 | Q104: =VLOOKUP(B104,[1]Sheet1!$A$1:$F$6212,6,0) -> #N/A
A105: 355003434 | B105: 805451 | C105: مصنع سهم الاسطورة للفحم المضغوط | D105: Sahm Al-Ostoura Factory for Compressed Coal | E105: تبوك | F105: 0582155000 | G105: 0144292308 | H105: sawad1970@hotmail.com | I105: 0144292308 | J105: مفتوح | K105: صناعي | L105: اصدار رخصة بناء | M105: 2014-11-30 | N105: 2034-04-27 | O105: 2845 | P105: 41792 | Q105: =VLOOKUP(B105,[1]Sheet1!$A$1:$F$6212,6,0) -> #N/A
A106: 4030164688 | B106: 805317 | C106: مصنع شركة برافو السعودية لتكرير الزيوت | D106: Bravo Saudi Co. Factory for Refining Oils | E106: تبوك | F106: 0506364050 | G106: 0122687270 | H106: a.adel@batterjeeholding.com | I106: 0126080404 | J106: مفتوح | K106: صناعي | L106: متوقف عن الإنشاء | M106: 2014-09-08 | N106: 2034-02-02 | O106: 9600 | P106: 39028 | Q106: =VLOOKUP(B106,[1]Sheet1!$A$1:$F$6212,6,0) -> #N/A
A107: 1010062236 | B107: 805082 | C107: مصنع شركة رضا الوطنية للأسفلت المحسن | D107: Reda National Company Factory for Improved Asphalt | E107: تبوك | F107: 0507303087 | G107: 0114980888 | H107: yousef.alrashid@redanational.com | I107: 0114980619 | J107: مفتوح | K107: صناعي | L107: اصدار رخصة بناء | M107: 2014-06-26 | N107: 2034-11-09 | O107: 9295 | P107: 31476 | Q107: =VLOOKUP(B107,[1]Sheet1!$A$1:$F$6212,6,0) -> #N/A
... A111: 4030145589 | B111: 800105 | C111: المصنع العالمي المتطور لزيوت التشحيم | D111: Advanced Global Factory for Lubricating oils | E111: جدة الأولى | F111: 0503982832 | G111: 0126380695 | H111: admin-jeddah@unilube.ae | I111: 0126368636 | J111: مفتوح | K111: صناعي | L111: مكتمل إنشائياً | M111: 2010-02-07 | N111: 2029-07-04 | O111: 5625 | P111: 37942 | Q111: =VLOOKUP(B111,[1]Sheet1!$A$1:$F$6212,6,0) -> #N/A
A112: 4030145589 | B112: 800278 | C112: المصنع العالمي المتطور لزيوت التشحيم | D112: Advanced Global Factory for Lubricating oils | E112: جدة الأولى | F112: 0503982832 | G112: 0126380695 | H112: admin-jeddah@unilube.ae | I112: 0126368636 | J112: مفتوح | K112: صناعي | L112: منتج | M112: 2009-03-21 | N112: 2018-12-01 | O112: 11324 | P112: 1/1/53 0:00 | Q112: =VLOOKUP(B112,[1]Sheet1!$A$1:$F$6212,6,0) -> #N/A
A113: 4030228817 | B113: 803624 | C113: فرع شركة نوافل العربية للزيوت المحدودة | D113: Branch of Nawafel Al-Arabia Oils Company Limited | E113: جدة الأولى | F113: 0555204935 | G113: 0112911912 | H113: nawafilarabicoils@hotmail.com | I113: 0114797606 | J113: مفتوح | K113: صناعي | L113: منتج | M113: 2013-01-09 | N113: 2032-06-04 | O113: 3325 | P113: 41050 | Q113: =VLOOKUP(B113,[1]Sheet1!$A$1:$F$6212,6,0) -> #N/A
A114: 4030192001 | B114: 31029 | C114: مصنع المجد للأسفلت المستحلب | D114: Al Majd Asphalt Emulsion Factory | E114: جدة الأولى | F114: 0500862047 | G114: 0126082173 | H114: kareamona2@yahoo.com | I114: 026082173 | J114: مفتوح | K114: صناعي | L114: منتج | M114: 2006-12-18 | N114: 2031-03-20 | O114: 4156 | P114: 40016 | Q114: =VLOOKUP(B114,[1]Sheet1!$A$1:$F$6212,6,0) -> #N/A
A115: 4030254064 | B115: 800280 | C115: مصنع خلط زيوت التشحيم | D115: Lubricants Mixing Factory | E115: جدة الأولى | F115: 0505513476 | G115: 0126370966 | H115: aawwad@apsco-ksa.com | I115: 0126370966 | J115: مفتوح | K115: صناعي | L115: منتج | M115: 2009-10-07 | N115: 2019-06-20 | O115: 42000 | P115: 41519 | Q115: =VLOOKUP(B115,[1]Sheet1!$A$1:$F$6212,6,0) -> #N/A
A116: 4030163108 | B116: 280108 | C116: مصنع زيوت العربية | D116: Arabia Oils Factory | E116: جدة الأولى | F116: 0505699964 | G116: 0126082022 | H116: sainrex@yahoo.com | I116: 0126082258 | J116: مفتوح | K116: صناعي | L116: منتج | M116: 2007-05-20 | N116: 2030-08-31 | O116: 3750 | P116: 38922 | Q116: =VLOOKUP(B116,[1]Sheet1!$A$1:$F$6212,6,0) -> #N/A
...

Sheet ورقة1
A1: رقم العقد | B1: العميل | C1: Mobile | D1: Phone | E1: Email | F1: Fax | G1: المدينة | H1: حالة العميل | I1: نوع الأرض | J1: حالة الإنشائية | K1: تاريخ البدء | L1: تاريخ الإنتهاء | M1: Area | N1: رقم السجل التجاري | O1: تاريخ إصدار السجل التجاري | P1: الأنشطة الصناعية
A2: 801190 | B2: مصنع أسامة عبدالعزيز الدهيشي لهياكل السيارات | C2: 0505450758 | D2: 0112416652 | E2: info@aldheeshi.com | F2: 0112440368 | G2: الخرج | H2: مفتوح | I2: صناعي | J2: منتج | K2: 2010-06-29 | L2: 2029-11-22 | M2: 10500 | N2: 1010239390 | O2: 2 | P2: صنع المركبات ذات المحركات والمركبات المقطورة ونصف المقطورة | Q2: =VLOOKUP(N2,ورقة2!$A$1:$J$14632,3,0) -> Osama Abdul Aziz Al-Dahishi Factory for Car Bodies
A3: 805402 | B3: مصنع الجعيثن للصناعات الحديدية | C3: 0504270970 | D3: 0115500000 | E3: mubarak@aljeathen.com | F3: 0115510000 | G3: الخرج | H3: مفتوح | I3: صناعي | J3: لم يبدأ في التنفيذ | K3: 2014-11-16 | L3: 2034-04-12 | M3: 65818 | N3: 1011000322 | O3: 28546 | P3: صنع المركبات ذات المحركات والمركبات المقطورة ونصف المقطورة | Q3: =VLOOKUP(N3,ورقة2!$A$1:$J$14632,3,0) -> Al-Jeathen Factory for Steel Industries
A4: 805352 | B4: مصنع شركة الاتحاد الدوليه للصناعات المعدنية | C4: 0594111120 | D4: 0114459027 | E4: vip_z55z@hotmail.com | F4: 0114459027 | G4: الخرج | H4: مفتوح | I4: صناعي | J4: متوقف عن الإنشاء | K4: 2014-11-03 | L4: 2034-03-30 | M4: 10484 | N4: 1010402346 | O4: 41662 | P4: صنع المركبات ذات المحركات والمركبات المقطورة ونصف المقطورة | Q4: =VLOOKUP(N4,ورقة2!$A$1:$J$14632,3,0) -> Al-Etihad International Co. Factory for Metal Industries
A5: 805898 | B5: مصنع عبدالرحمن محمد الرويشد للمنتجات المعدنيه | C5: 0553075709 | D5: 0115448339 | E5: rowish_acv@hotmail.com | F5: 0115453121 | G5: الخرج | H5: مفتوح | I5: صناعي | J5: متوقف عن الإنشاء | K5: 2015-02-24 | L5: 2034-07-21 | M5: 9322 | N5: 1011022145 | O5: 41837 | P5: صنع المركبات ذات المحركات والمركبات المقطورة ونصف المقطورة | Q5: =VLOOKUP(N5,ورقة2!$A$1:$J$14632,3,0) -> Abdel Rahman Mohamed Al-Ruwaished Factory for Metal Products
A6: 804986 | B6: مصنع السعودية للأتوبيسات | C6: 0504488444 | D6: 0114484477 | E6: industry@owaidah.com.sa | F6: 0114469761 | G6: الرياض الأولى | H6: مفتوح | I6: صناعي | J6: منتج | K6: 2014-04-22 | L6: 2029-10-29 | M6: 8420 | N6: 1010225012 | O6: 39040 | P6: صنع المركبات ذات المحركات والمركبات المقطورة ونصف المقطورة | Q6: =VLOOKUP(N6,ورقة2!$A$1:$J$14632,3,0) -> Saudi Bus Factory
A7: 805522 | B7: هايل تريلور العربية السعودية المحدودة | C7: 0535259069 | D7: 0535259069 | E7: smohammed@heiltrailer.com | F7: 0112187801 | G7: الرياض الثالثة | H7: مفتوح | I7: مصنع جاهز | J7: منتج | K7: 2014-12-15 | L7: 2019-10-22 | M7: 2936 | N7: 1010427174 | O7: 41940 | P7: صنع المركبات ذات المحركات والمركبات المقطورة ونصف المقطورة | Q7: =VLOOKUP(N7,ورقة2!$A$1:$J$14632,3,0) -> Saudi Arabia Hale Tralor Company Limited
A8: 800357 | B8: مصنع المطرودي لهياكل السيارات | C8: 0553222284 | D8: 0114981592 | E8: fahadsalah24@hotmail.com | F8: 0114980723 | G8: الرياض الثانية | H8: مفتوح | I8: صناعي | J8: منتج | K8: 2009-06-12 | L8: 2019-02-23 | M8: 16000 | N8: 1010005675 | O8: 2 | P8: صنع المركبات ذات المحركات والمركبات المقطورة ونصف المقطورة | Q8: =VLOOKUP(N8,ورقة2!$A$1:$J$14632,3,0) -> Al-Matroudi Car Bodies Factory
A9: 30658 | B9: شركة الشمراني (مصنع مقطورات السحب والجر) | C9: 0500006597 | D9: 0126378612 | E9: shamrany_jed@hotmail.com | F9: 0126080797 | G9: جدة الأولى | H9: مفتوح | I9: صناعي | J9: منتج | K9: 2010-03-01 | L9: 2029-07-26 | M9: 11740 | N9: 4030086643 | O9: 33721 | P9: صنع المركبات ذات المحركات والمركبات المقطورة ونصف المقطورة | Q9: =VLOOKUP(N9,ورقة2!$A$1:$J$14632,3,0) -> Al-Shamrani company (Push-Pull Tractors Factory)
A10: 805014 | B10: مصنع إيثار لمعدات الإطفاء والسلامه | C10: 0582999999 | D10: 0126141667 | E10: faisal13456@gmail.com | F10: 0126141669 | G10: جدة الأولى | H10: مفتوح | I10: صناعي | J10: منتج | K10: 2014-05-28 | L10: 2034-10-12 | M10: 7080 | N10: 4030266121 | O10: 41696 | P10: صنع المركبات ذات المحركات والمركبات المقطورة ونصف المقطورة | Q10: =VLOOKUP(N10,ورقة2!$A$1:$J$14632,3,0) -> Eysar Factory for Fire Extinguishing and Safety Equipment
A11: 805102 | B11: مصتع مقطورات النامى | C11: 0553444748 | D11: 0114713573 | E11: alnmi_99@hotmail.com | F11: 0114713573 | G11: جدة الثالثة | H11: مفتوح | I11: صناعي | J11: منتج | K11: 2014-07-09 | L11: 2033-12-04 | M11: 9000 | N11: 4030267606 | O11: 41718 | P11: صنع معدات النقل الاخرى | Q11: =VLOOKUP(N11,ورقة2!$A$1:$J$14632,3,0) -> Al-Namy Trailers Factory
A12: 803302 | B12: مصنع عبدالله محمد السعدي لانتاج هياكل المقطورات | C12: 0555548989 | D12: 0126205050 | E12: f.m.aloufi@hotmail.com | F12: 026201059 | G12: جدة الثالثة | H12: مفتوح | I12: صناعي | J12: منتج | K12: 2012-10-13 | L12: 2032-03-09 | M12: 16890 | N12: 4030154013 | O12: 38413 | P12: صنع المركبات ذات المحركات والمركبات المقطورة ونصف المقطورة | Q12: =VLOOKUP(N12,ورقة2!$A$1:$J$14632,3,0) -> Abdullah Mohamed Al-Saadi Factory for Metal Industries
A13: 803659 | B13: مصنع عبده زايد علي الشميري للصناعات المعدنية | C13: 0505697584 | D13: 0126204915 | E13: alriyadh_consultant@yahoo.com | F13: 026204915 | G13: جدة الثالثة | H13: مفتوح | I13: صناعي | J13: مكتمل إنشائياً | K13: 2013-01-26 | L13: 2032-06-22 | M13: 9000 | N13: 4030137859 | O13: 37349 | P13: صنع المركبات ذات المحركات والمركبات المقطورة ونصف المقطورة | Q13: =VLOOKUP(N13,ورقة2!$A$1:$J$14632,3,0) -> Abdo Zayed Ali Al-Shemeri Factory for Metal Industries
... A167: 803505 | B167: مصنع ماجد عبدالله النهدي للمنتجات الاسفلتيه | C167: 0509999925 | D167: 0114769583 | E167: Majed-alshabibi@hotmail.com | F167: 0114769583 | G167: الخرج | H167: مفتوح | I167: صناعي | J167: متوقف عن الإنشاء | K167: 2012-12-15 | L167: 2032-05-11 | M167: 10443 | N167: 1010351304 | O167: 41181 | P167: الصناعات التحويلية الأخرى | Q167: =VLOOKUP(N167,ورقة2!$A$1:$J$14632,3,0) -> Majed Abdullah Nahdi Factory for Asphalt Products
A168: 801945 | B168: مصنع مرو الرياض للكيماويات | C168: 0504441840 | D168: 0114876009 | E168: sultan.mhmd390@gmail.com | F168: 0114876009 | G168: الخرج | H168: مفتوح | I168: صناعي | J168: تحت الإنشاء | K168: 2011-04-21 | L168: 2030-09-15 | M168: 11250 | N168: 8746/ت | O168: 40328 | P168: صنع المواد الكيميائية والمنتجات الكيميائية | Q168: =VLOOKUP(N168,ورقة2!$A$1:$J$14632,3,0) -> Maru Riyadh Chemicals Factory
A169: 803785 | B169: مصنع مستوى الهدف للأسمدة | C169: 0505101060 | D169: 0114955627 | E169: jalamneh@hadaflevel.com.sa | F169: 0114958689 | G169: الخرج | H169: مفتوح | I169: صناعي | J169: منتج | K169: 2013-03-12 | L169: 2032-08-07 | M169: 13910 | N169: 1010223127 | O169: 38971 | P169: صنع المواد الكيميائية والمنتجات الكيميائية | Q169: =VLOOKUP(N169,ورقة2!$A$1:$J$14632,3,0) -> Al-Hadaf Level Factory for Fertilizers
A170: 805160 | B170: مصنع موقفة للعوازل الاسفلتية | C170: 0555227044 | D170: 0114211687 | E170: naif0555227044@gmail.com | F170: 014211687 | G170: الخرج | H170: مفتوح | I170: صناعي | J170: لم يبدأ في التنفيذ | K170: 2014-07-23 | L170: 2033-12-18 | M170: 11044 | N170: 1010155159 | O170: 36397 | P170: الصناعات التحويلية الأخرى | Q170: =VLOOKUP(N170,ورقة2!$A$1:$J$14632,3,0) -> Mawkefa Factory for Asphalt Insulations
A171: 802585 | B171: مصنع نبات الأرض لإنتاج الاسمدة والمخصبات والمبيدات الحيوية | C171: 0595959512 | D171: 0114380940 | E171: a_algasem@hotmail.com | F171: 0112132603 | G171: الخرج | H171: مفتوح | I171: صناعي | J171: تحت الإنشاء | K171: 2012-01-10 | L171: 2031-06-05 | M171: 10398 | N171: 1010208095 | O171: 40607 | P171: صنع المواد الكيميائية والمنتجات الكيميائية | Q171: =VLOOKUP(N171,ورقة2!$A$1:$J$14632,3,0) -> Nabat Al-Ard Factory for the Production of Fertilizers and Bio-pesticides
A172: 805976 | B172: مصنع نقا للدهانات و المعاجين | C172: 0555439269 | D172: 0114952600 | E172: info@naqapaint.com | F172: 0114953325 | G172: الخرج | H172: مفتوح | I172: صناعي | J172: تحت الإنشاء | K172: 2015-03-24 | L172: 2034-08-18 | M172: 5060 | N172: 1011023256 | O172: 42059 | P172: صنع المواد الكيميائية والمنتجات الكيميائية | Q172: =VLOOKUP(N172,ورقة2!$A$1:$J$14632,3,0) -> Naqa Factory for Paints and Pastes
A173: 805827 | B173: مصنع نهر الصناعات لسليكات الصوديوم | C173: 0505818016 | D173: 0114563790 | E173: ali924444@gmil.com | F173: 0114536790 | G173: الخرج | H173: مفتوح | I173: صناعي | J173: لم يبدأ في التنفيذ | K173: 2015-01-28 | L173: 2034-06-24 | M173: 11249 | N173: 1011022829 | O173: 41963 | P173: صنع المواد الكيميائية والمنتجات الكيميائية | Q173: =VLOOKUP(N173,ورقة2!$A$1:$J$14632,3,0) -> Nahr Al-Senaat Factory for Sodium Silicate
A174: 805806 | B174: مصنع نوء الخير لكيماويات معالجة المياه | C174: 0504803464 | D174: 0114953041 | E174: naw_chemicals@hotmail.com | F174: 0114953041 | G174: الخرج | H174: مفتوح | I174: صناعي | J174: تحت الإنشاء | K174: 2015-02-05 | L174: 2034-07-02 | M174: 6815 | N174: 1011022595 | O174: 41933 | P174: صنع المواد الكيميائية والمنتجات الكيميائية | Q174: =VLOOKUP(N174,ورقة2!$A$1:$J$14632,3,0) -> Nou' El-Khair Factory for Water Treatment Chemicals
A175: 803312 | B175: مصنع وائل حسين سلامة للدهانات | C175: 0555308801 | D175: 0114001441 | E175: salamsafran@hotmail.com | F175: 0114235034 | G175: الخرج | H175: مفتوح | I175: صناعي | J175: تحت الإنشاء | K175: 2012-10-14 | L175: 2032-03-10 | M175: 5715 | N175: 1010305491 | O175: 2 | P175: صنع المواد الكيميائية والمنتجات الكيميائية | Q175: =VLOOKUP(N175,ورقة2!$A$1:$J$14632,3,0) -> Wael Hussein Salama Factory for Paints
A176: 40121 | B176: الشركة السعودية للدهانات الصناعية | C176: 0536000062 | D176: 0138472299 | E176: info@sipco.com.sa | F176: 0138473780 | G176: الدمام الأولى | H176: مفتوح | I176: صناعي | J176: منتج | K176: 2006-01-30 | L176: 2030-05-02 | M176: 16250 | N176: 2050011750 | O176: -53688 | P176: صنع المواد الكيميائية والمنتجات الكيميائية | Q176: =VLOOKUP(N176,ورقة2!$A$1:$J$14632,3,0) -> Saudi Industrial Paints Company (SIPCO)
A177: 40083 | B177: الشركة العربية للمعادن والكيماويات | C177: 0559550725 | D177: 0138472187 | E177: mshahrani@misaudi.com | F177: 0138473608 | G177: الدمام الأولى | H177: مفتوح | I177: صناعي | J177: منتج | K177: 2000-10-12 | L177: 2025-01-14 | M177: 28000 | N177: 2050004593 | O177: 2 | P177: صنع منتجات المعادن المشكلة، باستثناء الالات والمعدات | Q177: =VLOOKUP(N177,ورقة2!$A$1:$J$14632,3,0) -> Arab Co. for Metal & Chemicals
A178: 40038 | B178: المصنع الحديث للحديد والشكمانات | C178: 0505876530 | D178: 0138473320 | E178: e-steel@hotmail.com | F178: 0138473320 | G178: الدمام الأولى | H178: مفتوح | I178: صناعي | J178: منتج | K178: 2003-01-13 | L178: 2027-04-16 | M178: 5580 | N178: 2050046046 | O178: 38159 | P178: صنع منتجات المعادن اللافلزية الأخرى | Q178: =VLOOKUP(N178,ورقة2!$A$1:$J$14632,3,0) -> Modern Exhaust Pipe & Iron Factory
A179: 40064 | B179: المصنع السعودي لأكياس التعبئة | C179: 0599968959 | D179: 0138472115 | E179: azahrani@almoajilholding.com | F179: 0138341513 | G179: الدمام الأولى | H179: مفتوح | I179: صناعي | J179: منتج | K179: 1999-10-01 | L179: 2024-01-02 | M179: 11144 | N179: 2050015798 | O179: 31278 | P179: صنع منتجات المطاط والبلاستك | Q179: =VLOOKUP(N179,ورقة2!$A$1:$J$14632,3,0) -> Saudi Gas Cylinder Factory
A180: 40139 | B180: شركة اصباغ همبل العربية السعودية | C180: 0550660011 | D180: 0138471919 | E180: yual@sa.hempel.com | F180: 0138471816 | G180: الدمام الأولى | H180: مفتوح | I180: صناعي | J180: متوقف عن الإنتاج | K180: 2003-04-19 | L180: 2027-07-20 | M180: 20338 | N180: 2050002792 | O180: 26695 | P180: صنع المواد الكيميائية والمنتجات الكيميائية | Q180: =VLOOKUP(N180,ورقة2!$A$1:$J$14632,3,0) -> Hempel Paints (Saudi Arabia) Co.
... A182: 40051 | B182: شركة الصناعات الكيماوية للبناء المحدودة | C182: 0555160883 | D182: 0138471779 | E182: hsaleh@gerflorme.com | F182: 0138471781 | G182: الدمام الأولى | H182: مفتوح | I182: صناعي | J182: منتج | K182: 2000-08-23 | L182: 2024-11-24 | M182: 17522 | N182: 2050076959 | O182: 2 | P182: صنع المواد الكيميائية والمنتجات الكيميائية | Q182: =VLOOKUP(N182,ورقة2!$A$1:$J$14632,3,0) -> Chemical Industries Co. Ltd. For Construction
A183: 40122 | B183: شركة المحولات السعودية المحدودة | C183: 0550502459 | D183: 0138472030 | E183: hanik@sauditransformers.com | F183: 0138471718 | G183: الدمام الأولى | H183: مفتوح | I183: صناعي | J183: منتج | K183: 2007-04-25 | L183: 2027-09-08 | M183: 24375 | N183: 001/205006 | O183: 2 | P183: صنع المعدات الكهربائية | Q183: =VLOOKUP(N183,ورقة2!$A$1:$J$14632,3,0) -> Saudi Transformer Co. Ltd.
A184: 40111 | B184: شركة بارويد العربية السعودية المحدودة | C184: 0500508409 | D184: 0138473888 | E184: b_aroid@hotmail.com | F184: 0138472143 | G184: الدمام الأولى | H184: مفتوح | I184: صناعي | J184: منتج | K184: 2001-07-19 | L184: 2025-10-19 | M184: 35000 | N184: 2050004457 | O184: 2 | P184: صنع منتجات المعادن المشكلة، باستثناء الالات والمعدات | Q184: =VLOOKUP(N184,ورقة2!$A$1:$J$14632,3,0) -> Baroid Saudi Arabia Co. Ltd.
A185: 40001 | B185: شركة تنهات للتعدين | C185: 0504684002 | D185: 0138473600 | E185: factory@tanhatmining.com | F185: 0138473600 | G185: الدمام الأولى | H185: مفتوح | I185: صناعي | J185: منتج | K185: 2001-09-08 | L185: 2025-12-10 | M185: 14875 | N185: 2050025945 | O185: 34175 | P185: صنع منتجات المعادن المشكلة، باستثناء الالات والمعدات | Q185: =VLOOKUP(N185,ورقة2!$A$1:$J$14632,3,0) -> Tenhat Mining Co.
A186: 40032 | B186: شركة سيجما السعودية للدهانات المحدودة | C186: 0503848025 | D186: 0138471734 | E186: sami.marzooq@sigmapaints.com | F186: 0138471734 | G186: الدمام الأولى | H186: مفتوح | I186: صناعي | J186: منتج | K186: 2005-03-27 | L186: 2029-06-28 | M186: 14194 | N186: 2050009638 | O186: 2 | P186: صنع المواد الكيميائية والمنتجات الكيميائية | Q186: =VLOOKUP(N186,ورقة2!$A$1:$J$14632,3,0) -> Sigma Paints Saudi Arabia Co., Ltd.
A187: 40076 | B187: شركة نابكو الحديثة للمنتوجات البلاستيك | C187: 0504823990 | D187: 0138473040 | E187: adahan@napcogroup.com | F187: 0138471484 | G187: الدمام الأولى | H187: مفتوح | I187: صناعي | J187: منتج | K187: 2001-12-22 | L187: 2026-03-25 | M187: 8308 | N187: 2050024798 | O187: 2 | P187: صنع منتجات المطاط والبلاستك | Q187: =VLOOKUP(N187,ورقة2!$A$1:$J$14632,3,0) -> NAPCO Modern Plastic Products Company
A188: 40063 | B188: مصنع الاسيد الحديث | C188: 0550500226 | D188: 0138472121 | E188: mail@modernacid.com | F188: 0138472121 | G188: الدمام الأولى | H188: مفتوح | I188: صناعي | J188: متوقف عن الإنتاج | K188: 1999-05-21 | L188: 2023-08-21 | M188: 2400 | N188: 2050034044 | O188: 2 | P188: صنع المواد الكيميائية والمنتجات الكيميائية | Q188: =VLOOKUP(N188,ورقة2!$A$1:$J$14632,3,0) -> Al-Asid Modern Company
A189: 804930 | B189: مصنع المنيوم الجزيرة | C189: 0553111471 | D189: 0138472040 | E189: info@alumjaz.com | F189: 0138473927 | G189: الدمام الأولى | H189: مفتوح | I189: صناعي | J189: منتج | K189: 2014-04-08 | L189: 2023-12-20 | M189: 5222 | N189: 2050045913 | O189: 2 | P189: صنع منتجات المعادن المشكلة، باستثناء الالات والمعدات | Q189: =VLOOKUP(N189,ورقة2!$A$1:$J$14632,3,0) -> Al-Jazirah Aluminum Plant
A190: 804921 | B190: مصنع عبداللة هاشم للمعدات والغازات | C190: 0556691414 | D190: 0138471517 | E190: salami@er.ahg.com.sa | F190: 0138471764 | G190: الدمام الأولى | H190: مفتوح | I190: صناعي | J190: منتج | K190: 2014-04-07 | L190: 2024-12-07 | M190: 18385 | N190: 2050024268 | O190: 33909 | P190: صنع المواد الكيميائية والمنتجات الكيميائية | Q190: =VLOOKUP(N190,ورقة2!$A$1:$J$14632,3,0) -> Abdullah Hashim Factory for Equipment and Gases
A191: 40002 | B191: مصنع كيماويات مواد البناء | C191: 0505889479 | D191: 0138471450 | E191: moussa@cmci-sa.com | F191: 0138471575 | G191: الدمام الأولى | H191: مفتوح | I191: صناعي | J191: منتج | K191: 2006-12-09 | L191: 2031-03-11 | M191: 2292 | N191: 2050028294 | O191: 2 | P191: صنع المواد الكيميائية والمنتجات الكيميائية | Q191: =VLOOKUP(N191,ورقة2!$A$1:$J$14632,3,0) -> Construction Materials Chemicals Factory
A192: 290237 | B192: مصنع كيماويات مواد البناء | C192: 0505889479 | D192: 0138471450 | E192: moussa@cmci-sa.com | F192: 0138471575 | G192: الدمام الأولى | H192: مفتوح | I192: صناعي | J192: منتج | K192: 2008-03-30 | L192: 2030-07-22 | M192: 8640 | N192: 2050028294 | O192: 2 | P192: صنع المواد الكيميائية والمنتجات الكيميائية | Q192: =VLOOKUP(N192,ورقة2!$A$1:$J$14632,3,0) -> Construction Materials Chemicals Factory
A193: 50076 | B193: اراسكو للصناعات الكيميائية | C193: 0506014991 | D193: 0138123451 | E193: archem@arasco.com | F193: 0138123133 | G193: الدمام الثانية | H193: مفتوح | I193: صناعي | J193: منتج | K193: 2001-05-14 | L193: 2025-08-13 | M193: 12400 | N193: 2050037275 | O193: 2 | P193: صنع المواد الكيميائية والمنتجات الكيميائية | Q193: =VLOOKUP(N193,ورقة2!$A$1:$J$14632,3,0) -> NULL
A194: 50476 | B194: الشركة السعودية لانتاج مواد النظافة | C194: 0559266711 | D194: 0138121135 | E194: raddad@sidco.com.sa | F194: 0138123336 | G194: الدمام الثانية | H194: مفتوح | I194: صناعي | J194: منتج | K194: 2003-12-24 | L194: 2028-03-26 | M194: 15000 | N194: 2050006900 | O194: 28913 | P194: صنع المواد الكيميائية والمنتجات الكيميائية | Q194: =VLOOKUP(N194,ورقة2!$A$1:$J$14632,3,0) -> Saudi Industrial Detergents Company (SIDCO)
A195: 801939 | B195: الشركة السعودية للخرسانة الجاهزة | C195: 0555864563 | D195: 0138822373 | E195: mohammed.alshehri@saudireadymix.com.sa | F195: 0138822037 | G195: الدمام الثانية | H195: مفتوح | I195: صناعي | J195: منتج | K195: 2012-01-01 | L195: 2026-07-20 | M195: 64500 | N195: 2051024902 | O195: 36968 | P195: صنع منتجات المعادن اللافلزية الأخرى | Q195: =VLOOKUP(N195,ورقة2!$A$1:$J$14632,3,0) -> Saudi Ready-mix Concrete Company
... A276: 50254 | B276: مصنع شركة صالح وعبدالعزيز ابا حسين للكيماويات | C276: 0506082984 | D276: 0138990114 | E276: abnew@abahsain.net | F276: 0138990114 | G276: الدمام الثانية | H276: مفتوح | I276: صناعي | J276: منتج | K276: 1996-10-29 | L276: 2021-01-29 | M276: 10050 | N276: 2050047234 | O276: 2 | P276: صنع المواد الكيميائية والمنتجات الكيميائية | Q276: =VLOOKUP(N276,ورقة2!$A$1:$J$14632,3,0) -> Factory of Saleh and Abdul Aziz Abou Hussein Co. for Chemicals Industry
A277: 802157 | B277: مصنع شركة عبر الخليج للانظمة الصناعية | C277: 0541033873 | D277: 0138975654 | E277: amg@pgisystem.com | F277: 0138975654 | G277: الدمام الثانية | H277: مفتوح | I277: صناعي | J277: منتج | K277: 2011-08-10 | L277: 2031-01-03 | M277: 5514 | O277: -53688 | P277: صنع منتجات المعادن المشكلة، باستثناء الالات والمعدات | Q277: =VLOOKUP(N277,ورقة2!$A$1:$J$14632,3,0) -> Al-Dawaa Medical Services Co. Ltd.
A278: 280022 | B278: مصنع صالح وعبدالعزيز أباحسين لمزج الزيوت | C278: 0540430777 | D278: 0138984045 | E278: abnew@abahsain.net | F278: 0138571570 | G278: الدمام الثانية | H278: مفتوح | I278: صناعي | J278: منتج | K278: 2010-08-15 | L278: 2028-01-31 | M278: 12375 | N278: 2050049525 | O278: 38613 | P278: صنع فحم الكوك والمنتجات النفطية المكررة | Q278: =VLOOKUP(N278,ورقة2!$A$1:$J$14632,3,0) -> Saleh and Abdul Aziz Abou Hussein Factory for Oils Mixing
A279: 50268 | B279: مصنع فافا لصناعات التغليف | C279: 0503822962 | D279: 0138122105 | E279: hussain.alnasser@salmangroup.com | F279: 0138122106 | G279: الدمام الثانية | H279: مفتوح | I279: صناعي | J279: منتج | K279: 1997-08-21 | L279: 2021-11-22 | M279: 7500 | N279: 2051024844 | O279: 2 | P279: صنع منتجات المطاط والبلاستك | Q279: =VLOOKUP(N279,ورقة2!$A$1:$J$14632,3,0) -> Fafa Factory for Packaging Industries
A280: 50350 | B280: مصنع كناري للمنظفات و المطهرات الكيماوية | C280: 0594039810 | D280: 0138126820 | E280: omar.200900@yahoo.com | F280: 0138126850 | G280: الدمام الثانية | H280: مفتوح | I280: صناعي | J280: متوقف عن الإنتاج | K280: 1999-10-04 | L280: 2024-01-05 | M280: 6000 | N280: 2050035483 | O280: 2 | P280: صنع المواد الكيميائية والمنتجات الكيميائية | Q280: =VLOOKUP(N280,ورقة2!$A$1:$J$14632,3,0) -> Canary Factory for Chemical Detergent and Disinfectants
A281: 800859 | B281: مصنع كوب النجمه لتعبئة وتغليف السكر | C281: 0505815781 | D281: 0138580204 | E281: almanastar@hotmail.com | F281: 0138814463 | G281: الدمام الثانية | H281: مفتوح | I281: صناعي | J281: منتج | K281: 2010-02-06 | L281: 2029-07-03 | M281: 2500 | N281: 2050065048 | O281: 39945 | P281: صنع منتجات المطاط والبلاستك | Q281: =VLOOKUP(N281,ورقة2!$A$1:$J$14632,3,0) -> Koob Al-Negma Factory for Sugar Packing and Packaging
A282: 801472 | B282: مصنع منار للدهانات | C282: 0505829680 | D282: 0138120634 | E282: abujamal_51@yahoo.com | F282: 038120634 | G282: الدمام الثانية | H282: مفتوح | I282: صناعي | J282: منتج | K282: 2010-01-31 | L282: 2027-07-19 | M282: 4750 | N282: 2050049741 | O282: 2 | P282: صنع المواد الكيميائية والمنتجات الكيميائية | Q282: =VLOOKUP(N282,ورقة2!$A$1:$J$14632,3,0) -> Manar Paints Factory
A283: 50365 | B283: مصنع هبة لصناعة أجهزة إطفاء الحريق المحدودة | C283: 0505817970 | D283: 0138121821 | E283: khalid.saheli@heba-Fire.com | F283: 0138121723 | G283: الدمام الثانية | H283: مفتوح | I283: صناعي | J283: منتج | K283: 1996-05-28 | L283: 2020-08-29 | M283: 25350 | N283: 2050033115 | O283: 35751 | P283: صنع المعدات الكهربائية | Q283: =VLOOKUP(N283,ورقة2!$A$1:$J$14632,3,0) -> Heba Factory Limited for the manufacturer of fire extinguishers
A284: 50187 | B284: مصنع هيت لإنتاج شحوم التزييت | C284: 0505820182 | D284: 0138123005 | E284: nezar@eheet.com | F284: 0138123009 | G284: الدمام الثانية | H284: مفتوح | I284: صناعي | J284: منتج | K284: 1999-09-20 | L284: 2023-12-22 | M284: 5625 | N284: 2050022658 | O284: 2 | P284: صنع المواد الكيميائية والمنتجات الكيميائية | Q284: =VLOOKUP(N284,ورقة2!$A$1:$J$14632,3,0) -> Hit Factory for the Production of Lubricating Greases
A285: 50260 | B285: واحة اميرون للكيماويات | C285: 0544955404 | D285: 0138121511 | E285: akram@oasisameronpaints.com | F285: 0138121128 | G285: الدمام الثانية | H285: مفتوح | I285: صناعي | J285: منتج | K285: 2010-02-15 | L285: 2029-07-12 | M285: 2750 | N285: 2051007992 | O285: 2 | P285: صنع المواد الكيميائية والمنتجات الكيميائية | Q285: =VLOOKUP(N285,ورقة2!$A$1:$J$14632,3,0) -> Oasis Ameron Co. Ltd.
A286: 50271 | B286: واحة اميرون للكيماويات | C286: 0544955404 | D286: 0138121511 | E286: akram@oasisameronpaints.com | F286: 0138121128 | G286: الدمام الثانية | H286: مفتوح | I286: صناعي | J286: منتج | K286: 2010-02-15 | L286: 2029-07-12 | M286: 15500 | N286: 2051007992 | O286: 2 | P286: صنع المواد الكيميائية والمنتجات الكيميائية | Q286: =VLOOKUP(N286,ورقة2!$A$1:$J$14632,3,0) -> Oasis Ameron Co. Ltd.
A287: 10007 | B287: الشركة السعودية للكيماويات والمبيدات الحشرية | C287: 0505415831 | D287: 0114488079 | E287: salah_vip05@yahoo.com | F287: 0114486792 | G287: الرياض الأولى | H287: مفتوح | I287: صناعي | J287: منتج | K287: 1999-07-28 | L287: 2023-10-29 | M287: 7350 | N287: 1010007998 | O287: 2 | P287: صنع المواد الكيميائية والمنتجات الكيميائية | Q287: =VLOOKUP(N287,ورقة2!$A$1:$J$14632,3,0) -> Saudi Chemicals and Pesticides Co.
A288: 10009 | B288: شركة منتجات الأحبار المحدودة | C288: 0505226377 | D288: 0114489260 | E288: alshuwaier@inksaudi.com | F288: 0114474195 | G288: الرياض الأولى | H288: مفتوح | I288: صناعي | J288: منتج | K288: 2000-01-29 | L288: 2024-04-30 | M288: 10147 | N288: 1010148904 | O288: 35851 | P288: صنع المواد الكيميائية والمنتجات الكيميائية | Q288: =VLOOKUP(N288,ورقة2!$A$1:$J$14632,3,0) -> Ink Products Co. Ltd. Factory
A289: 802340 | B289: مصنع العطير للمجوهرات | C289: 0503211842 | D289: 0114460321 | E289: otsad112233@hotmail.com | F289: 0114955999 | G289: الرياض الأولى | H289: مفتوح | I289: استثماري | J289: منتج | K289: 2011-07-09 | L289: 2030-12-02 | M289: 1511 | N289: 1010069638 | O289: 2 | P289: الصناعات التحويلية الأخرى | Q289: =VLOOKUP(N289,ورقة2!$A$1:$J$14632,3,0) -> Al Otair Jewellery Factory
... A493: 802600 | B493: مصنع سعيد هادي القحطاني للدهانات | C493: 0598408400 | D493: 0172330816 | E493: saeed-hady-alqahtani@hotmail.com | F493: 0172330816 | G493: عسيـــر | H493: مفتوح | I493: صناعي | J493: منتج | K493: 2012-01-15 | L493: 2030-11-08 | M493: 3800 | N493: 5855035391 | O493: 40468 | P493: صنع المواد الكيميائية والمنتجات الكيميائية | Q493: =VLOOKUP(N493,ورقة2!$A$1:$J$14632,3,0) -> Saeed Hadi Al-Qahtani Paints Factory
A494: 804957 | B494: مصنع شركة جوتن السعودية المحدودة للدهانات | C494: 0555555665 | D494: 0555555665 | E494: mohamed.alsaiary@jotun.com | F494: 0555555665 | G494: عسيـــر | H494: مفتوح | I494: صناعي | J494: منتج | K494: 2014-04-13 | L494: 2028-10-30 | M494: 16440 | N494: - | O494: 2 | P494: صنع المواد الكيميائية والمنتجات الكيميائية | Q494: =VLOOKUP(N494,ورقة2!$A$1:$J$14632,3,0) -> Al-Hanaya Restaurant & Supermarket
A495: 803820 | B495: شركة مصنع السيد للأواني المنزلية | C495: 0505504776 | D495: 0125202780 | E495: hisham@alsayed-f.com | F495: 025202780 | G495: مكة المكرمة | H495: مفتوح | I495: صناعي | J495: منتج | K495: 2013-03-17 | L495: 2032-08-11 | M495: 3949 | N495: 4031010358 | O495: 29641 | P495: صنع منتجات المعادن المشكلة، باستثناء الالات والمعدات | Q495: =VLOOKUP(N495,ورقة2!$A$1:$J$14632,3,0) -> Al-Said Household Utensils Factory Co.
A496: 60023 | B496: مصنع اكسجين الرياض فرع مكة المكرمة | C496: 0556148946 | D496: 0125222562 | E496: albassam80@gmail.com | F496: 0114468319 | G496: مكة المكرمة | H496: مفتوح | I496: صناعي | J496: منتج | K496: 2002-01-09 | L496: 2026-04-12 | M496: 2592 | N496: 1010000523 | O496: 34454 | P496: صنع المواد الكيميائية والمنتجات الكيميائية | Q496: =VLOOKUP(N496,ورقة2!$A$1:$J$14632,3,0) -> Riyadh Oxygen Plant - Mecca Branch
A497: 802834 | B497: مصنع المجيد الحديث لتصنيع العطور والعود | C497: 0507014185 | D497: 0125203975 | E497: Abdullah.abbasi@ajmalksa.com | F497: 025203975 | G497: مكة المكرمة | H497: مفتوح | I497: صناعي | J497: منتج | K497: 2004-06-19 | L497: 2023-11-14 | M497: 6912 | N497: 4031047939 | O497: 2 | P497: صنع المواد الكيميائية والمنتجات الكيميائية | Q497: =VLOOKUP(N497,ورقة2!$A$1:$J$14632,3,0) -> Majid Modern Factory for Perfumes and Oud Manufacturing
A498: 60026 | B498: مصنع شركة السرتي للعطور | C498: 0505510773 | D498: 0125203752 | E498: sassati@sassatbestwmes.com | F498: 025203752 | G498: مكة المكرمة | H498: مفتوح | I498: صناعي | J498: منتج | K498: 2004-06-06 | L498: 2028-09-07 | M498: 6993 | N498: 4031007905 | O498: 28954 | P498: صنع المواد الكيميائية والمنتجات الكيميائية | Q498: =VLOOKUP(N498,ورقة2!$A$1:$J$14632,3,0) -> Elsarty Perfumes Co. factory
A499: 60006 | B499: مصنع شركة قبص لصناعة العطور | C499: 0504502485 | D499: 0125222988 | E499: mohammad@gabas.com | F499: 025222988 | G499: مكة المكرمة | H499: مفتوح | I499: صناعي | J499: منتج | K499: 2001-09-23 | L499: 2025-12-25 | M499: 4032 | N499: 4030141375 | O499: 2 | P499: صنع المواد الكيميائية والمنتجات الكيميائية | Q499: =VLOOKUP(N499,ورقة2!$A$1:$J$14632,3,0) -> Qabas Perfumes Co. Factory
A500: 60031 | B500: مصنع مكة لدهانات السيارات | C500: 0555566270 | D500: 0125220011 | E500: omar@AKA.com.sa | F500: 025220011 | G500: مكة المكرمة | H500: مفتوح | I500: صناعي | J500: منتج | K500: 1997-04-28 | L500: 2021-07-30 | M500: 5760 | N500: 4031036989 | O500: 2 | P500: صنع المواد الكيميائية والمنتجات الكيميائية | Q500: =VLOOKUP(N500,ورقة2!$A$1:$J$14632,3,0) -> Makka Factory for Automotive Paints
A501: 804158 | B501: شركة اتحاد اتصالات | C501: 0543211121 | D501: 0112118029 | E501: Corporate.sales@mobily.com.sa | F501: 012118029 | G501: الخرج | H501: مفتوح | I501: استثماري | J501: قائم | K501: 2013-06-08 | L501: 2018-04-14 | M501: 100 | N501: 2051031626 | O501: 2 | P501: - | Q501: =VLOOKUP(N501,ورقة2!$A$1:$J$14632,3,0) -> Mobily
A502: 804159 | B502: شركة اتحاد اتصالات | C502: 0543211121 | D502: 0112118029 | E502: Corporate.sales@mobily.com.sa | F502: 012118029 | G502: الخرج | H502: مفتوح | I502: استثماري | J502: قائم | K502: 2013-06-08 | L502: 2018-04-14 | M502: 100 | N502: 2051031626 | O502: 2 | P502: - | Q502: =VLOOKUP(N502,ورقة2!$A$1:$J$14632,3,0) -> Mobily
A503: 804160 | B503: شركة اتحاد اتصالات | C503: 0543211121 | D503: 0112118029 | E503: Corporate.sales@mobily.com.sa | F503: 012118029 | G503: الخرج | H503: مفتوح | I503: استثماري | J503: قائم | K503: 2013-06-08 | L503: 2018-04-14 | M503: 450 | N503: 2051031626 | O503: 2 | P503: - | Q503: =VLOOKUP(N503,ورقة2!$A$1:$J$14632,3,0) -> Mobily
A504: 804676 | B504: شركة الاتصالات السعودية | C504: 0514527000 | D504: 0114527000 | E504: contact@stc.com.sa | F504: 0114529005 | G504: الخرج | H504: مفتوح | I504: استثماري | J504: قائم | K504: 2014-01-19 | L504: 2018-11-25 | M504: 400 | N504: 1010150269 | O504: 2 | P504: - | Q504: =VLOOKUP(N504,ورقة2!$A$1:$J$14632,3,0) -> Saudi Telecom Company (STC)
A505: 804737 | B505: شركة الاتصالات السعودية | C505: 0514527000 | D505: 0114527000 | E505: contact@stc.com.sa | F505: 0114529005 | G505: الخرج | H505: مفتوح | I505: استثماري | J505: قائم | K505: 2014-01-19 | L505: 2018-11-25 | M505: 100 | N505: 1010150269 | O505: 2 | P505: - | Q505: =VLOOKUP(N505,ورقة2!$A$1:$J$14632,3,0) -> Saudi Telecom Company (STC)
A506: 40027 | B506: الشركة السعودية للصناعات الاساسية سابك | C506: 0000000000 | D506: 0138108433 | E506: aalmarzooq@sabic.com | F506: 0138108420 | G506: الدمام الأولى | H506: مفتوح | I506: صناعي | J506: منتج | K506: 2001-05-28 | L506: 2025-08-27 | M506: 17088 | N506: 2055003702 | O506: 28129 | P506: صنع المواد الكيميائية والمنتجات الكيميائية | Q506: =VLOOKUP(N506,ورقة2!$A$1:$J$14632,3,0) -> Saudi Arabia Basic Industries Corporation - SABIC
... A618: 800375 | B618: الشركة السعودية للمنتجات الصحية | C618: 0505492757 | D618: 0114980820 | E618: dispro@dispro.net | F618: 0114984879 | G618: الرياض الثانية | H618: مفتوح | I618: صناعي | J618: منتج | K618: 2009-09-12 | L618: 2019-05-26 | M618: 7840 | N618: 1010012866 | O618: 2 | P618: صنع منتجات المعادن اللافلزية الأخرى | Q618: =VLOOKUP(N618,ورقة2!$A$1:$J$14632,3,0) -> NULL
A619: 20218 | B619: الشركة العالمية لتصنيع الخيوط الجراحية والمستلزمات الطبية | C619: 0503467821 | D619: 0114054234 | E619: turkybawazir@korgma.com.sa | F619: 0114053273 | G619: الرياض الثانية | H619: مفتوح | I619: صناعي | J619: متوقف عن الإنتاج | K619: 1997-03-30 | L619: 2021-06-30 | M619: 9480 | N619: لا يوجد | O619: 2 | P619: صنع المنتجات الصيدلانية | Q619: =VLOOKUP(N619,ورقة2!$A$1:$J$14632,3,0) -> NULL
A620: 20581 | B620: الشركة المتحدة للصناعات الطبية المحدودة | C620: 0504404223 | D620: 0112650665 | E620: general@unimed.com.sa | F620: 0112650569 | G620: الرياض الثانية | H620: مفتوح | I620: صناعي | J620: منتج | K620: 1996-01-03 | L620: 2020-04-04 | M620: 5000 | N620: 1010120406 | O620: 2 | P620: صنع المنتجات الصيدلانية | Q620: =VLOOKUP(N620,ورقة2!$A$1:$J$14632,3,0) -> Al-Teknia Al-Hararia Co. for the Production of Al-Firax
A621: 801665 | B621: الشركة الوطنية للمنتجات الطبية المحدودة | C621: 0503495331 | D621: 0114981666 | E621: Faisal.almaammar@damad.com | F621: 0114985607 | G621: الرياض الثانية | H621: مفتوح | I621: صناعي | J621: منتج | K621: 2011-03-31 | L621: 2030-08-25 | M621: 20047 | N621: 1010012450 | O621: -53688 | P621: صنع المنتجات الصيدلانية | Q621: =VLOOKUP(N621,ورقة2!$A$1:$J$14632,3,0) -> National Medical Products Co. Ltd.
A622: 20206 | B622: المصنع السعودي لادوات النظافة - بريشكو | C622: 0502889433 | D622: 0112652879 | E622: info@alhaleefgroup.com | F622: 0114481566 | G622: الرياض الثانية | H622: مفتوح | I622: صناعي | J622: منتج | K622: 1997-06-15 | L622: 2021-09-16 | M622: 3750 | N622: 1010133918 | O622: 34779 | P622: صنع منتجات المطاط والبلاستك | Q622: =VLOOKUP(N622,ورقة2!$A$1:$J$14632,3,0) -> Saudi Factory for toiletries ( Brichko )
A623: 802799 | B623: شركة المصنع العربي للكواشف المخبرية والمحاليل الطبية | C623: 0569758953 | D623: 0112652400 | E623: mail@adamcoltd.com | F623: 0112651365 | G623: الرياض الثانية | H623: مفتوح | I623: صناعي | J623: منتج | K623: 2012-03-14 | L623: 2031-08-09 | M623: 5500 | N623: 1010128901 | O623: 2 | P623: صنع المنتجات الصيدلانية | Q623: =VLOOKUP(N623,ورقة2!$A$1:$J$14632,3,0) -> Arab Factory Co. for Lab Reagets & Medical Solutions
A624: 20751 | B624: شركة المنتجات الطبية والتجميلية - الرياض فارما | C624: 0540639921 | D624: 0112650111 | E624: mshreah@riyadhpharma.com | F624: 0112650505 | G624: الرياض الثانية | H624: مفتوح | I624: صناعي | J624: منتج | K624: 1995-08-23 | L624: 2019-11-23 | M624: 20000 | N624: 1010131637 | O624: 34685 | P624: صنع المنتجات الصيدلانية | Q624: =VLOOKUP(N624,ورقة2!$A$1:$J$14632,3,0) -> Medical & Cosmetic Products Company-Riyadh Pharma
A625: 20723 | B625: شركة ديماس للمنتجات الطبية | C625: 0568607005 | D625: 0114991894 | E625: demas@demas-group.com | F625: 0114990869 | G625: الرياض الثانية | H625: مفتوح | I625: صناعي | J625: منتج | K625: 2001-08-29 | L625: 2025-11-30 | M625: 3750 | N625: 1010028038 | O625: 29236 | P625: صنع المنتجات الصيدلانية | Q625: =VLOOKUP(N625,ورقة2!$A$1:$J$14632,3,0) -> Demas Company for Medical Products
A626: 802753 | B626: شركة ديماس للمنتجات الطبية | C626: 0568607005 | D626: 0114991894 | E626: demas@demas-group.com | F626: 0114990869 | G626: الرياض الثانية | H626: مفتوح | I626: استثماري | J626: منتج | K626: 2012-03-03 | L626: 2021-11-14 | M626: 2592 | N626: 1010028038 | O626: 29236 | P626: صنع منتجات المطاط والبلاستك | Q626: =VLOOKUP(N626,ورقة2!$A$1:$J$14632,3,0) -> Demas Company for Medical Products
A627: 804787 | B627: شركة مصنع صحة للمحاليل والمستحضرات الطبية | C627: 0553573338 | D627: 0112423454 | E627: sahhamedicl@hotmail.com | F627: 0112423212 | G627: الرياض الثانية | H627: مفتوح | I627: استثماري | J627: متوقف عن الإنشاء | K627: 2014-03-09 | L627: 2033-08-03 | M627: 2494 | N627: 1010169086 | O627: 2 | P627: صنع المنتجات الصيدلانية | Q627: =VLOOKUP(N627,ورقة2!$A$1:$J$14632,3,0) -> Seha Factory for Solutions and Pharmaceuticals
A628: 800884 | B628: شركة ميس السعودية للمنتجات الطبيه المحدودة | C628: 0556262527 | D628: 0112650184 | E628: fm@mais.com.sa | F628: 0112650139 | G628: الرياض الثانية | H628: مفتوح | I628: استثماري | J628: منتج | K628: 2010-02-22 | L628: 2019-11-04 | M628: 5000 | N628: 1010112398 | O628: 2 | P628: صنع المنتجات الصيدلانية | Q628: =VLOOKUP(N628,ورقة2!$A$1:$J$14632,3,0) -> Saudi Mais Company for Medical Products
A629: 803214 | B629: شركة ميس السعودية للمنتجات الطبيه المحدودة | C629: 0556262527 | D629: 0112650184 | E629: fm@mais.com.sa | F629: 0112650139 | G629: الرياض الثانية | H629: مفتوح | I629: صناعي | J629: منتج | K629: 2012-09-17 | L629: 2032-02-12 | M629: 20000 | N629: 1010112398 | O629: 2 | P629: صنع المنتجات الصيدلانية | Q629: =VLOOKUP(N629,ورقة2!$A$1:$J$14632,3,0) -> Saudi Mais Company for Medical Products
A630: 20148 | B630: مصنع الادوات والمستلزمات الطبية | C630: 0533322288 | D630: 0112655554 | E630: info@mdm-sa.com | F630: 0112653449 | G630: الرياض الثانية | H630: مفتوح | I630: صناعي | J630: منتج | K630: 1995-01-18 | L630: 2019-04-21 | M630: 5035 | N630: 1010180167 | O630: 2 | P630: صنع المنتجات الصيدلانية | Q630: =VLOOKUP(N630,ورقة2!$A$1:$J$14632,3,0) -> Medical Tools and Supplies Factory
A631: 804286 | B631: مصنع الادوية الوطني | C631: 0504475849 | D631: 0112651002 | E631: prpask@hotmail.com | F631: 0112651006 | G631: الرياض الثانية | H631: مفتوح | I631: صناعي | J631: منتج | K631: 2012-04-12 | L631: 2029-09-28 | M631: 9000 | N631: 1010058194 | O631: 2 | P631: صنع المنتجات الصيدلانية | Q631: =VLOOKUP(N631,ورقة2!$A$1:$J$14632,3,0) -> National Pharmaceutical Factory
... A821: 805941 | B821: شركة الزامل للمكيفات والأجهزة المنزلية | C821: 0555932328 | D821: 0138473333 | E821: ramzi@zamilindustrial.com | F821: 0138471302 | G821: الدمام الأولى | H821: مفتوح | I821: صناعي | J821: منتج | K821: 2014-12-18 | L821: 2018-11-03 | M821: 18935 | N821: 2050033719 | O821: 35941 | P821: صنع المعدات الكهربائية | Q821: =VLOOKUP(N821,ورقة2!$A$1:$J$14632,3,0) -> NULL
A822: 40109 | B822: شركة المحولات السعودية المحدودة | C822: 0550502459 | D822: 0138472030 | E822: hanik@sauditransformers.com | F822: 0138471718 | G822: الدمام الأولى | H822: مفتوح | I822: صناعي | J822: منتج | K822: 2005-02-06 | L822: 2029-05-09 | M822: 32091 | N822: 001/205006 | O822: 2 | P822: صنع المعدات الكهربائية | Q822: =VLOOKUP(N822,ورقة2!$A$1:$J$14632,3,0) -> Saudi Transformer Co. Ltd.
A823: 40020 | B823: مصنع الزامل للمكيفات والاجهزة المنزلية | C823: 0555932328 | D823: 0138473333 | E823: ramzi@zamilindustrial.com | F823: 0138471302 | G823: الدمام الأولى | H823: مفتوح | I823: صناعي | J823: منتج | K823: 2003-04-26 | L823: 2027-07-27 | M823: 3450 | N823: 2050033719 | O823: 2 | P823: صنع المعدات الكهربائية | Q823: =VLOOKUP(N823,ورقة2!$A$1:$J$14632,3,0) -> NULL
A824: 804929 | B824: مصنع السلامة للرديترات | C824: 0509888881 | D824: 0138471287 | E824: info@salamaradiator.com | F824: 0138471963 | G824: الدمام الأولى | H824: مفتوح | I824: صناعي | J824: منتج | K824: 2014-04-08 | L824: 2029-10-15 | M824: 4248 | N824: 2050043736 | O824: 37879 | P824: صنع منتجات المعادن المشكلة، باستثناء الالات والمعدات | Q824: =VLOOKUP(N824,ورقة2!$A$1:$J$14632,3,0) -> Al-Salamah Radiators Factory
A825: 40082 | B825: مصنع الشرق والغرب | C825: 0506849716 | D825: 0138472956 | E825: mohammed.ismail@atco.com.sa | F825: 0138473909 | G825: الدمام الأولى | H825: مفتوح | I825: صناعي | J825: منتج | K825: 2002-03-28 | L825: 2026-06-28 | M825: 4146 | N825: 007/205000 | O825: 2 | P825: صنع منتجات المعادن المشكلة، باستثناء الالات والمعدات | Q825: =VLOOKUP(N825,ورقة2!$A$1:$J$14632,3,0) -> Al-Sharq Wa Al-Gharb Factory
A826: 10032 | B826: المصنع الحديث للسخانات والبرادات | C826: 0555448143 | D826: 0114489868 | E826: m.aldosary@al-jazierah.com | F826: 0114486137 | G826: الرياض الأولى | H826: مفتوح | I826: صناعي | J826: منتج | K826: 1996-05-09 | L826: 2020-08-11 | M826: 3779 | N826: 1010167208 | O826: 37060 | P826: صنع المعدات الكهربائية | Q826: =VLOOKUP(N826,ورقة2!$A$1:$J$14632,3,0) -> Modern Factory for Heaters
A827: 805472 | B827: المصنع السعودي للتكييف | C827: 0550456333 | D827: 0114484366 | E827: mr.naif.d@hotmail.com | F827: 014484366 | G827: الرياض الأولى | H827: مفتوح | I827: استثماري | J827: منتج | K827: 2014-01-14 | L827: 2018-11-21 | M827: 1193 | N827: 1010269324 | O827: 39972 | P827: - | Q827: =VLOOKUP(N827,ورقة2!$A$1:$J$14632,3,0) -> #N/A
A828: 801593 | B828: شركة مصنع الميناء للوحات الكهربائية | C828: 0505461374 | D828: 0114489351 | E828: faryad@alminagroup.net | F828: 0114485793 | G828: الرياض الأولى | H828: مفتوح | I828: صناعي | J828: منتج | K828: 2011-03-08 | L828: 2030-08-02 | M828: 3293 | N828: 1010268025 | O828: 40322 | P828: صنع المعدات الكهربائية | Q828: =VLOOKUP(N828,ورقة2!$A$1:$J$14632,3,0) -> Al Mina Electrical Panel Board Factory Co.
A829: 800929 | B829: مصنع الجزيرة للأجهزة المنزلية | C829: 0503422996 | D829: 0114489868 | E829: m.aldosary@al-jazierah.com | F829: 0114469759 | G829: الرياض الأولى | H829: مفتوح | I829: صناعي | J829: منتج | K829: 2010-10-23 | L829: 2030-03-18 | M829: 5802 | N829: 1010167206 | O829: 37060 | P829: صنع المعدات الكهربائية | Q829: =VLOOKUP(N829,ورقة2!$A$1:$J$14632,3,0) -> Al-Jazira Factory for Home Appliances
A830: 800928 | B830: مصنع الجزيرة للاجهزة المنزلية | C830: 0503422996 | D830: 0114480353 | E830: m.aldosary@aljazierah.com | F830: 0114487214 | G830: الرياض الأولى | H830: مفتوح | I830: صناعي | J830: متوقف عن الإنتاج | K830: 2010-06-26 | L830: 2029-11-19 | M830: 2184 | N830: 1010167206 | O830: -53688 | P830: صنع المعدات الكهربائية | Q830: =VLOOKUP(N830,ورقة2!$A$1:$J$14632,3,0) -> Al-Jazira Factory for Home Appliances
A831: 804180 | B831: مصنع الجزيرة للاجهزة المنزلية | C831: 0503422996 | D831: 0114480353 | E831: m.aldosary@aljazierah.com | F831: 0114487214 | G831: الرياض الأولى | H831: مفتوح | I831: استثماري | J831: قائم | K831: 2013-05-08 | L831: 2018-03-15 | M831: 3917 | N831: 1010167206 | O831: -53688 | P831: صنع المعدات الكهربائية | Q831: =VLOOKUP(N831,ورقة2!$A$1:$J$14632,3,0) -> Al-Jazira Factory for Home Appliances
A832: 10016 | B832: مصنع ناصر الحميد للمكيفات والبرادات | C832: 0505421768 | D832: 0114480275 | E832: nabil4go@hotmail.com | F832: 0114480683 | G832: الرياض الأولى | H832: مفتوح | I832: صناعي | J832: متوقف عن الإنتاج | K832: 1995-07-20 | L832: 2029-07-03 | M832: 2888 | N832: 1010004862 | O832: -53688 | P832: صنع الالات والمعدات غير المصنفة في موضع اخر | Q832: =VLOOKUP(N832,ورقة2!$A$1:$J$14632,3,0) -> Nasser Al-Hamid Factory for Air-conditioners and Refrigerators
A833: 10017 | B833: مصنع ناصر الحميد للمكيفات والبرادات | C833: 0505421768 | D833: 0114480275 | E833: nabil4go@hotmail.com | F833: 0114480683 | G833: الرياض الأولى | H833: مفتوح | I833: صناعي | J833: منتج | K833: 1996-01-08 | L833: 2020-04-09 | M833: 6825 | N833: 1010004862 | O833: -53688 | P833: صنع الالات والمعدات غير المصنفة في موضع اخر | Q833: =VLOOKUP(N833,ورقة2!$A$1:$J$14632,3,0) -> Nasser Al-Hamid Factory for Air-conditioners and Refrigerators
A834: 10019 | B834: مصنع نجد الحديث للبرادات والسخانات | C834: 0505400985 | D834: 0114487009 | E834: amsaa7@hotmail.com | F834: 0114486580 | G834: الرياض الأولى | H834: مفتوح | I834: صناعي | J834: منتج | K834: 1999-05-28 | L834: 2023-08-28 | M834: 3500 | N834: 1010006143 | O834: 2 | P834: صنع المعدات الكهربائية | Q834: =VLOOKUP(N834,ورقة2!$A$1:$J$14632,3,0) -> New Najd Factory for Refrigerators & Heaters
A835: 805424 | B835: مصنع راسيل للمفاتيح واللوحات الكهربائية | C835: 0501202202 | D835: 0114984151 | E835: naseralsanie@hotmail.com | F835: 0114986123 | G835: الرياض الثالثة | H835: مفتوح | I835: مصنع جاهز | J835: منتج | K835: 2014-11-20 | L835: 2019-09-26 | M835: 1499 | N835: 1010310973 | O835: 40713 | P835: صنع المعدات الكهربائية | Q835: =VLOOKUP(N835,ورقة2!$A$1:$J$14632,3,0) -> Raseel Factory for Switches & Electrical Panels
A836: 803848 | B836: الشركة السعودية الحديثة لصناعة الاسلاك والكابلات الكهربائية | C836: 0505232352 | D836: 0112650850 | E836: rcgc@riyadh-cables.com | F836: 0112651423 | G836: الرياض الثانية | H836: مفتوح | I836: صناعي | J836: منتج | K836: 2013-05-06 | L836: 2032-09-30 | M836: 25160 | N836: 1010106953 | O836: 2 | P836: صنع المعدات الكهربائية | Q836: =VLOOKUP(N836,ورقة2!$A$1:$J$14632,3,0) -> Saudi Modern Company for Special Electric Wire & Cables Industry
A837: 803849 | B837: الشركة السعودية الحديثة لصناعة الاسلاك والكابلات الكهربائية | C837: 0505232352 | D837: 0112650850 | E837: rcgc@riyadh-cables.com | F837: 0112651423 | G837: الرياض الثانية | H837: مفتوح | I837: صناعي | J837: منتج | K837: 2013-05-06 | L837: 2032-09-30 | M837: 46024 | N837: 1010106953 | O837: 41753 | P837: صنع المعدات الكهربائية | Q837: =VLOOKUP(N837,ورقة2!$A$1:$J$14632,3,0) -> Saudi Modern Company for Special Electric Wire & Cables Industry
...

Sheet ورقة2
A1: رقم السجل التجاري | B1: اسم العميل | C1: اسم العميل - انجليزي
A2: 1010073387 | B2: شركة انارة المحدودة | C2: NULL
A3: 2257024803 | B3: شركة عبدالله وخالد عبدالرحمن الشعيبي للتجارة ةالصناعة | C3: Al Shoaibi Plastic Factory
A4: 4030165161 | B4: مصنع عبدالرحمن حسين منصور الشريف لقوالب ومكائن البلك | C4: NULL
A5: NULL | B5: مصنع مملكة الحلويات والشوكولاته والسكاكر والبسكويت | C5: NULL
A6: 4030158088 | B6: المصنع السعودي للقوالب المعدنية | C6: Saudi Factory for Metal Molds
A7: 2257038479 | B7: مصنع خليفة خليفة الهاشل للأسلاك الكهربائية | C7: NULL
A8: 1010049775 | B8: مصنع خلف سعد المطيري للمنتجات المعدنيه | C8: Khalaf Saad Al-Mutairi Factory for Metal Products
A9: 1010038481 | B9: مصنع مركز القباني التجاري للحلويات | C9: Al-Qabbani Commercial Center Factory for Sweets
A10: 1010075948 | B10: مصنع مناع ظافر العمري للزجاج والمرايا | C10: Mannaa Zafer Al-Amri Factory for Glass & Mirrors
A11: 2257041043 | B11: مصنع الشروق للأسقف وشرائح الألمنيوم | C11: Al-Shorouq Factory for Aluminium Ceilings and Slides
A12: 3550024597 | B12: مصنع أسس الحديثة للمصاعد | C12: NULL
A13: 3550026947 | B13: مصنع عبدالله محمد حمدي للبلوك | C13: NULL
A14: 4350000678 | B14: مصنع عبدالعزيز علي الملحم للمناديل والكرتون | C14: NULL
A15: 5950011654 | B15: مصنع نطاقات الشرق الأوسط للبلوك والخرسانة الجاهزة | C15: NULL
A16: 4030135180 | B16: مصنع سامي محمد مصطفى ابو غانم للبلاستيك | C16: NULL
A17: 3350035796 | B17: مصنع/ محمد حمد صالح المقبل للثلاجات والبرادات | C17: NULL
... A185: 1010245946 | B185: مصنع شركة تقنية الطرق للأسفلت المحسن | C185: Road Technology co. factory for Enhanced Asphalt
B186: مصنع شركة ابناء عبدالله عبد المحسن الخضري للصناعات الخرسانية | C186: Abdullah Abdul Mohsen Al-Khodari Co. Factory for Concrete Industries
A187: 33632 | C187: القصيم الثانية
A188: 1110001026 | B188: مصنع شركة تقنية العالم لتعبئة الزيوت | C188: NULL
A189: 1113003789 | B189: مصنع شركة كميت للأعمدة الخرسانية | C189: NULL
A190: 4031050332 | B190: موسسة محمد احمد سليمان الحازمي | C190: Mohamed Ahmed Al-Hazmi Trading Est. (Health Center)
A191: 1010064067 | B191: شركة مصنع آليات النظافة المحدودة | C191: Al-Rubaian Factory Co. for Hand Carts and Janitorial Tasks
A192: 1010084384 | B192: مصنع نافا للمنتجات الهندسية | C192: NAFA Engineering Products Factory
A193: 4604003765 | B193: شركة السلام الدولية المحدودة | C193: NULL
A194: 5855024347 | B194: شركة مصنع دهانات المملكة | C194: Kingdom Paints Factory Co.
A195: 4030187699 | B195: مصنع أحمد عبد ربه الحربي للمبسطات الحديدية | C195: Ahmed Abed Rabbo Military Factory for Flat Iron Bars
A196: 1010209741 | B196: مصنع المنيوم الرياض | C196: Riyadh Aluminium Plant
A197: NULL | B197: مصنع المهيدب للصناعات الغذائية | C197: NULL
A198: 2257038479 | B198: مصنع خليفة خليفة الهاشل للأسلاك الكهربائية | C198: NULL
A199: 5855054594 | B199: مصنع اوركا للابواب والاعمال المعدنية | C199: ORCA Factory for Metal Doors and Products
A200: 3550027488 | B200: مصنع خديجه محمد البلوي لتدوير وتصنيع البلاستيك | C200: NULL
A201: 4650044762 | B201: مصنع مياه أريس | C201: Aris Water Factory
A202: 2051038700 | B202: مصنع شواهد البناء للتحكم الصناعي | C202: NULL
A203: 5855034459 | B203: مصنع ناصر سالم مهدى المهرى | C203: NULL
A204: 4030083606 | B204: مصنع اسلاك اللحام السعودية | C204: NULL
A205: 4030239159 | B205: مصنع شركة الفيحاء الدولية لتدوير المعادن | C205: NULL
A206: 4030109617 | B206: مصنع عبدالحكيم محمد شماخ للمياه المعبأه | C206: NULL
A207: 4030151342 | B207: مصنع المستقبل الباهر للبلاستيك | C207: Al-Mostakbal Al-Baher Plastic Factory
A208: 4030241150 | B208: شركة مصنع السنابل الشامل للمنتجات البلاستيكية المحدودة | C208: Al-Sanabel Comprehensive Plastic Products Factory Co. Ltd.
A209: 2257032128 | B209: شركة مصنع الشرق للأدوية | C209: NULL
... A220: 1010353134 | B220: مصنع المسكن المتكامل للمنتجات الخشبية | C220: NULL
A221: لا يوجد | B221: مصنع حمد محمد الدريس للمنتجات الاسمنتية | C221: NULL
A222: 4030283205 | B222: مصنع شركة الرواد الجديدة للصناعة والتجارة | C222: NULL
A223: 1010077408 | B223: مصنع شركة عبد الله أبونيان لتصنيع أغشية التناضح العكسي | C223: NULL
A224: 4030198653 | B224: مصنع رجاء خليل ابو طعيمه لأنتاج الاعلاف | C224: NULL
A225: 1010166685 | B225: مؤسسة المنزل الجاهز للمقاولات | C225: NULL
A226: 1010185603 | B226: مصنع ثروات الجزيرة للخامات الصناعية | C226: NULL
A227: 4030137859 | B227: مصنع عبده زايد علي الشميري للصناعات المعدنية | C227: Abdo Zayed Ali Al-Shemeri Factory for Metal Industries
A228: 3550023276 | B228: مصنع الزيتونة الشمالية للصناعات الغذائية | C228: NULL
A229: 1010053926 | B229: مصنع الأبواب الجلدية والخشبية السحابة | C229: Leather and Wooden Sliding Doors Factory
A230: 1010220371 | B230: مصنع شركة عوض سعد مشبب بن ظفرة وشريكة للمنتجات الصحية الخزفية | C230: Awad Saad Mushabbab Bin Zafra & Partner Co. for Ceramic Healthy Products
A231: 4030280582 | B231: مصنع شركة تجميع البلاستيك | C231: NULL
A232: 4030012213 | B232: شركة مصنع الخرسانة السعودية المنقولة المحدودة | C232: Saudi Transport Beton Factory Co. Ltd.
A233: 3550011862 | B233: مصنع الجابري للمعجنات والحلويات والتمور | C233: Al-Jabari Factory for Pastries, Sweets and Dates
... A348: 0 | B348: وزارة العمل | C348: Ministry of Labor
B349: مصنع البراك لأبواب الكراجات | C349: Al Barrak Factory for Garage Doors
A350: 34254 | C350: الأحساء الأولى
A351: 4030065310 | B351: شركة مصانع الجزيرة للمنتجات الفولاذية المحدودة | C351: NULL
A352: NULL | B352: مصنع كتكوت للصناعات الغذائية | C352: NULL
A353: 1010074887 | B353: شركة مصنع الربيعان لعبات اليد ومهمات النظافة وحماية صحة البيئة | C353: NULL
A354: 2257041171 | B354: مصنع الأمل للصناعات الغذائية | C354: Al-Amal Factory for Food Industries
A355: 2250041902 | B355: شركة مصنع الشرقية لدرفة الحديد | C355: Al-Sharqiya Iron Rolling Factory
A356: 4030282898 | B356: مصنع جواد الجود للصناعات التحويلية | C356: McCain Jeddah Factory for Manufacturing Industries
A357: 2050034075 | B357: مصنع عبداللطيف صالح الحمد لقضيب التسليح | C357: Abdul Latif Saleh Al Hamad Factory for Rebars
A358: 1113003873 | B358: مصنع تقنية علوم اللحام | C358: NULL
A359: 4650004437 | B359: مصنع المدينة للبلاستيك والمنتجات الورقية | C359: NULL
A360: 5855048695 | B360: مصنع ثلاجات الماسية للثلاجات والمكيفات | C360: NULL
A361: 5850069990 | B361: مصنع إبهار القفار للأكواب الورقية | C361: NULL
A362: 4030247288 | B362: مصنع كيماويات الامن الحيوي السعودي | C362: Saudi Security Bio-chemicals Factory
A363: 5950004848 | B363: مصنع على ناصر القاضى للمنتجات البلاستيكية | C363: Ali Nasser AL-Kadi Factory for Plastic Products
A364: 2252067146 | B364: مصنع فاطمه محمد الخرس للقوارير البلاستيكيه | C364: NULL
... A393: 4030127076 | B393: مصنع علا محمد المغربي للمنتجات المعدنية | C393: Ola Mohamed Al-Maghrabi Factory for Metal Products
A394: NULL | B394: مصنع علي موسى القريني للعبوات المختبرية | C394: NULL
A395: 4650057676 | B395: مصنع حمد محمد الدريس للمنتجات الاسمنتية | C395: Hamad Mohamed Al-Drees Cement Products Factory
A396: 1010221835 | B396: النخبة للصناعات الغذائية | C396: NULL
A397: 3450012868 | B397: مصنع الحازمي للصناعات البلاستيكية | C397: Al-Hazmy Factory for Plastic Industries
A398: 3350025944 | B398: مصنع عثمان بايق العمودي لتدوير الاطارات والنفايات | C398: NULL
A399: 5906027895 | B399: مصنع فهد سعد القحطاني للمنتجات الاسمنتية | C399: NULL
A400: 2511019095 | B400: مصنع فارس سلمي المطيري لاعمال الرخام | C400: NULL
A401: 1011024467 | B401: مصنع يوسف سليمان البواردي للطاقة الشمسية | C401: NULL
A402: 2051062783 | B402: مصنع شركة أس كي أم للتكييف | C402: NULL
A403: 5950004848 | B403: مصنع على ناصر القاضى للمنتجات البلاستيكية | C403: Ali Nasser AL-Kadi Factory for Plastic Products
A404: 3403013946 | B404: مصنع اكسجين الشمال للغازات الطبية و الصناعية | C404: Al-Shamal Oxygen Plant for Medical and Industrial Gases
A405: 1010156798 | B405: مصنع شركة خزام الدرعية للصناعات الحديدية | C405: Khuzam Al-Dir'iya Iron Industries Co. Factory
A406: 5900034191 | B406: مصنع خلب الدولية للمياه الصحيه | C406: NULL
... A435: 1010001054 | B435: بنك الرياض | C435: Riyad Bank
B436: شركة الاتصالات السعودية المتنقلة | C436: Saudi Mobile Telecommunication Company -Zain
A437: 1 | C437: حائل
A438: 1010150269 | B438: شركة الاتصالات السعودية | C438: Saudi Telecom Company (STC)
A439: 4030195653 | B439: مصنع الجواد زين لمستحضرات التجميل | C439: Al-Jawad Zain Cosmetics Factory
A440: NULL | B440: شركة الفنار | C440: NULL
A441: 4030159413 | B441: مصنع مدينة الدواء للصناعات الدوائية | C441: Drug City Factory for Pharmaceutical Industry
A442: لا يوجد | B442: مصنع عبدالوهاب فهد الحازمي للحجر الصناعي | C442: Abdul Wahab Fahd Al-Hazemi Factory for Industrial Stone
A443: 4030279113 | B443: مصنع شركة القوى الفعالة للمحولات واللوحات الكهربائية | C443: Al-Quwa Al-Faala Company Factory for Transformers and Electrical Panels
A444: 1126002277 | B444: مصنع شركة كرم للبلاستيك | C444: Karam Plastic Co. Factory
A445: 4030275656 | B445: مصنع مرجان السعودية للمنتجات النفطية المكررة | C445: Aisha Farid Abdul Salam Factory for Oil Refinery
A446: 1010414191 | B446: مصنع شركة جدار للمنتجات الاسمنتيه | C446: NULL
A447: 4030209042 | B447: مصتع عدنان محمد باحمدين لتكرير الزيوت | C447: Adnan Mohamed Bahamdin Factory for Oil Refinery
...

Sheet Sheet3
E2: 1010014590 | F2: 494828
E3: 1010073685 | F3: 243061
E4: 1010085734 | F4: 228167
E5: 1010010813 | F5: 220177
E6: 1010029494 | F6: 200175
E7: 1010008551 | F7: 176511
E8: 1010052927 | F8: 150893
E9: 1010014993 | F9: 128869
E10: 1010064131 | F10: 124082
E11: 1010053014 | F11: 94873
E12: 1010061089 | F12: 89974
E13: 1010106953 | F13: 83876
E14: 1010070479 | F14: 80752
E15: 1010071668 | F15: 78345
E16: 1010084155 | F16: 75336
... E601: 1010008540 | F601: 500

Sheet Sheet2
A1: رقم السجل التجاري | B1: رقم العقد | C1: العميل | D1: Name of factories | E1: المدينة | F1: Mobile | G1: Phone | H1: Email | I1: Fax | J1: حالة العميل | K1: نوع الأرض | L1: حالة الإنشائية | M1: تاريخ البدء | N1: تاريخ الإنتهاء | O1: Area | P1: تاريخ إصدار السجل التجاري | Q1: الأنشطة الصناعية
A2: 1010014590 | B2: 800785 | C2: شركة الخزف السعودية | D2: Saudi Ceramic Company | E2: الرياض الثانية | F2: 0504103118 | G2: 0112650265 | H2: alenzie@saudiceramics.com | I2: 0112653333 | J2: مفتوح | K2: صناعي | L2: منتج | M2: 2010-04-13 | N2: 2029-09-06 | O2: 269982 | P2: 28514 | Q2: =VLOOKUP(B2,[1]Sheet1!$A$1:$F$6212,6,0) -> #N/A
A3: 1010085734 | B3: 806537 | C3: مصنع الشركة العربية للانابيب | D3: Arabian Pipes Company | E3: الرياض الثانية | F3: 0503478702 | G3: 0112650123 | H3: info@arabian-pipes.com | I3: 0112650312 | J3: مفتوح | K3: صناعي | L3: منتج | M3: 2014-11-16 | N3: 2034-04-11 | O3: 228167 | P3: 33474 | Q3: =VLOOKUP(B3,[1]Sheet1!$A$1:$F$6212,6,0) -> #N/A
A4: 1010010813 | B4: 806733 | C4: مركز سابك الصناعي | D4: NULL | E4: الرياض الثانية | F4: 0504478143 | G4: 0112503131 | H4: alsherehyf@sabic.com | I4: 0112651101 | J4: مفتوح | K4: صناعي | L4: منتج | M4: 2014-05-08 | N4: 2019-03-15 | O4: 192746 | P4: 28129 | Q4: =VLOOKUP(B4,[1]Sheet1!$A$1:$F$6212,6,0) -> #N/A
A5: 1010029494 | B5: 800350 | C5: الراشد ايه بيوتنج | D5: Al-Rashid Abetong Co. Ltd. | E5: الرياض الثانية | F5: 0503155602 | G5: 0114981222 | H5: ahmed@alrashidabetong.com | I5: 0112792448 | J5: مفتوح | K5: صناعي | L5: منتج | M5: 2009-07-19 | N5: 2019-04-01 | O5: 183576 | P5: 2 | Q5: =VLOOKUP(B5,[1]Sheet1!$A$1:$F$6212,6,0) -> #N/A
A6: 1010008551 | B6: 807131 | C6: مصنع الرياض للأثاث | D6: Riyadh Furniture Industries Factory | E6: الرياض الثانية | F6: 0506424801 | G6: 0114981216 | H6: info@athath.com | I6: 014981216 | J6: مفتوح | K6: صناعي | L6: منتج | M6: 2016-04-07 | N6: 2035-09-01 | O6: 146484 | P6: 27631 | Q6: =VLOOKUP(B6,[1]Sheet1!$A$1:$F$6212,6,0) -> #N/A
A7: 1010064131 | B7: 807391 | C7: مصنع البابطين للاعمدة والصواري المجلفنة وملحقاتها | D7: #N/A | E7: الرياض الثانية | F7: 0505273911 | G7: 0112650003 | H7: kaha-yami@al-babtain.com.sa | I7: 0112651983 | J7: مفتوح | K7: صناعي | L7: منتج | M7: 2016-06-19 | N7: 2032-12-16 | O7: 124082 | P7: 31734 | Q7: =VLOOKUP(B7,[1]Sheet1!$A$1:$F$6212,6,0) -> #N/A
A8: 1010073685 | B8: 807629 | C8: شركة العبداللطيف للأستثمار الصناعي | D8: Al-Abdullatif Industrial Investment Company | E8: الرياض الثانية | F8: 0505757403 | G8: 0112658888 | H8: jaber@carpets.com | I8: 0112659999 | J8: مفتوح | K8: صناعي | L8: منتج | M8: 2016-10-23 | N8: 2030-05-23 | O8: 114917 | P8: 32777 | Q8: =VLOOKUP(B8,[1]Sheet1!$A$1:$F$6212,6,0) -> #N/A
A9: 1010071668 | B9: 805080 | C9: شركة الشاهين للصناعات المعدنية | D9: Al Shaheen Metal Industries Co. | E9: الرياض الثانية | F9: 0505456833 | G9: 0112656565 | H9: ahmed@alshahin.com | I9: 0112651526 | J9: مفتوح | K9: صناعي | L9: منتج | M9: 2014-06-25 | N9: 2033-08-19 | O9: 78345 | P9: 32588 | Q9: =VLOOKUP(B9,[1]Sheet1!$A$1:$F$6212,6,0) -> #N/A
A10: 1010084155 | B10: 807020 | C10: شركة تصنيع مواد التعبئة والتغليف - فيبكو | D10: NULL | E10: الرياض الثانية | F10: 0564994747 | G10: 0112652299 | H10: sms@fipco.com.sa | I10: 0112651275 | J10: مفتوح | K10: صناعي | L10: منتج | M10: 2016-04-30 | N10: 2035-09-24 | O10: 75336 | P10: 33405 | Q10: =VLOOKUP(B10,[1]Sheet1!$A$1:$F$6212,6,0) -> #N/A
A11: 1010057929 | B11: 807304 | C11: مصنع بلاستيك الوطنيه | D11: NULL | E11: الرياض الثانية | F11: 0504818829 | G11: 0112650523 | H11: gs-razak@wataniaind.com | I11: 0112652692 | J11: مفتوح | K11: صناعي | L11: منتج | M11: 2016-10-11 | N11: 2036-03-07 | O11: 66329 | P11: 1/1/53 0:00 | Q11: =VLOOKUP(B11,[1]Sheet1!$A$1:$F$6212,6,0) -> #N/A
A12: 1010070479 | B12: 807351 | C12: الشركة المتحدة للمنتجات الخشبية والمعدنية | D12: NULL | E12: الرياض الثانية | F12: 0505414691 | G12: 0112657777 | H12: info@uwpco.com | I12: 0112652817 | J12: مفتوح | K12: صناعي | L12: منتج | M12: 2016-06-08 | N12: 2022-04-03 | O12: 65776 | P12: 32488 | Q12: =VLOOKUP(B12,[1]Sheet1!$A$1:$F$6212,6,0) -> #N/A
A13: 1010052927 | B13: 21039 | C13: الشركة السعودية الحديثة لصناعة المعادن والكابلات والبلاستيك -الرياض للكابلات والمعادن | D13: Saudi Modern Company for Metals, Cables and Plastic Industry Ltd. (Riyadh Cables and Metals) (RC&M) | E13: الرياض الثانية | F13: 0505232352 | G13: 0112650850 | H13: rcgc@riyadh-cables.com | I13: 0112651423 | J13: مفتوح | K13: صناعي | L13: منتج | M13: 2011-01-01 | N13: 2030-05-27 | O13: 63000 | P13: 2 | Q13: =VLOOKUP(B13,[1]Sheet1!$A$1:$F$6212,6,0) -> #N/A
A14: 1010000320 | B14: 800430 | C14: مصنع معامل الرياض للإنتاج المخملي | D14: Riyadh Labs Factory for the Velvety Production | E14: الرياض الثانية | F14: 0553377774 | G14: 0112651849 | H14: abdullah@rvf.sa | I14: 0112652175 | J14: مفتوح | K14: صناعي | L14: منتج | M14: 2009-08-05 | N14: 2019-04-18 | O14: 60532 | P14: 20972 | Q14: =VLOOKUP(B14,[1]Sheet1!$A$1:$F$6212,6,0) -> #N/A
A15: 1010011738 | B15: 280230 | C15: مصنع الشركة السعودية للطوب الرملي والجيري ومواد البناء | D15: Sand - Lime Brick Factory | E15: الرياض الثانية | F15: 0539404005 | G15: 0112651824 | H15: raedmohmmed@saudilime.com | I15: 0112651175 | J15: مفتوح | K15: صناعي | L15: منتج | M15: 2014-05-13 | N15: 2030-11-09 | O15: 60078 | P15: 28213 | Q15: =VLOOKUP(B15,[1]Sheet1!$A$1:$F$6212,6,0) -> #N/A
A16: 1010049588 | B16: 800463 | C16: شركة الجميح وشل لزيوت التشحيم | D16: Aljomaih and Shell Lubricating Oil Company | E16: الرياض الثانية | F16: 0553678512 | G16: 0112650888 | H16: admin@aljomaihshell.com | I16: 0112650949 | J16: مفتوح | K16: صناعي | L16: منتج | M16: 2009-04-18 | N16: 2018-12-28 | O16: 60000 | P16: 30440 | Q16: =VLOOKUP(B16,[1]Sheet1!$A$1:$F$6212,6,0) -> #N/A
A17: 1010014993 | B17: 800353 | C17: الشركة السعودية لإنتاج الانابيب الفخارية | D17: NULL | E17: الرياض الثانية | F17: 0555333050 | G17: 0114980772 | H17: saad@svcpfactory.com | I17: 0114984815 | J17: مفتوح | K17: صناعي | L17: منتج | M17: 2006-10-30 | N17: 2031-01-30 | O17: 58489 | P17: 28536 | Q17: =VLOOKUP(B17,[1]Sheet1!$A$1:$F$6212,6,0) -> #N/A
A18: 1010009671 | B18: 20675 | C18: شركة المباني الخفيفة - سيبوركس | D18: Light Weight Co. -SIPOREX | E18: الرياض الثانية | F18: 0550002479 | G18: 0114981800 | H18: thamer@lccsiporex.com | I18: 0114982072 | J18: مفتوح | K18: صناعي | L18: منتج | M18: 2002-01-25 | N18: 2026-04-27 | O18: 57560 | P18: 27906 | Q18: =VLOOKUP(B18,[1]Sheet1!$A$1:$F$6212,6,0) -> #N/A
A19: 1010061089 | B19: 290428 | C19: شركة صناعات الخريف | D19: Al-Khorayef Industries Co. | E19: الرياض الثانية | F19: 0503409694 | G19: 0112651124 | H19: factory@alkhorayef.com | I19: 0112652348 | J19: مفتوح | K19: صناعي | L19: منتج | M19: 2008-07-19 | N19: 2030-11-11 | O19: 55533 | P19: 31369 | Q19: =VLOOKUP(B19,[1]Sheet1!$A$1:$F$6212,6,0) -> #N/A
A20: 1010145258 | B20: 804879 | C20: مجمع شركة الفداغي الصناعية | D20: Al-Fadaghi Industrial Company Complex | E20: الرياض الثانية | F20: 0555224242 | G20: 0114953000 | H20: info@alfaddahgi.com | I20: 0114954000 | J20: مفتوح | K20: صناعي | L20: منتج | M20: 2014-03-28 | N20: 2023-12-10 | O20: 54798 | P20: 2 | Q20: =VLOOKUP(B20,[1]Sheet1!$A$1:$F$6212,6,0) -> #N/A
A21: 1010054991 | B21: 808687 | C21: شركة دانيا للأغذية المحدودة | D21: NULL | E21: الرياض الثانية | F21: 0533999097 | G21: 0114981414 | H21: moalt@arlafoods.com | I21: 0114980628 | J21: مفتوح | K21: صناعي | L21: منتج | M21: 2017-08-10 | N21: 2029-04-01 | O21: 54056 | P21: 30853 | Q21: =VLOOKUP(B21,[1]Sheet1!$A$1:$F$6212,6,0) -> #N/A
A22: 1010052201 | B22: 800718 | C22: مجموعة عبدالله شمسان الصناعية | D22: Abdullah Shamsan Industrial Group | E22: الرياض الثانية | F22: 0599919356 | G22: 0112651600 | H22: ahmad@shamsangroup.com | I22: 0112650952 | J22: مفتوح | K22: صناعي | L22: منتج | M22: 2009-11-07 | N22: 2029-04-02 | O22: 53350 | P22: 30648 | Q22: =VLOOKUP(B22,[1]Sheet1!$A$1:$F$6212,6,0) -> #N/A
A23: 1010016778 | B23: 280252 | C23: شركة الدهانات السعودية المحدوده - بينتكو | D23: Saudi Paints Co. | E23: الرياض الثانية | F23: 0505473464 | G23: 0114465555 | H23: Paintco@Paintco.net | I23: 0114460611 | J23: مفتوح | K23: صناعي | L23: منتج | M23: 2007-11-05 | N23: 2031-02-15 | O23: 53075 | P23: 2 | Q23: =VLOOKUP(B23,[1]Sheet1!$A$1:$F$6212,6,0) -> #N/A
... A26: 1010075300 | B26: 804022 | C26: المصنع الوطني لأنتاج العبوات الزجاجية | D26: Saudi National Lighting and Electricity Co. | E26: الرياض الثانية | F26: 0505455753 | G26: 0112652323 | H26: yas@zoujaj-glass.com | I26: 0112651347 | J26: مفتوح | K26: صناعي | L26: منتج | M26: 2013-05-16 | N26: 2032-10-10 | O26: 48454 | P26: 2 | Q26: =VLOOKUP(B26,[1]Sheet1!$A$1:$F$6212,6,0) -> #N/A
A27: 1010061412 | B27: 20153 | C27: شركة أيه بي بي للصناعات الكهربائية | D27: ABB | E27: الرياض الثانية | F27: 0505488292 | G27: 0112653030 | H27: fatahallah.abdulbaqi@sa.abb.com | I27: 0112651211 | J27: مفتوح | K27: صناعي | L27: منتج | M27: 2010-12-30 | N27: 2030-05-25 | O27: 48450 | P27: 1/1/53 0:00 | Q27: =VLOOKUP(B27,[1]Sheet1!$A$1:$F$6212,6,0) -> #N/A
A28: 1010056593 | B28: 290158 | C28: مصنع الجميح لإنتاج العلب | D28: Al-Jomaih Factory for the Production of Cans | E28: الرياض الثانية | F28: 0566669915 | G28: 0112652381 | H28: HTAHER@aljomaihbev.com | I28: 0112651696 | J28: مفتوح | K28: صناعي | L28: منتج | M28: 2008-02-27 | N28: 2030-06-20 | O28: 48000 | P28: 1/1/53 0:00 | Q28: =VLOOKUP(B28,[1]Sheet1!$A$1:$F$6212,6,0) -> #N/A
A29: 1010033645 | B29: 800833 | C29: شركة البلاد للآنابيب الخرسانية المحدودة | D29: NULL | E29: الرياض الثانية | F29: 0504491480 | G29: 0114793531 | H29: info@albiladpipes.com | I29: 0114771372 | J29: مفتوح | K29: صناعي | L29: منتج | M29: 2010-01-23 | N29: 2029-06-19 | O29: 47543 | P29: 29485 | Q29: =VLOOKUP(B29,[1]Sheet1!$A$1:$F$6212,6,0) -> #N/A
A30: - | B30: 808927 | C30: شركة الربيع السعودية للاغذية | D30: Al-Hanaya Restaurant & Supermarket | E30: الرياض الثانية | F30: 0504405214 | G30: 0114980000 | H30: grm@alrabie.com | I30: - | J30: مفتوح | K30: صناعي | L30: منتج | M30: 2017-05-16 | N30: 2030-12-14 | O30: 47126 | P30: 2 | Q30: =VLOOKUP(B30,[1]Sheet1!$A$1:$F$6212,6,0) -> #N/A
A31: 1010106953 | B31: 803849 | C31: الشركة السعودية الحديثة لصناعة الاسلاك والكابلات الكهربائية | D31: Saudi Modern Company for Special Electric Wire & Cables Industry | E31: الرياض الثانية | F31: 0505232352 | G31: 0112650850 | H31: rcgc@riyadh-cables.com | I31: 0112651423 | J31: مفتوح | K31: صناعي | L31: منتج | M31: 2013-05-06 | N31: 2032-09-30 | O31: 46024 | P31: 41753 | Q31: =VLOOKUP(B31,[1]Sheet1!$A$1:$F$6212,6,0) -> #N/A
A32: 1010067273 | B32: 803920 | C32: مصنع الجريسي لصناعة الأثاث | D32: Al- Jeraisy Furniture Factory | E32: الرياض الثانية | F32: 0507839533 | G32: 0114984222 | H32: jff_info@jeraisy.com | I32: 0114982355 | J32: مفتوح | K32: صناعي | L32: منتج | M32: 2014-03-26 | N32: 2032-08-31 | O32: 45000 | P32: 2 | Q32: =VLOOKUP(B32,[1]Sheet1!$A$1:$F$6212,6,0) -> #N/A
A33: 1010139400 | B33: 807043 | C33: مصنع الخضير للصناعات المعدنية | D33: NULL | E33: الرياض الثانية | F33: 0504465224 | G33: 0112652244 | H33: info@alkhodair.com | I33: 0112651294 | J33: مفتوح | K33: صناعي | L33: منتج | M33: 2016-03-15 | N33: 2035-08-09 | O33: 44959 | P33: 35032 | Q33: =VLOOKUP(B33,[1]Sheet1!$A$1:$F$6212,6,0) -> #N/A
A34: 1010029561 | B34: 800403 | C34: المصنع السعودي لأسطوانات الغاز | D34: Saudi Gas Cylinder Factory | E34: الرياض الثانية | F34: 0505450719 | G34: 0112651196 | H34: enagas@enagas.com.sa | I34: 0112652065 | J34: مفتوح | K34: صناعي | L34: منتج | M34: 2014-02-08 | N34: 2018-12-14 | O34: 44250 | P34: 2 | Q34: =VLOOKUP(B34,[1]Sheet1!$A$1:$F$6212,6,0) -> #N/A
A35: 1010026063 | B35: 807709 | C35: الشركة الوطنية المحدودة للجلفنة والأعمدة الحديدية | D35: NULL | E35: الرياض الثانية | F35: 0555458842 | G35: 00966112652078 | H35: Info@galvanco.com | I35: 00966112652079 | J35: مفتوح | K35: صناعي | L35: منتج | M35: 2016-11-14 | N35: 2029-06-25 | O35: 44101 | P35: 28846 | Q35: =VLOOKUP(B35,[1]Sheet1!$A$1:$F$6212,6,0) -> #N/A
A36: 2051000622 | B36: 800398 | C36: مصنع عميقة للفوانيس والأعمدة والجلفنة | D36: National Galvanizing and Coating Company | E36: الرياض الثانية | F36: 0505413790 | G36: 0114984587 | H36: omega@omega-abahsain.com | I36: 0114982383 | J36: مفتوح | K36: صناعي | L36: منتج | M36: 2009-01-04 | N36: 2018-09-16 | O36: 41250 | P36: 31301 | Q36: =VLOOKUP(B36,[1]Sheet1!$A$1:$F$6212,6,0) -> #N/A
A37: 1010006939 | B37: 800369 | C37: شركة المواد العمرانية | D37: NULL | E37: الرياض الثانية | F37: 0563633989 | G37: 0112651837 | H37: almudayfer_group@alomraniah.com | I37: 0112651836 | J37: مفتوح | K37: صناعي | L37: منتج | M37: 2009-06-17 | N37: 2019-02-28 | O37: 40250 | P37: 2 | Q37: =VLOOKUP(B37,[1]Sheet1!$A$1:$F$6212,6,0) -> #N/A
A38: 1010138372 | B38: 807078 | C38: الشركة السعودية للمأكولات الخفيفة المحدودة | D38: Saudi Light Food Co. Ltd. | E38: الرياض الثانية | F38: 0554005464 | G38: 0112018888 | H38: abdullah.al-nafie@pepsico.com | I38: 0112011188 | J38: مفتوح | K38: صناعي | L38: منتج | M38: 2016-03-28 | N38: 2019-02-23 | O38: 40081 | P38: 34987 | Q38: =VLOOKUP(B38,[1]Sheet1!$A$1:$F$6212,6,0) -> #N/A
A39: 1010012057 | B39: 290077 | C39: شركة الانارة السعودية المحدودة | D39: NULL | E39: الرياض الثانية | F39: 0555809749 | G39: 0112651010 | H39: lami@saudilighting.com | I39: 0112652194 | J39: مفتوح | K39: صناعي | L39: منتج | M39: 2008-01-30 | N39: 2030-05-22 | O39: 40050 | P39: 28238 | Q39: =VLOOKUP(B39,[1]Sheet1!$A$1:$F$6212,6,0) -> #N/A
A40: 1010096120 | B40: 807688 | C40: شركة يونيتشارم الخليج للصناعات الصحية المحدودة | D40: Unicharm Gulf Hygienic Industries Company | E40: الرياض الثانية | F40: 0555202393 | G40: 0112651633 | H40: adel-harbi@GulfHygienic.com.sa | I40: 0112651614 | J40: مفتوح | K40: صناعي | L40: منتج | M40: 2016-11-13 | N40: 2036-04-09 | O40: 39006 | P40: 33783 | Q40: =VLOOKUP(B40,[1]Sheet1!$A$1:$F$6212,6,0) -> #N/A
... A50: 1010039827 | B50: 280235 | C50: شركة صناعات العزل العربية - عوازل | D50: Arab Insulation Industries Co. - Insulators | E50: الرياض الثانية | F50: 0505563666 | G50: 0114981604 | H50: hr@awazel.com | I50: 0114981707 | J50: مفتوح | K50: صناعي | L50: منتج | M50: 2007-06-30 | N50: 2030-10-12 | O50: 34500 | P50: 29753 | Q50: =VLOOKUP(B50,[1]Sheet1!$A$1:$F$6212,6,0) -> #N/A
A51: 1010095382 | B51: 808591 | C51: شركة عدوان للصناعات الكيماوية | D51: NULL | E51: الرياض الثانية | F51: 0505466329 | G51: 0112650041 | H51: faisal@adwanchem.com | I51: 0112650023 | J51: مفتوح | K51: صناعي | L51: منتج | M51: 2017-07-18 | N51: 2018-07-07 | O51: 34232 | P51: 1/1/53 0:00 | Q51: =VLOOKUP(B51,[1]Sheet1!$A$1:$F$6212,6,0) -> #N/A
A52: 1010063903 | B52: 805137 | C52: الشركة الوطنية لصناعة الاسمدة الكيماوية | D52: National Chemical Fertilizers Company | E52: الرياض الثانية | F52: 0501311131 | G52: 0112651327 | H52: info@nafkal.com | I52: 012651327 | J52: مفتوح | K52: صناعي | L52: منتج | M52: 2014-07-17 | N52: 2034-12-01 | O52: 33750 | P52: 31712 | Q52: =VLOOKUP(B52,[1]Sheet1!$A$1:$F$6212,6,0) -> #N/A
A53: 1010111255 | B53: 808034 | C53: المصنع السعودي لصناعة الصوف الصخري | D53: Saudi Rock Wool Factory | E53: الرياض الثانية | F53: 0556000064 | G53: 0112650034 | H53: khalid@saudirockwool.com | I53: 0112650073 | J53: مفتوح | K53: صناعي | L53: منتج | M53: 2017-04-07 | N53: 2018-03-26 | O53: 28246 | P53: 2 | Q53: =VLOOKUP(B53,[1]Sheet1!$A$1:$F$6212,6,0) -> #N/A
A54: 1010076996 | B54: 20997 | C54: مصنع الغذائية لتجميد الخضراوات | D54: Al-Ghezaya Ready Foods Factory - Maakolat | E54: الرياض الثانية | F54: 0538739026 | G54: 0112650909 | H54: ali_alsalem@wafrah.com | I54: 0112650606 | J54: مفتوح | K54: صناعي | L54: منتج | M54: 1996-06-19 | N54: 2020-09-19 | O54: 27661 | P54: 33012 | Q54: =VLOOKUP(B54,[1]Sheet1!$A$1:$F$6212,6,0) -> #N/A
A55: 1010000734 | B55: 20151 | C55: مصانع شركة الجميح لتعبئة المرطبات | D55: Al-Jomaih Co. Factories for Refreshment Packaging | E55: الرياض الثانية | F55: 0504112768 | G55: 0112651746 | H55: headoffice@aljomaih.com.sa | I55: 0112651696 | J55: مفتوح | K55: صناعي | L55: منتج | M55: 2014-05-17 | N55: 2030-11-13 | O55: 26790 | P55: 2 | Q55: =VLOOKUP(B55,[1]Sheet1!$A$1:$F$6212,6,0) -> #N/A
A56: 1010102318 | B56: 20158 | C56: الشركة الوطنية لصناعة البطاريات | D56: National Batteries Manufacturing Company | E56: الرياض الثانية | F56: 0500121253 | G56: 0112650019 | H56: sami@battariat.com | I56: 0112650057 | J56: مفتوح | K56: صناعي | L56: منتج | M56: 1994-08-03 | N56: 2018-11-03 | O56: 25000 | P56: 33910 | Q56: =VLOOKUP(B56,[1]Sheet1!$A$1:$F$6212,6,0) -> #N/A
A57: 1010021424 | B57: 807820 | C57: شركة سولزر السعودي للمضخات المحدودة | D57: NULL | E57: الرياض الثانية | F57: 0500544001 | G57: 0112652123 | H57: fahad.subaie@sulzer.com | I57: 0112651071 | J57: مفتوح | K57: صناعي | L57: منتج | M57: 2016-12-06 | N57: 2036-05-02 | O57: 24821 | P57: 28949 | Q57: =VLOOKUP(B57,[1]Sheet1!$A$1:$F$6212,6,0) -> #N/A
A58: 1010171861 | B58: 20650 | C58: الشركة المتحدة للمحولات الكهربائية | D58: United Transformers Electric Co. (UTEC) | E58: الرياض الثانية | F58: 0504816569 | G58: 0114984590 | H58: info@utec.com.sa | I58: 0114983831 | J58: مفتوح | K58: صناعي | L58: منتج | M58: 2003-05-16 | N58: 2027-08-16 | O58: 24500 | P58: 37214 | Q58: =VLOOKUP(B58,[1]Sheet1!$A$1:$F$6212,6,0) -> #N/A
A59: 1010046436 | B59: 800394 | C59: شركة العبيكان للطباعة والنشر | D59: Obeikan Packaging Factory | E59: الرياض الثانية | F59: 0541244376 | G59: 0112651144 | H59: zayed@obeikan.com.sa | I59: 0112650785 | J59: مفتوح | K59: صناعي | L59: منتج | M59: 2009-10-15 | N59: 2019-06-28 | O59: 24450 | P59: 2 | Q59: =VLOOKUP(B59,[1]Sheet1!$A$1:$F$6212,6,0) -> #N/A
A60: 1010066206 | B60: 802701 | C60: مصنع ناردين للإنارة | D60: Nardin Lighting Factory | E60: الرياض الثانية | F60: 0555809749 | G60: 0112652144 | H60: abdullah.lami@philips.com | I60: 0112652194 | J60: مفتوح | K60: صناعي | L60: منتج | M60: 2011-05-20 | N60: 2030-10-14 | O60: 24400 | P60: 31945 | Q60: =VLOOKUP(B60,[1]Sheet1!$A$1:$F$6212,6,0) -> #N/A
A61: 1010149731 | B61: 803821 | C61: شركة اتحاد الخليج للأغذية | D61: Gulf Union Foods Company | E61: الرياض الثانية | F61: 0554200580 | G61: 0112652855 | H61: abrahim@gwf-union.com | I61: 0112652779 | J61: مفتوح | K61: صناعي | L61: منتج | M61: 2013-03-17 | N61: 2018-01-21 | O61: 22454 | P61: 1/1/53 0:00 | Q61: =VLOOKUP(B61,[1]Sheet1!$A$1:$F$6212,6,0) -> #N/A
A62: 1010083670 | B62: 20673 | C62: المصنع السعودي للشماغ | D62: Saudi Shemagh Factory | E62: الرياض الثانية | F62: 0509996786 | G62: 0114980558 | H62: alajlan2000@hotmail.com | I62: 0114980570 | J62: مفتوح | K62: صناعي | L62: منتج | M62: 1998-03-22 | N62: 2022-06-22 | O62: 22000 | P62: 2 | Q62: =VLOOKUP(B62,[1]Sheet1!$A$1:$F$6212,6,0) -> #N/A
A63: 1010437255 | B63: 806703 | C63: مصنع كي أس بي العربية للمضخات المحدودة | D63: KSB Pumps Arabia Company | E63: الرياض الثانية | F63: 0566061867 | G63: 0112652081 | H63: badr-alobaid@ksbarabia.com | I63: 0112651972 | J63: مفتوح | K63: صناعي | L63: منتج | M63: 2015-11-30 | N63: 2020-10-04 | O63: 20961 | P63: 42250 | Q63: =VLOOKUP(B63,[1]Sheet1!$A$1:$F$6212,6,0) -> #N/A
A64: 1010195874 | B64: 806739 | C64: شركة هينكل العربية لمنتجات العناية المنزلية والشخصية | D64: Henkel Arabia for Home and Personal Care Products Co.Ltd | E64: الرياض الثانية | F64: 0505266433 | G64: 0112652655 | H64: daifullah.alsalmi@henkel.com | I64: 0112651856 | J64: مفتوح | K64: صناعي | L64: منتج | M64: 2015-11-30 | N64: 2020-10-04 | O64: 20185 | P64: 38070 | Q64: =VLOOKUP(B64,[1]Sheet1!$A$1:$F$6212,6,0) -> #N/A
A65: 1010131637 | B65: 20751 | C65: شركة المنتجات الطبية والتجميلية - الرياض فارما | D65: Medical & Cosmetic Products Company-Riyadh Pharma | E65: الرياض الثانية | F65: 0540639921 | G65: 0112650111 | H65: mshreah@riyadhpharma.com | I65: 0112650505 | J65: مفتوح | K65: صناعي | L65: منتج | M65: 1995-08-23 | N65: 2019-11-23 | O65: 20000 | P65: 34685 | Q65: =VLOOKUP(B65,[1]Sheet1!$A$1:$F$6212,6,0) -> #N/A
A66: 1010126846 | B66: 807024 | C66: مصنع العبوات البلاستيكية فرع شركة بلاستيك السعودية لأنظمة التغليف | D66: NULL | E66: الرياض الثانية | F66: 0506230374 | G66: 0114985950 | H66: aelgazzar@takweenai.com | I66: 0114985666 | J66: مفتوح | K66: صناعي | L66: منتج | M66: 2016-05-23 | N66: 2035-10-16 | O66: 19977 | P66: 34542 | Q66: =VLOOKUP(B66,[1]Sheet1!$A$1:$F$6212,6,0) -> #N/A
A67: 1010037702 | B67: 808507 | C67: مصنع شركة هرفى للكيك والمعجنات | D67: NULL | E67: الرياض الثانية | F67: 0561444410 | G67: 0114509767 | H67: elkarawi@herfy.com | I67: 0114501824 | J67: مفتوح | K67: صناعي | L67: منتج | M67: 2017-05-31 | N67: 2031-12-18 | O67: 19765 | P67: 29655 | Q67: =VLOOKUP(B67,[1]Sheet1!$A$1:$F$6212,6,0) -> #N/A
A68: - | B68: 808945 | C68: مصنع الفنار للأنظمه الكهربائية | D68: Al-Hanaya Restaurant & Supermarket | E68: الرياض الثانية | F68: 0505400194 | G68: 0112651114 | H68: ahmad.almadani@alfanar.com | I68: - | J68: مفتوح | K68: صناعي | L68: منتج | M68: 2017-05-30 | N68: 2031-12-17 | O68: 15418 | P68: 2 | Q68: =VLOOKUP(B68,[1]Sheet1!$A$1:$F$6212,6,0) -> #N/A
A69: 1010064609 | B69: 808504 | C69: شركة مصانع شنايدر الكيترك العربية السعودية المحدودة | D69: NULL | E69: الرياض الثانية | F69: 0505276127 | G69: 0112651515 | H69: khalid.mubarak@sa.schneider-electric.com | I69: 0112651880 | J69: مفتوح | K69: صناعي | L69: منتج | M69: 2017-05-30 | N69: 2032-12-06 | O69: 13459 | P69: 31780 | Q69: =VLOOKUP(B69,[1]Sheet1!$A$1:$F$6212,6,0) -> #N/A
A70: 1010221531 | B70: 280152 | C70: شركة لازوردي للمجوهرات | D70: NULL | E70: الرياض الثانية | F70: 0505464155 | G70: 0112651119 | H70: abdullah.obaid@lazurde.com | I70: 0112656060 | J70: مفتوح | K70: صناعي | L70: منتج | M70: 2007-06-16 | N70: 2031-09-18 | O70: 12400 | P70: 38920 | Q70: =VLOOKUP(B70,[1]Sheet1!$A$1:$F$6212,6,0) -> #N/A
A71: 1010074777 | B71: 20344 | C71: مصنع العمرانية للرخام والحجر | D71: NULL | E71: الرياض الثانية | F71: 0563633989 | G71: 0112651937 | H71: almudayfer_group@alomraniah.com | I71: 0112654226 | J71: مفتوح | K71: صناعي | L71: منتج | M71: 2009-04-25 | N71: 2019-01-04 | O71: 11000 | P71: 2 | Q71: =VLOOKUP(B71,[1]Sheet1!$A$1:$F$6212,6,0) -> #N/A
A72: 1010138813 | B72: 800903 | C72: شركة الفنار للقوالب | D72: Al-Fanar Molds Co. | E72: الرياض الثانية | F72: 0506026945 | G72: 0114982521 | H72: suwaida@alfanar.com | I72: 0114981108 | J72: مفتوح | K72: صناعي | L72: منتج | M72: 2010-10-09 | N72: 2030-03-05 | O72: 9750 | P72: 35007 | Q72: =VLOOKUP(B72,[1]Sheet1!$A$1:$F$6212,6,0) -> #N/A
A73: 1010037702 | B73: 20994 | C73: شركة هرفي لإنتاج اللحوم | D73: NULL | E73: الرياض الثانية | F73: 0561444410 | G73: 0114509767 | H73: elkarawi@herfy.com | I73: 0114501824 | J73: مفتوح | K73: صناعي | L73: منتج | M73: 1998-12-12 | N73: 2023-03-14 | O73: 9472 | P73: 2 | Q73: =VLOOKUP(B73,[1]Sheet1!$A$1:$F$6212,6,0) -> #N/A
... A94: 1010091172 | B94: 801925 | C94: شركة مصنع المنهل للمياه المحدودة | D94: NULL | E94: الرياض الثانية | F94: 0505463246 | G94: 0112650000 | H94: hodere.alharbi@nestle-waters.com.sa | I94: 0112650934 | J94: مفتوح | K94: صناعي | L94: منتج | M94: 2011-04-23 | N94: 2030-09-16 | O94: 31250 | P94: 33624 | Q94: =VLOOKUP(B94,[1]Sheet1!$A$1:$F$6212,6,0) -> #N/A
A95: 1010075274 | B95: 804710 | C95: الشركة العربية للبلاط المحدودة - ارتك | D95: Arabian Tile Co. Ltd. (ARTIC) | E95: الرياض الثانية | F95: 0593333504 | G95: 0112652101 | H95: info@artic.com.sa | I95: 0112651054 | J95: مفتوح | K95: صناعي | L95: منتج | M95: 2014-02-03 | N95: 2033-06-29 | O95: 30750 | P95: 1/1/53 0:00 | Q95: =VLOOKUP(B95,[1]Sheet1!$A$1:$F$6212,6,0) -> #N/A
A96: 1010041994 | B96: 807766 | C96: الشركة العربية لمنتجات الالياف الزجاجية | D96: NULL | E96: الرياض الثانية | F96: 0505488825 | G96: 0112654041 | H96: info@aliaf.com | I96: 0112651901 | J96: مفتوح | K96: صناعي | L96: منتج | M96: 2016-12-06 | N96: 2028-07-28 | O96: 30053 | P96: 29927 | Q96: =VLOOKUP(B96,[1]Sheet1!$A$1:$F$6212,6,0) -> #N/A
A97: 1010008551 | B97: 807132 | C97: مصنع الرياض للأثاث | D97: Riyadh Furniture Industries Factory | E97: الرياض الثانية | F97: 0555024935 | G97: 0114980808 | H97: info@athath.com | I97: 0114981216 | J97: مفتوح | K97: صناعي | L97: منتج | M97: 2016-04-07 | N97: 2035-09-01 | O97: 30027 | P97: 25859 | Q97: =VLOOKUP(B97,[1]Sheet1!$A$1:$F$6212,6,0) -> #N/A
A98: 1010062598 | B98: 801278 | C98: شركة مشاريع التدفئة والتبريد | D98: Heating & Cooling Projects Company - Golden Star Factory | E98: الرياض الثانية | F98: 0555468543 | G98: 0112651500 | H98: goldenstar@cyberia.net.sa | I98: 0112651521 | J98: مفتوح | K98: صناعي | L98: منتج | M98: 2010-01-13 | N98: 2029-06-08 | O98: 30000 | P98: 31516 | Q98: =VLOOKUP(B98,[1]Sheet1!$A$1:$F$6212,6,0) -> #N/A
A99: 1010152543 | B99: 20318 | C99: شركة المطابع الأهلية للأوفست المحدودة | D99: Civil Offset Priniting Press Co. Ltd. | E99: الرياض الثانية | F99: 0504449021 | G99: 0114057561 | H99: msmi2009@hotmail.com | I99: 0114052703 | J99: مفتوح | K99: صناعي | L99: منتج | M99: 2002-07-07 | N99: 2026-10-06 | O99: 30000 | P99: 36192 | Q99: =VLOOKUP(B99,[1]Sheet1!$A$1:$F$6212,6,0) -> #N/A
A100: 1010109001 | B100: 806538 | C100: مصنع الغزل والنسيج السعودي | D100: NULL | E100: الرياض الثانية | F100: 0553377774 | G100: 0112651848 | H100: abdullah@rvf.sa | I100: 0112652175 | J100: مفتوح | K100: صناعي | L100: منتج | M100: 2014-11-16 | N100: 2034-04-11 | O100: 29998 | P100: 34076 | Q100: =VLOOKUP(B100,[1]Sheet1!$A$1:$F$6212,6,0) -> #N/A
A101: 1010061089 | B101: 804182 | C101: مصنع شركة صناعات الخريف للصناعات المعدنية | D101: Al-Khorayef Industries Co. | E101: الرياض الثانية | F101: 0503409694 | G101: 0112651124 | H101: factory@alkhorayef.com | I101: 0112652348 | J101: مفتوح | K101: صناعي | L101: منتج | M101: 2013-07-17 | N101: 2032-12-11 | O101: 29441 | P101: 31369 | Q101: =VLOOKUP(B101,[1]Sheet1!$A$1:$F$6212,6,0) -> #N/A
A102: 1010077017 | B102: 806637 | C102: الشركة الوطنية لصهر الرصاص | D102: National Lead Smelting Company | E102: الرياض الثانية | F102: 0505454501 | G102: 0112652424 | H102: ab.alfifi@rasass.com.sa | I102: 0112652223 | J102: مفتوح | K102: صناعي | L102: منتج | M102: 2015-08-05 | N102: 2034-12-30 | O102: 28818 | P102: 33013 | Q102: =VLOOKUP(B102,[1]Sheet1!$A$1:$F$6212,6,0) -> #N/A
A103: 1010074602 | B103: 800140 | C103: شركة الراشد للأغذية المحدودة | D103: Al Rashed Food Co. Ltd. | E103: الرياض الثانية | F103: 0505447814 | G103: 0112651394 | H103: alrashedfood@zagil.net | I103: 0112651392 | J103: مفتوح | K103: صناعي | L103: منتج | M103: 2009-03-03 | N103: 2028-07-27 | O103: 28500 | P103: 32841 | Q103: =VLOOKUP(B103,[1]Sheet1!$A$1:$F$6212,6,0) -> #N/A
A104: 1010066351 | B104: 804144 | C104: شركة لامينو السعودية | D104: Saudi Lamino Company | E104: الرياض الثانية | F104: 0500630888 | G104: 0112652325 | H104: ho@saudilamino.com | I104: 0112652169 | J104: مفتوح | K104: صناعي | L104: منتج | M104: 2009-12-08 | N104: 2019-08-21 | O104: 28160 | P104: 1/1/53 0:00 | Q104: =VLOOKUP(B104,[1]Sheet1!$A$1:$F$6212,6,0) -> #N/A
A105: 1010074978 | B105: 806590 | C105: فرع الشركة السعودية للصناعات الميكانيكية | D105: Technical Castings Factory | E105: الرياض الثانية | F105: 0503432319 | G105: 0112651979 | H105: ADMIN@SMI.COM.SA | I105: 0112651494 | J105: مفتوح | K105: صناعي | L105: منتج | M105: 2015-10-21 | N105: 2030-05-09 | O105: 28118 | P105: 32868 | Q105: =VLOOKUP(B105,[1]Sheet1!$A$1:$F$6212,6,0) -> #N/A
A106: 1010010813 | B106: 280211 | C106: مركز سابك الصناعي | D106: NULL | E106: الرياض الثانية | F106: 0504478143 | G106: 0112503131 | H106: alsherehyf@sabic.com | I106: 0112651101 | J106: مفتوح | K106: صناعي | L106: منتج | M106: 2007-06-24 | N106: 2030-10-06 | O106: 27431 | P106: 2 | Q106: =VLOOKUP(B106,[1]Sheet1!$A$1:$F$6212,6,0) -> #N/A
A107: 1010157474 | B107: 280155 | C107: شركة مسبك الرياض لصهر وتشكيل المعادن | D107: Riyadh Foundry Factory for Metal Smelting & Forming | E107: الرياض الثانية | F107: 0505994899 | G107: 0114984323 | H107: info@sudairygroup.com | I107: 0114980395 | J107: مفتوح | K107: صناعي | L107: منتج | M107: 2007-06-16 | N107: 2031-09-18 | O107: 26078 | P107: 32685 | Q107: =VLOOKUP(B107,[1]Sheet1!$A$1:$F$6212,6,0) -> #N/A
A108: 1010192092 | B108: 280494 | C108: مصنع وفور لدرفلة الحديد | D108: Wofour Factory for Steel Rolling | E108: الرياض الثانية | F108: 0544222927 | G108: 0112655580 | H108: Rakanaljohar1@gmail.com | I108: 0112655455 | J108: مفتوح | K108: صناعي | L108: منتج | M108: 2007-10-24 | N108: 2031-02-03 | O108: 26000 | P108: 1/1/53 0:00 | Q108: =VLOOKUP(B108,[1]Sheet1!$A$1:$F$6212,6,0) -> #N/A
A109: 1010247831 | B109: 800188 | C109: مصنع لمار للصناعات الخشبية | D109: Lamar Furniture & Decorations Factory | E109: الرياض الثانية | F109: 0553104850 | G109: 0112656555 | H109: lamar@alfanar.com | I109: 0112655454 | J109: مفتوح | K109: صناعي | L109: منتج | M109: 2009-03-12 | N109: 2030-07-15 | O109: 25822 | P109: 39546 | Q109: =VLOOKUP(B109,[1]Sheet1!$A$1:$F$6212,6,0) -> #N/A
A110: 1010106953 | B110: 803848 | C110: الشركة السعودية الحديثة لصناعة الاسلاك والكابلات الكهربائية | D110: Saudi Modern Company for Special Electric Wire & Cables Industry | E110: الرياض الثانية | F110: 0505232352 | G110: 0112650850 | H110: rcgc@riyadh-cables.com | I110: 0112651423 | J110: مفتوح | K110: صناعي | L110: منتج | M110: 2013-05-06 | N110: 2032-09-30 | O110: 25160 | P110: 2 | Q110: =VLOOKUP(B110,[1]Sheet1!$A$1:$F$6212,6,0) -> #N/A
A111: 1010080589 | B111: 807018 | C111: الشركة العربية لمركبات البلاستيك | D111: Arabian Plastic Compounds Company - APC | E111: الرياض الثانية | F111: 0590000109 | G111: 0112650088 | H111: ricom@apc-spf.com.sa | I111: 0112650330 | J111: مفتوح | K111: صناعي | L111: منتج | M111: 2016-03-12 | N111: 2035-08-06 | O111: 25038 | P111: 33204 | Q111: =VLOOKUP(B111,[1]Sheet1!$A$1:$F$6212,6,0) -> #N/A
A112: 1010217048 | B112: 808060 | C112: مصنع البابطين للاجهزة المنزلية | D112: NULL | E112: الرياض الثانية | F112: 0544902088 | G112: 0112650700 | H112: hrm@abeico.com.sa | I112: 0112651391 | J112: مفتوح | K112: صناعي | L112: منتج | M112: 2017-03-02 | N112: 2032-09-07 | O112: 24803 | P112: 38789 | Q112: =VLOOKUP(B112,[1]Sheet1!$A$1:$F$6212,6,0) -> #N/A
A113: 1010071763 | B113: 805952 | C113: الشركة الوطنية لصناعة الأثاث - أثاث | D113: National Furniture Manufacturing Company - Athath | E113: الرياض الثانية | F113: 0599277735 | G113: 0112651256 | H113: walid@athathco.com | I113: 0112651255 | J113: مفتوح | K113: صناعي | L113: منتج | M113: 2014-10-12 | N113: 2029-05-01 | O113: 24595 | P113: 32595 | Q113: =VLOOKUP(B113,[1]Sheet1!$A$1:$F$6212,6,0) -> #N/A
A114: 1010014590 | B114: 800784 | C114: شركة الخزف السعودية | D114: Saudi Ceramic Company | E114: الرياض الثانية | F114: 0504103118 | G114: 0112650265 | H114: alenzie@saudiceramics.com | I114: 0112653333 | J114: مفتوح | K114: صناعي | L114: منتج | M114: 2010-04-13 | N114: 2029-09-06 | O114: 24200 | P114: 28514 | Q114: =VLOOKUP(B114,[1]Sheet1!$A$1:$F$6212,6,0) -> #N/A
A115: 1010053015 | B115: 800470 | C115: مصنع الشركة الوطنية لمواد التعبئة المحدودة - وطن باك | D115: National Packing Materials Co. Ltd. - Watan Pack | E115: الرياض الثانية | F115: 0531169539 | G115: 0112652211 | H115: wadi@watanpac.com.sa | I115: 0112652483 | J115: مفتوح | K115: صناعي | L115: منتج | M115: 2009-10-21 | N115: 2019-07-04 | O115: 23100 | P115: 30703 | Q115: =VLOOKUP(B115,[1]Sheet1!$A$1:$F$6212,6,0) -> #N/A
A116: 1010061353 | B116: 807690 | C116: شركة عبدالله بن علي الشريف وشركاه للعبوات الكرتونية | D116: NULL | E116: الرياض الثانية | F116: 0505488354 | G116: 0114989944 | H116: hasan.alshareef@gmail.com | I116: 0114980294 | J116: مفتوح | K116: صناعي | L116: منتج | M116: 2016-11-14 | N116: 2027-07-17 | O116: 22851 | P116: 26809 | Q116: =VLOOKUP(B116,[1]Sheet1!$A$1:$F$6212,6,0) -> #N/A
A117: 1010014590 | B117: 800249 | C117: شركة الخزف السعودية | D117: Saudi Ceramic Company | E117: الرياض الثانية | F117: 0504103118 | G117: 0112650265 | H117: alenzie@saudiceramics.com | I117: 0112653333 | J117: مفتوح | K117: صناعي | L117: منتج | M117: 2009-02-28 | N117: 2018-11-10 | O117: 22500 | P117: 28514 | Q117: =VLOOKUP(B117,[1]Sheet1!$A$1:$F$6212,6,0) -> #N/A
A118: - | B118: 808931 | C118: شركة الشرق للصناعات البلاستيكية | D118: Al-Hanaya Restaurant & Supermarket | E118: الرياض الثانية | F118: 0501627177 | G118: 0112655555 | H118: ronazi@savola.com | I118: - | J118: مفتوح | K118: صناعي | L118: منتج | M118: 2017-09-24 | N118: 2028-05-27 | O118: 22389 | P118: 2 | Q118: =VLOOKUP(B118,[1]Sheet1!$A$1:$F$6212,6,0) -> #N/A
A119: 1010064067 | B119: 20237 | C119: شركة مصنع اليات النظافة المحدودة | D119: Al-Rubaian Factory Co. for Hand Carts and Janitorial Tasks | E119: الرياض الثانية | F119: 0504132987 | G119: 0112652066 | H119: osama@rem-ksa.com | I119: 0112652068 | J119: مفتوح | K119: صناعي | L119: منتج | M119: 2003-08-25 | N119: 2027-11-25 | O119: 22200 | P119: 31727 | Q119: =VLOOKUP(B119,[1]Sheet1!$A$1:$F$6212,6,0) -> #N/A
A120: 1010027369 | B120: 800422 | C120: شركة الصناعات المعدنية والفضية والذهبية | D120: Metal, Silver and Gold Industries Company | E120: الرياض الثانية | F120: 0505462387 | G120: 0114981276 | H120: mesigoco@yahoo.com | I120: 0114983148 | J120: مفتوح | K120: صناعي | L120: منتج | M120: 2009-01-31 | N120: 2028-06-27 | O120: 22141 | P120: 29218 | Q120: =VLOOKUP(B120,[1]Sheet1!$A$1:$F$6212,6,0) -> #N/A
... A126: - | B126: 808939 | C126: مصانع الشرق للتغليف | D126: Al-Hanaya Restaurant & Supermarket | E126: الرياض الثانية | F126: 0545026109 | G126: 0112655551 | H126: pr@alsharg-pl.com.sa | I126: - | J126: مفتوح | K126: صناعي | L126: منتج | M126: 2017-11-02 | N126: 2022-09-08 | O126: 20211 | P126: 2 | Q126: =VLOOKUP(B126,[1]Sheet1!$A$1:$F$6212,6,0) -> #N/A
A127: 1010012450 | B127: 801665 | C127: الشركة الوطنية للمنتجات الطبية المحدودة | D127: National Medical Products Co. Ltd. | E127: الرياض الثانية | F127: 0503495331 | G127: 0114981666 | H127: Faisal.almaammar@damad.com | I127: 0114985607 | J127: مفتوح | K127: صناعي | L127: منتج | M127: 2011-03-31 | N127: 2030-08-25 | O127: 20047 | P127: 1/1/53 0:00 | Q127: =VLOOKUP(B127,[1]Sheet1!$A$1:$F$6212,6,0) -> #N/A
A128: 1010112398 | B128: 803214 | C128: شركة ميس السعودية للمنتجات الطبيه المحدودة | D128: Saudi Mais Company for Medical Products | E128: الرياض الثانية | F128: 0556262527 | G128: 0112650184 | H128: fm@mais.com.sa | I128: 0112650139 | J128: مفتوح | K128: صناعي | L128: منتج | M128: 2012-09-17 | N128: 2032-02-12 | O128: 20000 | P128: 2 | Q128: =VLOOKUP(B128,[1]Sheet1!$A$1:$F$6212,6,0) -> #N/A
A129: 1010002481 | B129: 804141 | C129: مصنع البلاستيك السعودي | D129: Saudi Plastic Factory (SPF) | E129: الرياض الثانية | F129: 0556244000 | G129: 0114982807 | H129: spfi@awalnet.net.sa | I129: 0114983731 | J129: مفتوح | K129: صناعي | L129: منتج | M129: 2009-06-02 | N129: 2019-02-13 | O129: 20000 | P129: 23092 | Q129: =VLOOKUP(B129,[1]Sheet1!$A$1:$F$6212,6,0) -> #N/A
A130: 1010206707 | B130: 807681 | C130: مصنع الغذائية للمكرونة والشعيرية | D130: NULL | E130: الرياض الثانية | F130: 0538739026 | G130: 0112650909 | H130: ali_alaslem@wafrah.com | I130: 0112650606 | J130: مفتوح | K130: صناعي | L130: منتج | M130: 2016-12-09 | N130: 2036-05-05 | O130: 19938 | P130: 38424 | Q130: =VLOOKUP(B130,[1]Sheet1!$A$1:$F$6212,6,0) -> #N/A
A131: - | B131: 808937 | C131: صافية لمياه الشرب المعبأة | D131: Al-Hanaya Restaurant & Supermarket | E131: الرياض الثانية | F131: 0505473143 | G131: 0112651412 | H131: rb@safiawater.com | I131: - | J131: مفتوح | K131: صناعي | L131: منتج | M131: 2017-11-22 | N131: 2033-05-31 | O131: 19908 | P131: 2 | Q131: =VLOOKUP(B131,[1]Sheet1!$A$1:$F$6212,6,0) -> #N/A
A132: 1010144330 | B132: 801114 | C132: المصنع السعودي لعزل الأنابيب | D132: Saudi Pipe Insulation Factory | E132: الرياض الثانية | F132: 0502888055 | G132: 0112651414 | H132: sppi@sppi-llc.com | I132: 0112651474 | J132: مفتوح | K132: صناعي | L132: منتج | M132: 2010-08-16 | N132: 2030-01-09 | O132: 19825 | P132: 2 | Q132: =VLOOKUP(B132,[1]Sheet1!$A$1:$F$6212,6,0) -> #N/A
A133: 1010012057 | B133: 800460 | C133: شركة الانارة السعودية المحدودة | D133: NULL | E133: الرياض الثانية | F133: 0555809749 | G133: 0112651010 | H133: lami@saudilighting.com | I133: 0112652194 | J133: مفتوح | K133: صناعي | L133: منتج | M133: 2014-01-09 | N133: 2018-11-15 | O133: 19662 | P133: 28238 | Q133: =VLOOKUP(B133,[1]Sheet1!$A$1:$F$6212,6,0) -> #N/A
A134: 1010009673 | B134: 20486 | C134: مصنع منير المنيف للمنتجات البلاستيكية | D134: Mounir Abdullah Al-Moneef Factory for Plastic Pipes & Accessories | E134: الرياض الثانية | F134: 0553330022 | G134: 0112652533 | H134: mmp@sol.net.sa | I134: 0112651845 | J134: مفتوح | K134: صناعي | L134: منتج | M134: 2013-11-19 | N134: 2029-05-28 | O134: 19050 | P134: 2 | Q134: =VLOOKUP(B134,[1]Sheet1!$A$1:$F$6212,6,0) -> #N/A
A135: 1010000734 | B135: 21288 | C135: مصنع الجميح لصناعة صناديق السيارات والثلاجات | D135: Al-Jomaih Co. Factories for Refreshment Packaging | E135: الرياض الثانية | F135: 0505444141 | G135: 0114763824 | H135: SSaqer@ALJOMAIHBEV.com | I135: 0112919701 | J135: مفتوح | K135: صناعي | L135: منتج | M135: 2014-05-17 | N135: 2030-11-13 | O135: 18991 | P135: 2 | Q135: =VLOOKUP(B135,[1]Sheet1!$A$1:$F$6212,6,0) -> #N/A
A136: - | B136: 808957 | C136: مصنع الوطن للأثاث الخشبي والمعدني ويرادات المياه | D136: Al-Hanaya Restaurant & Supermarket | E136: الرياض الثانية | F136: 0505401247 | G136: 0114480068 | H136: alwatan@alwatanfac.com.sa | I136: - | J136: مفتوح | K136: صناعي | L136: منتج | M136: 2017-03-16 | N136: 2036-08-08 | O136: 18719 | P136: 2 | Q136: =VLOOKUP(B136,[1]Sheet1!$A$1:$F$6212,6,0) -> #N/A
...

Sheet Sheet4
A1: رقم السجل التجاري | B1: رقم العقد | C1: العميل | D1: Name of factories | E1: المدينة | F1: Mobile | G1: Phone | H1: Email | I1: Fax | J1: حالة العميل | K1: نوع الأرض | L1: حالة الإنشائية | M1: تاريخ البدء | N1: تاريخ الإنتهاء | O1: Area | P1: تاريخ إصدار السجل التجاري | Q1: الأنشطة الصناعية
A2: 1010014590 | B2: 800785 | C2: شركة الخزف السعودية | D2: Saudi Ceramic Company | E2: الرياض الثانية | F2: 0504103118 | G2: 0112650265 | H2: alenzie@saudiceramics.com | I2: 0112653333 | J2: مفتوح | K2: صناعي | L2: منتج | M2: 2010-04-13 | N2: 2029-09-06 | O2: 269982 | P2: 28514 | Q2: =VLOOKUP(B2,[1]Sheet1!$A$1:$F$6212,6,0) -> #N/A
A3: 1010085734 | B3: 806537 | C3: مصنع الشركة العربية للانابيب | D3: Arabian Pipes Company | E3: الرياض الثانية | F3: 0503478702 | G3: 0112650123 | H3: info@arabian-pipes.com | I3: 0112650312 | J3: مفتوح | K3: صناعي | L3: منتج | M3: 2014-11-16 | N3: 2034-04-11 | O3: 228167 | P3: 33474 | Q3: =VLOOKUP(B3,[1]Sheet1!$A$1:$F$6212,6,0) -> #N/A
A4: 1010010813 | B4: 806733 | C4: مركز سابك الصناعي | D4: NULL | E4: الرياض الثانية | F4: 0504478143 | G4: 0112503131 | H4: alsherehyf@sabic.com | I4: 0112651101 | J4: مفتوح | K4: صناعي | L4: منتج | M4: 2014-05-08 | N4: 2019-03-15 | O4: 192746 | P4: 28129 | Q4: =VLOOKUP(B4,[1]Sheet1!$A$1:$F$6212,6,0) -> #N/A
A5: 1010029494 | B5: 800350 | C5: الراشد ايه بيوتنج | D5: Al-Rashid Abetong Co. Ltd. | E5: الرياض الثانية | F5: 0503155602 | G5: 0114981222 | H5: ahmed@alrashidabetong.com | I5: 0112792448 | J5: مفتوح | K5: صناعي | L5: منتج | M5: 2009-07-19 | N5: 2019-04-01 | O5: 183576 | P5: 2 | Q5: =VLOOKUP(B5,[1]Sheet1!$A$1:$F$6212,6,0) -> #N/A
A6: 1010008551 | B6: 807131 | C6: مصنع الرياض للأثاث | D6: Riyadh Furniture Industries Factory | E6: الرياض الثانية | F6: 0506424801 | G6: 0114981216 | H6: info@athath.com | I6: 014981216 | J6: مفتوح | K6: صناعي | L6: منتج | M6: 2016-04-07 | N6: 2035-09-01 | O6: 146484 | P6: 27631 | Q6: =VLOOKUP(B6,[1]Sheet1!$A$1:$F$6212,6,0) -> #N/A
A7: 1010064131 | B7: 807391 | C7: مصنع البابطين للاعمدة والصواري المجلفنة وملحقاتها | D7: #N/A | E7: الرياض الثانية | F7: 0505273911 | G7: 0112650003 | H7: kaha-yami@al-babtain.com.sa | I7: 0112651983 | J7: مفتوح | K7: صناعي | L7: منتج | M7: 2016-06-19 | N7: 2032-12-16 | O7: 124082 | P7: 31734 | Q7: =VLOOKUP(B7,[1]Sheet1!$A$1:$F$6212,6,0) -> #N/A
A8: 1010073685 | B8: 807629 | C8: شركة العبداللطيف للأستثمار الصناعي | D8: Al-Abdullatif Industrial Investment Company | E8: الرياض الثانية | F8: 0505757403 | G8: 0112658888 | H8: jaber@carpets.com | I8: 0112659999 | J8: مفتوح | K8: صناعي | L8: منتج | M8: 2016-10-23 | N8: 2030-05-23 | O8: 114917 | P8: 32777 | Q8: =VLOOKUP(B8,[1]Sheet1!$A$1:$F$6212,6,0) -> #N/A
A9: 1010071668 | B9: 805080 | C9: شركة الشاهين للصناعات المعدنية | D9: Al Shaheen Metal Industries Co. | E9: الرياض الثانية | F9: 0505456833 | G9: 0112656565 | H9: ahmed@alshahin.com | I9: 0112651526 | J9: مفتوح | K9: صناعي | L9: منتج | M9: 2014-06-25 | N9: 2033-08-19 | O9: 78345 | P9: 32588 | Q9: =VLOOKUP(B9,[1]Sheet1!$A$1:$F$6212,6,0) -> #N/A
A10: 1010084155 | B10: 807020 | C10: شركة تصنيع مواد التعبئة والتغليف - فيبكو | D10: NULL | E10: الرياض الثانية | F10: 0564994747 | G10: 0112652299 | H10: sms@fipco.com.sa | I10: 0112651275 | J10: مفتوح | K10: صناعي | L10: منتج | M10: 2016-04-30 | N10: 2035-09-24 | O10: 75336 | P10: 33405 | Q10: =VLOOKUP(B10,[1]Sheet1!$A$1:$F$6212,6,0) -> #N/A
A11: 1010057929 | B11: 807304 | C11: مصنع بلاستيك الوطنيه | D11: NULL | E11: الرياض الثانية | F11: 0504818829 | G11: 0112650523 | H11: gs-razak@wataniaind.com | I11: 0112652692 | J11: مفتوح | K11: صناعي | L11: منتج | M11: 2016-10-11 | N11: 2036-03-07 | O11: 66329 | P11: 1/1/53 0:00 | Q11: =VLOOKUP(B11,[1]Sheet1!$A$1:$F$6212,6,0) -> #N/A
A12: 1010070479 | B12: 807351 | C12: الشركة المتحدة للمنتجات الخشبية والمعدنية | D12: NULL | E12: الرياض الثانية | F12: 0505414691 | G12: 0112657777 | H12: info@uwpco.com | I12: 0112652817 | J12: مفتوح | K12: صناعي | L12: منتج | M12: 2016-06-08 | N12: 2022-04-03 | O12: 65776 | P12: 32488 | Q12: =VLOOKUP(B12,[1]Sheet1!$A$1:$F$6212,6,0) -> #N/A
A13: 1010052927 | B13: 21039 | C13: الشركة السعودية الحديثة لصناعة المعادن والكابلات والبلاستيك -الرياض للكابلات والمعادن | D13: Saudi Modern Company for Metals, Cables and Plastic Industry Ltd. (Riyadh Cables and Metals) (RC&M) | E13: الرياض الثانية | F13: 0505232352 | G13: 0112650850 | H13: rcgc@riyadh-cables.com | I13: 0112651423 | J13: مفتوح | K13: صناعي | L13: منتج | M13: 2011-01-01 | N13: 2030-05-27 | O13: 63000 | P13: 2 | Q13: =VLOOKUP(B13,[1]Sheet1!$A$1:$F$6212,6,0) -> #N/A
A14: 1010000320 | B14: 800430 | C14: مصنع معامل الرياض للإنتاج المخملي | D14: Riyadh Labs Factory for the Velvety Production | E14: الرياض الثانية | F14: 0553377774 | G14: 0112651849 | H14: abdullah@rvf.sa | I14: 0112652175 | J14: مفتوح | K14: صناعي | L14: منتج | M14: 2009-08-05 | N14: 2019-04-18 | O14: 60532 | P14: 20972 | Q14: =VLOOKUP(B14,[1]Sheet1!$A$1:$F$6212,6,0) -> #N/A
A15: 1010011738 | B15: 280230 | C15: مصنع الشركة السعودية للطوب الرملي والجيري ومواد البناء | D15: Sand - Lime Brick Factory | E15: الرياض الثانية | F15: 0539404005 | G15: 0112651824 | H15: raedmohmmed@saudilime.com | I15: 0112651175 | J15: مفتوح | K15: صناعي | L15: منتج | M15: 2014-05-13 | N15: 2030-11-09 | O15: 60078 | P15: 28213 | Q15: =VLOOKUP(B15,[1]Sheet1!$A$1:$F$6212,6,0) -> #N/A
A16: 1010049588 | B16: 800463 | C16: شركة الجميح وشل لزيوت التشحيم | D16: Aljomaih and Shell Lubricating Oil Company | E16: الرياض الثانية | F16: 0553678512 | G16: 0112650888 | H16: admin@aljomaihshell.com | I16: 0112650949 | J16: مفتوح | K16: صناعي | L16: منتج | M16: 2009-04-18 | N16: 2018-12-28 | O16: 60000 | P16: 30440 | Q16: =VLOOKUP(B16,[1]Sheet1!$A$1:$F$6212,6,0) -> #N/A
A17: 1010014993 | B17: 800353 | C17: الشركة السعودية لإنتاج الانابيب الفخارية | D17: NULL | E17: الرياض الثانية | F17: 0555333050 | G17: 0114980772 | H17: saad@svcpfactory.com | I17: 0114984815 | J17: مفتوح | K17: صناعي | L17: منتج | M17: 2006-10-30 | N17: 2031-01-30 | O17: 58489 | P17: 28536 | Q17: =VLOOKUP(B17,[1]Sheet1!$A$1:$F$6212,6,0) -> #N/A
A18: 1010009671 | B18: 20675 | C18: شركة المباني الخفيفة - سيبوركس | D18: Light Weight Co. -SIPOREX | E18: الرياض الثانية | F18: 0550002479 | G18: 0114981800 | H18: thamer@lccsiporex.com | I18: 0114982072 | J18: مفتوح | K18: صناعي | L18: منتج | M18: 2002-01-25 | N18: 2026-04-27 | O18: 57560 | P18: 27906 | Q18: =VLOOKUP(B18,[1]Sheet1!$A$1:$F$6212,6,0) -> #N/A
A19: 1010061089 | B19: 290428 | C19: شركة صناعات الخريف | D19: Al-Khorayef Industries Co. | E19: الرياض الثانية | F19: 0503409694 | G19: 0112651124 | H19: factory@alkhorayef.com | I19: 0112652348 | J19: مفتوح | K19: صناعي | L19: منتج | M19: 2008-07-19 | N19: 2030-11-11 | O19: 55533 | P19: 31369 | Q19: =VLOOKUP(B19,[1]Sheet1!$A$1:$F$6212,6,0) -> #N/A
A20: 1010145258 | B20: 804879 | C20: مجمع شركة الفداغي الصناعية | D20: Al-Fadaghi Industrial Company Complex | E20: الرياض الثانية | F20: 0555224242 | G20: 0114953000 | H20: info@alfaddahgi.com | I20: 0114954000 | J20: مفتوح | K20: صناعي | L20: منتج | M20: 2014-03-28 | N20: 2023-12-10 | O20: 54798 | P20: 2 | Q20: =VLOOKUP(B20,[1]Sheet1!$A$1:$F$6212,6,0) -> #N/A
A21: 1010054991 | B21: 808687 | C21: شركة دانيا للأغذية المحدودة | D21: NULL | E21: الرياض الثانية | F21: 0533999097 | G21: 0114981414 | H21: moalt@arlafoods.com | I21: 0114980628 | J21: مفتوح | K21: صناعي | L21: منتج | M21: 2017-08-10 | N21: 2029-04-01 | O21: 54056 | P21: 30853 | Q21: =VLOOKUP(B21,[1]Sheet1!$A$1:$F$6212,6,0) -> #N/A
A22: 1010052201 | B22: 800718 | C22: مجموعة عبدالله شمسان الصناعية | D22: Abdullah Shamsan Industrial Group | E22: الرياض الثانية | F22: 0599919356 | G22: 0112651600 | H22: ahmad@shamsangroup.com | I22: 0112650952 | J22: مفتوح | K22: صناعي | L22: منتج | M22: 2009-11-07 | N22: 2029-04-02 | O22: 53350 | P22: 30648 | Q22: =VLOOKUP(B22,[1]Sheet1!$A$1:$F$6212,6,0) -> #N/A
A23: 1010016778 | B23: 280252 | C23: شركة الدهانات السعودية المحدوده - بينتكو | D23: Saudi Paints Co. | E23: الرياض الثانية | F23: 0505473464 | G23: 0114465555 | H23: Paintco@Paintco.net | I23: 0114460611 | J23: مفتوح | K23: صناعي | L23: منتج | M23: 2007-11-05 | N23: 2031-02-15 | O23: 53075 | P23: 2 | Q23: =VLOOKUP(B23,[1]Sheet1!$A$1:$F$6212,6,0) -> #N/A
... A26: 1010075300 | B26: 804022 | C26: المصنع الوطني لأنتاج العبوات الزجاجية | D26: Saudi National Lighting and Electricity Co. | E26: الرياض الثانية | F26: 0505455753 | G26: 0112652323 | H26: yas@zoujaj-glass.com | I26: 0112651347 | J26: مفتوح | K26: صناعي | L26: منتج | M26: 2013-05-16 | N26: 2032-10-10 | O26: 48454 | P26: 2 | Q26: =VLOOKUP(B26,[1]Sheet1!$A$1:$F$6212,6,0) -> #N/A
A27: 1010061412 | B27: 20153 | C27: شركة أيه بي بي للصناعات الكهربائية | D27: ABB | E27: الرياض الثانية | F27: 0505488292 | G27: 0112653030 | H27: fatahallah.abdulbaqi@sa.abb.com | I27: 0112651211 | J27: مفتوح | K27: صناعي | L27: منتج | M27: 2010-12-30 | N27: 2030-05-25 | O27: 48450 | P27: 1/1/53 0:00 | Q27: =VLOOKUP(B27,[1]Sheet1!$A$1:$F$6212,6,0) -> #N/A
A28: 1010056593 | B28: 290158 | C28: مصنع الجميح لإنتاج العلب | D28: Al-Jomaih Factory for the Production of Cans | E28: الرياض الثانية | F28: 0566669915 | G28: 0112652381 | H28: HTAHER@aljomaihbev.com | I28: 0112651696 | J28: مفتوح | K28: صناعي | L28: منتج | M28: 2008-02-27 | N28: 2030-06-20 | O28: 48000 | P28: 1/1/53 0:00 | Q28: =VLOOKUP(B28,[1]Sheet1!$A$1:$F$6212,6,0) -> #N/A
A29: 1010033645 | B29: 800833 | C29: شركة البلاد للآنابيب الخرسانية المحدودة | D29: NULL | E29: الرياض الثانية | F29: 0504491480 | G29: 0114793531 | H29: info@albiladpipes.com | I29: 0114771372 | J29: مفتوح | K29: صناعي | L29: منتج | M29: 2010-01-23 | N29: 2029-06-19 | O29: 47543 | P29: 29485 | Q29: =VLOOKUP(B29,[1]Sheet1!$A$1:$F$6212,6,0) -> #N/A
A30: - | B30: 808927 | C30: شركة الربيع السعودية للاغذية | D30: Al-Hanaya Restaurant & Supermarket | E30: الرياض الثانية | F30: 0504405214 | G30: 0114980000 | H30: grm@alrabie.com | I30: - | J30: مفتوح | K30: صناعي | L30: منتج | M30: 2017-05-16 | N30: 2030-12-14 | O30: 47126 | P30: 2 | Q30: =VLOOKUP(B30,[1]Sheet1!$A$1:$F$6212,6,0) -> #N/A
A31: 1010106953 | B31: 803849 | C31: الشركة السعودية الحديثة لصناعة الاسلاك والكابلات الكهربائية | D31: Saudi Modern Company for Special Electric Wire & Cables Industry | E31: الرياض الثانية | F31: 0505232352 | G31: 0112650850 | H31: rcgc@riyadh-cables.com | I31: 0112651423 | J31: مفتوح | K31: صناعي | L31: منتج | M31: 2013-05-06 | N31: 2032-09-30 | O31: 46024 | P31: 41753 | Q31: =VLOOKUP(B31,[1]Sheet1!$A$1:$F$6212,6,0) -> #N/A
A32: 1010067273 | B32: 803920 | C32: مصنع الجريسي لصناعة الأثاث | D32: Al- Jeraisy Furniture Factory | E32: الرياض الثانية | F32: 0507839533 | G32: 0114984222 | H32: jff_info@jeraisy.com | I32: 0114982355 | J32: مفتوح | K32: صناعي | L32: منتج | M32: 2014-03-26 | N32: 2032-08-31 | O32: 45000 | P32: 2 | Q32: =VLOOKUP(B32,[1]Sheet1!$A$1:$F$6212,6,0) -> #N/A
A33: 1010139400 | B33: 807043 | C33: مصنع الخضير للصناعات المعدنية | D33: NULL | E33: الرياض الثانية | F33: 0504465224 | G33: 0112652244 | H33: info@alkhodair.com | I33: 0112651294 | J33: مفتوح | K33: صناعي | L33: منتج | M33: 2016-03-15 | N33: 2035-08-09 | O33: 44959 | P33: 35032 | Q33: =VLOOKUP(B33,[1]Sheet1!$A$1:$F$6212,6,0) -> #N/A
A34: 1010029561 | B34: 800403 | C34: المصنع السعودي لأسطوانات الغاز | D34: Saudi Gas Cylinder Factory | E34: الرياض الثانية | F34: 0505450719 | G34: 0112651196 | H34: enagas@enagas.com.sa | I34: 0112652065 | J34: مفتوح | K34: صناعي | L34: منتج | M34: 2014-02-08 | N34: 2018-12-14 | O34: 44250 | P34: 2 | Q34: =VLOOKUP(B34,[1]Sheet1!$A$1:$F$6212,6,0) -> #N/A
A35: 1010026063 | B35: 807709 | C35: الشركة الوطنية المحدودة للجلفنة والأعمدة الحديدية | D35: NULL | E35: الرياض الثانية | F35: 0555458842 | G35: 00966112652078 | H35: Info@galvanco.com | I35: 00966112652079 | J35: مفتوح | K35: صناعي | L35: منتج | M35: 2016-11-14 | N35: 2029-06-25 | O35: 44101 | P35: 28846 | Q35: =VLOOKUP(B35,[1]Sheet1!$A$1:$F$6212,6,0) -> #N/A
A36: 2051000622 | B36: 800398 | C36: مصنع عميقة للفوانيس والأعمدة والجلفنة | D36: National Galvanizing and Coating Company | E36: الرياض الثانية | F36: 0505413790 | G36: 0114984587 | H36: omega@omega-abahsain.com | I36: 0114982383 | J36: مفتوح | K36: صناعي | L36: منتج | M36: 2009-01-04 | N36: 2018-09-16 | O36: 41250 | P36: 31301 | Q36: =VLOOKUP(B36,[1]Sheet1!$A$1:$F$6212,6,0) -> #N/A
A37: 1010006939 | B37: 800369 | C37: شركة المواد العمرانية | D37: NULL | E37: الرياض الثانية | F37: 0563633989 | G37: 0112651837 | H37: almudayfer_group@alomraniah.com | I37: 0112651836 | J37: مفتوح | K37: صناعي | L37: منتج | M37: 2009-06-17 | N37: 2019-02-28 | O37: 40250 | P37: 2 | Q37: =VLOOKUP(B37,[1]Sheet1!$A$1:$F$6212,6,0) -> #N/A
A38: 1010138372 | B38: 807078 | C38: الشركة السعودية للمأكولات الخفيفة المحدودة | D38: Saudi Light Food Co. Ltd. | E38: الرياض الثانية | F38: 0554005464 | G38: 0112018888 | H38: abdullah.al-nafie@pepsico.com | I38: 0112011188 | J38: مفتوح | K38: صناعي | L38: منتج | M38: 2016-03-28 | N38: 2019-02-23 | O38: 40081 | P38: 34987 | Q38: =VLOOKUP(B38,[1]Sheet1!$A$1:$F$6212,6,0) -> #N/A
A39: 1010012057 | B39: 290077 | C39: شركة الانارة السعودية المحدودة | D39: NULL | E39: الرياض الثانية | F39: 0555809749 | G39: 0112651010 | H39: lami@saudilighting.com | I39: 0112652194 | J39: مفتوح | K39: صناعي | L39: منتج | M39: 2008-01-30 | N39: 2030-05-22 | O39: 40050 | P39: 28238 | Q39: =VLOOKUP(B39,[1]Sheet1!$A$1:$F$6212,6,0) -> #N/A
A40: 1010096120 | B40: 807688 | C40: شركة يونيتشارم الخليج للصناعات الصحية المحدودة | D40: Unicharm Gulf Hygienic Industries Company | E40: الرياض الثانية | F40: 0555202393 | G40: 0112651633 | H40: adel-harbi@GulfHygienic.com.sa | I40: 0112651614 | J40: مفتوح | K40: صناعي | L40: منتج | M40: 2016-11-13 | N40: 2036-04-09 | O40: 39006 | P40: 33783 | Q40: =VLOOKUP(B40,[1]Sheet1!$A$1:$F$6212,6,0) -> #N/A
... A50: 1010039827 | B50: 280235 | C50: شركة صناعات العزل العربية - عوازل | D50: Arab Insulation Industries Co. - Insulators | E50: الرياض الثانية | F50: 0505563666 | G50: 0114981604 | H50: hr@awazel.com | I50: 0114981707 | J50: مفتوح | K50: صناعي | L50: منتج | M50: 2007-06-30 | N50: 2030-10-12 | O50: 34500 | P50: 29753 | Q50: =VLOOKUP(B50,[1]Sheet1!$A$1:$F$6212,6,0) -> #N/A
A51: 1010095382 | B51: 808591 | C51: شركة عدوان للصناعات الكيماوية | D51: NULL | E51: الرياض الثانية | F51: 0505466329 | G51: 0112650041 | H51: faisal@adwanchem.com | I51: 0112650023 | J51: مفتوح | K51: صناعي | L51: منتج | M51: 2017-07-18 | N51: 2018-07-07 | O51: 34232 | P51: 1/1/53 0:00 | Q51: =VLOOKUP(B51,[1]Sheet1!$A$1:$F$6212,6,0) -> #N/A
A52: 1010063903 | B52: 805137 | C52: الشركة الوطنية لصناعة الاسمدة الكيماوية | D52: National Chemical Fertilizers Company | E52: الرياض الثانية | F52: 0501311131 | G52: 0112651327 | H52: info@nafkal.com | I52: 012651327 | J52: مفتوح | K52: صناعي | L52: منتج | M52: 2014-07-17 | N52: 2034-12-01 | O52: 33750 | P52: 31712 | Q52: =VLOOKUP(B52,[1]Sheet1!$A$1:$F$6212,6,0) -> #N/A
A53: 1010111255 | B53: 808034 | C53: المصنع السعودي لصناعة الصوف الصخري | D53: Saudi Rock Wool Factory | E53: الرياض الثانية | F53: 0556000064 | G53: 0112650034 | H53: khalid@saudirockwool.com | I53: 0112650073 | J53: مفتوح | K53: صناعي | L53: منتج | M53: 2017-04-07 | N53: 2018-03-26 | O53: 28246 | P53: 2 | Q53: =VLOOKUP(B53,[1]Sheet1!$A$1:$F$6212,6,0) -> #N/A
A54: 1010076996 | B54: 20997 | C54: مصنع الغذائية لتجميد الخضراوات | D54: Al-Ghezaya Ready Foods Factory - Maakolat | E54: الرياض الثانية | F54: 0538739026 | G54: 0112650909 | H54: ali_alsalem@wafrah.com | I54: 0112650606 | J54: مفتوح | K54: صناعي | L54: منتج | M54: 1996-06-19 | N54: 2020-09-19 | O54: 27661 | P54: 33012 | Q54: =VLOOKUP(B54,[1]Sheet1!$A$1:$F$6212,6,0) -> #N/A
A55: 1010000734 | B55: 20151 | C55: مصانع شركة الجميح لتعبئة المرطبات | D55: Al-Jomaih Co. Factories for Refreshment Packaging | E55: الرياض الثانية | F55: 0504112768 | G55: 0112651746 | H55: headoffice@aljomaih.com.sa | I55: 0112651696 | J55: مفتوح | K55: صناعي | L55: منتج | M55: 2014-05-17 | N55: 2030-11-13 | O55: 26790 | P55: 2 | Q55: =VLOOKUP(B55,[1]Sheet1!$A$1:$F$6212,6,0) -> #N/A
A56: 1010102318 | B56: 20158 | C56: الشركة الوطنية لصناعة البطاريات | D56: National Batteries Manufacturing Company | E56: الرياض الثانية | F56: 0500121253 | G56: 0112650019 | H56: sami@battariat.com | I56: 0112650057 | J56: مفتوح | K56: صناعي | L56: منتج | M56: 1994-08-03 | N56: 2018-11-03 | O56: 25000 | P56: 33910 | Q56: =VLOOKUP(B56,[1]Sheet1!$A$1:$F$6212,6,0) -> #N/A
A57: 1010021424 | B57: 807820 | C57: شركة سولزر السعودي للمضخات المحدودة | D57: NULL | E57: الرياض الثانية | F57: 0500544001 | G57: 0112652123 | H57: fahad.subaie@sulzer.com | I57: 0112651071 | J57: مفتوح | K57: صناعي | L57: منتج | M57: 2016-12-06 | N57: 2036-05-02 | O57: 24821 | P57: 28949 | Q57: =VLOOKUP(B57,[1]Sheet1!$A$1:$F$6212,6,0) -> #N/A
A58: 1010171861 | B58: 20650 | C58: الشركة المتحدة للمحولات الكهربائية | D58: United Transformers Electric Co. (UTEC) | E58: الرياض الثانية | F58: 0504816569 | G58: 0114984590 | H58: info@utec.com.sa | I58: 0114983831 | J58: مفتوح | K58: صناعي | L58: منتج | M58: 2003-05-16 | N58: 2027-08-16 | O58: 24500 | P58: 37214 | Q58: =VLOOKUP(B58,[1]Sheet1!$A$1:$F$6212,6,0) -> #N/A
A59: 1010046436 | B59: 800394 | C59: شركة العبيكان للطباعة والنشر | D59: Obeikan Packaging Factory | E59: الرياض الثانية | F59: 0541244376 | G59: 0112651144 | H59: zayed@obeikan.com.sa | I59: 0112650785 | J59: مفتوح | K59: صناعي | L59: منتج | M59: 2009-10-15 | N59: 2019-06-28 | O59: 24450 | P59: 2 | Q59: =VLOOKUP(B59,[1]Sheet1!$A$1:$F$6212,6,0) -> #N/A
A60: 1010066206 | B60: 802701 | C60: مصنع ناردين للإنارة | D60: Nardin Lighting Factory | E60: الرياض الثانية | F60: 0555809749 | G60: 0112652144 | H60: abdullah.lami@philips.com | I60: 0112652194 | J60: مفتوح | K60: صناعي | L60: منتج | M60: 2011-05-20 | N60: 2030-10-14 | O60: 24400 | P60: 31945 | Q60: =VLOOKUP(B60,[1]Sheet1!$A$1:$F$6212,6,0) -> #N/A
A61: 1010149731 | B61: 803821 | C61: شركة اتحاد الخليج للأغذية | D61: Gulf Union Foods Company | E61: الرياض الثانية | F61: 0554200580 | G61: 0112652855 | H61: abrahim@gwf-union.com | I61: 0112652779 | J61: مفتوح | K61: صناعي | L61: منتج | M61: 2013-03-17 | N61: 2018-01-21 | O61: 22454 | P61: 1/1/53 0:00 | Q61: =VLOOKUP(B61,[1]Sheet1!$A$1:$F$6212,6,0) -> #N/A
A62: 1010083670 | B62: 20673 | C62: المصنع السعودي للشماغ | D62: Saudi Shemagh Factory | E62: الرياض الثانية | F62: 0509996786 | G62: 0114980558 | H62: alajlan2000@hotmail.com | I62: 0114980570 | J62: مفتوح | K62: صناعي | L62: منتج | M62: 1998-03-22 | N62: 2022-06-22 | O62: 22000 | P62: 2 | Q62: =VLOOKUP(B62,[1]Sheet1!$A$1:$F$6212,6,0) -> #N/A
A63: 1010437255 | B63: 806703 | C63: مصنع كي أس بي العربية للمضخات المحدودة | D63: KSB Pumps Arabia Company | E63: الرياض الثانية | F63: 0566061867 | G63: 0112652081 | H63: badr-alobaid@ksbarabia.com | I63: 0112651972 | J63: مفتوح | K63: صناعي | L63: منتج | M63: 2015-11-30 | N63: 2020-10-04 | O63: 20961 | P63: 42250 | Q63: =VLOOKUP(B63,[1]Sheet1!$A$1:$F$6212,6,0) -> #N/A
A64: 1010195874 | B64: 806739 | C64: شركة هينكل العربية لمنتجات العناية المنزلية والشخصية | D64: Henkel Arabia for Home and Personal Care Products Co.Ltd | E64: الرياض الثانية | F64: 0505266433 | G64: 0112652655 | H64: daifullah.alsalmi@henkel.com | I64: 0112651856 | J64: مفتوح | K64: صناعي | L64: منتج | M64: 2015-11-30 | N64: 2020-10-04 | O64: 20185 | P64: 38070 | Q64: =VLOOKUP(B64,[1]Sheet1!$A$1:$F$6212,6,0) -> #N/A
A65: 1010131637 | B65: 20751 | C65: شركة المنتجات الطبية والتجميلية - الرياض فارما | D65: Medical & Cosmetic Products Company-Riyadh Pharma | E65: الرياض الثانية | F65: 0540639921 | G65: 0112650111 | H65: mshreah@riyadhpharma.com | I65: 0112650505 | J65: مفتوح | K65: صناعي | L65: منتج | M65: 1995-08-23 | N65: 2019-11-23 | O65: 20000 | P65: 34685 | Q65: =VLOOKUP(B65,[1]Sheet1!$A$1:$F$6212,6,0) -> #N/A
A66: 1010126846 | B66: 807024 | C66: مصنع العبوات البلاستيكية فرع شركة بلاستيك السعودية لأنظمة التغليف | D66: NULL | E66: الرياض الثانية | F66: 0506230374 | G66: 0114985950 | H66: aelgazzar@takweenai.com | I66: 0114985666 | J66: مفتوح | K66: صناعي | L66: منتج | M66: 2016-05-23 | N66: 2035-10-16 | O66: 19977 | P66: 34542 | Q66: =VLOOKUP(B66,[1]Sheet1!$A$1:$F$6212,6,0) -> #N/A
A67: 1010037702 | B67: 808507 | C67: مصنع شركة هرفى للكيك والمعجنات | D67: NULL | E67: الرياض الثانية | F67: 0561444410 | G67: 0114509767 | H67: elkarawi@herfy.com | I67: 0114501824 | J67: مفتوح | K67: صناعي | L67: منتج | M67: 2017-05-31 | N67: 2031-12-18 | O67: 19765 | P67: 29655 | Q67: =VLOOKUP(B67,[1]Sheet1!$A$1:$F$6212,6,0) -> #N/A
A68: - | B68: 808945 | C68: مصنع الفنار للأنظمه الكهربائية | D68: Al-Hanaya Restaurant & Supermarket | E68: الرياض الثانية | F68: 0505400194 | G68: 0112651114 | H68: ahmad.almadani@alfanar.com | I68: - | J68: مفتوح | K68: صناعي | L68: منتج | M68: 2017-05-30 | N68: 2031-12-17 | O68: 15418 | P68: 2 | Q68: =VLOOKUP(B68,[1]Sheet1!$A$1:$F$6212,6,0) -> #N/A
A69: 1010064609 | B69: 808504 | C69: شركة مصانع شنايدر الكيترك العربية السعودية المحدودة | D69: NULL | E69: الرياض الثانية | F69: 0505276127 | G69: 0112651515 | H69: khalid.mubarak@sa.schneider-electric.com | I69: 0112651880 | J69: مفتوح | K69: صناعي | L69: منتج | M69: 2017-05-30 | N69: 2032-12-06 | O69: 13459 | P69: 31780 | Q69: =VLOOKUP(B69,[1]Sheet1!$A$1:$F$6212,6,0) -> #N/A
A70: 1010221531 | B70: 280152 | C70: شركة لازوردي للمجوهرات | D70: NULL | E70: الرياض الثانية | F70: 0505464155 | G70: 0112651119 | H70: abdullah.obaid@lazurde.com | I70: 0112656060 | J70: مفتوح | K70: صناعي | L70: منتج | M70: 2007-06-16 | N70: 2031-09-18 | O70: 12400 | P70: 38920 | Q70: =VLOOKUP(B70,[1]Sheet1!$A$1:$F$6212,6,0) -> #N/A
A71: 1010074777 | B71: 20344 | C71: مصنع العمرانية للرخام والحجر | D71: NULL | E71: الرياض الثانية | F71: 0563633989 | G71: 0112651937 | H71: almudayfer_group@alomraniah.com | I71: 0112654226 | J71: مفتوح | K71: صناعي | L71: منتج | M71: 2009-04-25 | N71: 2019-01-04 | O71: 11000 | P71: 2 | Q71: =VLOOKUP(B71,[1]Sheet1!$A$1:$F$6212,6,0) -> #N/A
A72: 1010138813 | B72: 800903 | C72: شركة الفنار للقوالب | D72: Al-Fanar Molds Co. | E72: الرياض الثانية | F72: 0506026945 | G72: 0114982521 | H72: suwaida@alfanar.com | I72: 0114981108 | J72: مفتوح | K72: صناعي | L72: منتج | M72: 2010-10-09 | N72: 2030-03-05 | O72: 9750 | P72: 35007 | Q72: =VLOOKUP(B72,[1]Sheet1!$A$1:$F$6212,6,0) -> #N/A
A73: 1010037702 | B73: 20994 | C73: شركة هرفي لإنتاج اللحوم | D73: NULL | E73: الرياض الثانية | F73: 0561444410 | G73: 0114509767 | H73: elkarawi@herfy.com | I73: 0114501824 | J73: مفتوح | K73: صناعي | L73: منتج | M73: 1998-12-12 | N73: 2023-03-14 | O73: 9472 | P73: 2 | Q73: =VLOOKUP(B73,[1]Sheet1!$A$1:$F$6212,6,0) -> #N/A
... A75: 1010071694 | B75: 804515 | C75: الشركة العربية للطاقة الشمسية | D75: NULL | E75: الرياض الثانية | F75: 0505206163 | G75: 0112651573 | H75: a.alghamdi@olayangroup.com | I75: 0112651556 | J75: مفتوح | K75: صناعي | L75: منتج | M75: 2013-11-01 | N75: 2033-03-27 | O75: 7500 | P75: 2 | Q75: =VLOOKUP(B75,[1]Sheet1!$A$1:$F$6212,6,0) -> #N/A

Sheet تقرير التوافق
B1: تقرير التوافق الخاص بـ قائمة بيانات التواصل للمصـانع.xls
B2: التشغيل على 14/12/2017 08:25
B4: لا تعتمد إصدارات Excel السابقة الميزات التالية الموجودة في هذا المصنف. قد يتم فقدان هذه الميزات أو تخفيضها عند فتح هذا المصنف في إصدار سابق من Excel أو حفظه بتنسيق ملف سابق.
B6: فقد بسيط في الدقة | E6: # مرات التواجد | F6: الإصدار
B8: بعض الصيغ الموجودة في هذا المصنف مرتبطة بمصنفات أخرى مغلقة. عند إعادة حساب هذه الصيغ في الإصدارات السابقة من Excel دون فتح المصنفات المرتبطة، سيتعذر إرجاع أي أحرف تتجاوز حد 255 حرف. | E8: 500
E9: P2:P501!"Sheet1" | F9: Excel 97-2003
